Workbook

Sheet 2026 Points
A1: Team | B1: Rank | C1: Null | D1: Points
A2: Nick | B2: =rank(D2,D$2:D$10) -> 6 | C2: =countif(E2:L2, 0) -> 2 | D2: =sum(E2:L2) -> 1123 | E2: =IFERROR(VLOOKUP(E13,'2026 Ranking'!$D:$F,3,0),0) -> 232 | F2: =IFERROR(VLOOKUP(F13,'2026 Ranking'!$D:$F,3,0),0) -> 388 | G2: =IFERROR(VLOOKUP(G13,'2026 Ranking'!$D:$F,3,0),0) -> 328 | H2: =IFERROR(VLOOKUP(H13,'2026 Ranking'!$D:$F,3,0),0) -> 30 | I2: =IFERROR(VLOOKUP(I13,'2026 Ranking'!$D:$F,3,0),0) -> 65 | J2: =IFERROR(VLOOKUP(J13,'2026 Ranking'!$D:$F,3,0),0) -> 0 | K2: =IFERROR(VLOOKUP(K13,'2026 Ranking'!$D:$F,3,0),0) -> 0 | L2: =IFERROR(VLOOKUP(L13,'2026 Ranking'!$D:$F,3,0),0) -> 80
A3: Tim | B3: =rank(D3,D$2:D$10) -> 7 | C3: =countif(E3:L3, 0) -> 4 | D3: =sum(E3:L3) -> 521 | E3: =IFERROR(VLOOKUP(E14,'2026 Ranking'!$D:$F,3,0),0) -> 38 | F3: =IFERROR(VLOOKUP(F14,'2026 Ranking'!$D:$F,3,0),0) -> 0 | G3: =IFERROR(VLOOKUP(G14,'2026 Ranking'!$D:$F,3,0),0) -> 0 | H3: =IFERROR(VLOOKUP(H14,'2026 Ranking'!$D:$F,3,0),0) -> 0 | I3: =IFERROR(VLOOKUP(I14,'2026 Ranking'!$D:$F,3,0),0) -> 13 | J3: =IFERROR(VLOOKUP(J14,'2026 Ranking'!$D:$F,3,0),0) -> 454 | K3: =IFERROR(VLOOKUP(K14,'2026 Ranking'!$D:$F,3,0),0) -> 0 | L3: =IFERROR(VLOOKUP(L14,'2026 Ranking'!$D:$F,3,0),0) -> 16
A4: Cameron | B4: =rank(D4,D$2:D$10) -> 4 | C4: =countif(E4:L4, 0) -> 0 | D4: =sum(E4:L4) -> 1285 | E4: =IFERROR(VLOOKUP(E15,'2026 Ranking'!$D:$F,3,0),0) -> 141 | F4: =IFERROR(VLOOKUP(F15,'2026 Ranking'!$D:$F,3,0),0) -> 411 | G4: =IFERROR(VLOOKUP(G15,'2026 Ranking'!$D:$F,3,0),0) -> 248 | H4: =IFERROR(VLOOKUP(H15,'2026 Ranking'!$D:$F,3,0),0) -> 125 | I4: =IFERROR(VLOOKUP(I15,'2026 Ranking'!$D:$F,3,0),0) -> 130 | J4: =IFERROR(VLOOKUP(J15,'2026 Ranking'!$D:$F,3,0),0) -> 119 | K4: =IFERROR(VLOOKUP(K15,'2026 Ranking'!$D:$F,3,0),0) -> 87 | L4: =IFERROR(VLOOKUP(L15,'2026 Ranking'!$D:$F,3,0),0) -> 24
A5: Campbell | B5: =rank(D5,D$2:D$10) -> 3 | C5: =countif(E5:L5, 0) -> 0 | D5: =sum(E5:L5) -> 1426 | E5: =IFERROR(VLOOKUP(E16,'2026 Ranking'!$D:$F,3,0),0) -> 59 | F5: =IFERROR(VLOOKUP(F16,'2026 Ranking'!$D:$F,3,0),0) -> 90 | G5: =IFERROR(VLOOKUP(G16,'2026 Ranking'!$D:$F,3,0),0) -> 302 | H5: =IFERROR(VLOOKUP(H16,'2026 Ranking'!$D:$F,3,0),0) -> 523 | I5: =IFERROR(VLOOKUP(I16,'2026 Ranking'!$D:$F,3,0),0) -> 9 | J5: =IFERROR(VLOOKUP(J16,'2026 Ranking'!$D:$F,3,0),0) -> 335 | K5: =IFERROR(VLOOKUP(K16,'2026 Ranking'!$D:$F,3,0),0) -> 98 | L5: =IFERROR(VLOOKUP(L16,'2026 Ranking'!$D:$F,3,0),0) -> 10
A6: Dave | B6: =rank(D6,D$2:D$10) -> 1 | C6: =countif(E6:L6, 0) -> 1 | D6: =sum(E6:L6) -> 2004 | E6: =IFERROR(VLOOKUP(E17,'2026 Ranking'!$D:$F,3,0),0) -> 261 | F6: =IFERROR(VLOOKUP(F17,'2026 Ranking'!$D:$F,3,0),0) -> 134 | G6: =IFERROR(VLOOKUP(G17,'2026 Ranking'!$D:$F,3,0),0) -> 148 | H6: =IFERROR(VLOOKUP(H17,'2026 Ranking'!$D:$F,3,0),0) -> 852 | I6: =IFERROR(VLOOKUP(I17,'2026 Ranking'!$D:$F,3,0),0) -> 335 | J6: =IFERROR(VLOOKUP(J17,'2026 Ranking'!$D:$F,3,0),0) -> 0 | K6: =IFERROR(VLOOKUP(K17,'2026 Ranking'!$D:$F,3,0),0) -> 204 | L6: =IFERROR(VLOOKUP(L17,'2026 Ranking'!$D:$F,3,0),0) -> 70
A7: Mike | B7: =rank(D7,D$2:D$10) -> 5 | C7: =countif(E7:L7, 0) -> 1 | D7: =sum(E7:L7) -> 1208 | E7: =IFERROR(VLOOKUP(E18,'2026 Ranking'!$D:$F,3,0),0) -> 87 | F7: =IFERROR(VLOOKUP(F18,'2026 Ranking'!$D:$F,3,0),0) -> 45 | G7: =IFERROR(VLOOKUP(G18,'2026 Ranking'!$D:$F,3,0),0) -> 171 | H7: =IFERROR(VLOOKUP(H18,'2026 Ranking'!$D:$F,3,0),0) -> 330 | I7: =IFERROR(VLOOKUP(I18,'2026 Ranking'!$D:$F,3,0),0) -> 33 | J7: =IFERROR(VLOOKUP(J18,'2026 Ranking'!$D:$F,3,0),0) -> 0 | K7: =IFERROR(VLOOKUP(K18,'2026 Ranking'!$D:$F,3,0),0) -> 434 | L7: =IFERROR(VLOOKUP(L18,'2026 Ranking'!$D:$F,3,0),0) -> 108
A8: Andy | B8: =rank(D8,D$2:D$10) -> 2 | C8: =countif(E8:L8, 0) -> 1 | D8: =sum(E8:L8) -> 1959 | E8: =IFERROR(VLOOKUP(E19,'2026 Ranking'!$D:$F,3,0),0) -> 520 | F8: =IFERROR(VLOOKUP(F19,'2026 Ranking'!$D:$F,3,0),0) -> 360 | G8: =IFERROR(VLOOKUP(G19,'2026 Ranking'!$D:$F,3,0),0) -> 116 | H8: =IFERROR(VLOOKUP(H19,'2026 Ranking'!$D:$F,3,0),0) -> 237 | I8: =IFERROR(VLOOKUP(I19,'2026 Ranking'!$D:$F,3,0),0) -> 386 | J8: =IFERROR(VLOOKUP(J19,'2026 Ranking'!$D:$F,3,0),0) -> 84 | K8: =IFERROR(VLOOKUP(K19,'2026 Ranking'!$D:$F,3,0),0) -> 256 | L8: =IFERROR(VLOOKUP(L19,'2026 Ranking'!$D:$F,3,0),0) -> 0
A9: Joe | B9: =rank(D9,D$2:D$10) -> 9 | C9: =countif(E9:L9, 0) -> 2 | D9: =sum(E9:L9) -> 397 | E9: =IFERROR(VLOOKUP(E20,'2026 Ranking'!$D:$F,3,0),0) -> 0 | F9: =IFERROR(VLOOKUP(F20,'2026 Ranking'!$D:$F,3,0),0) -> 0 | G9: =IFERROR(VLOOKUP(G20,'2026 Ranking'!$D:$F,3,0),0) -> 5 | H9: =IFERROR(VLOOKUP(H20,'2026 Ranking'!$D:$F,3,0),0) -> 36 | I9: =IFERROR(VLOOKUP(I20,'2026 Ranking'!$D:$F,3,0),0) -> 58 | J9: =IFERROR(VLOOKUP(J20,'2026 Ranking'!$D:$F,3,0),0) -> 52 | K9: =IFERROR(VLOOKUP(K20,'2026 Ranking'!$D:$F,3,0),0) -> 21 | L9: =IFERROR(VLOOKUP(L20,'2026 Ranking'!$D:$F,3,0),0) -> 225
A10: Geminiani's Hipsters | B10: =rank(D10,D$2:D$10) -> 8 | C10: =countif(E10:L10, 0) -> 2 | D10: =sum(E10:L10) -> 422 | E10: =IFERROR(VLOOKUP(E21,'2026 Ranking'!$D:$F,3,0),0) -> 0 | F10: =IFERROR(VLOOKUP(F21,'2026 Ranking'!$D:$F,3,0),0) -> 100 | G10: =IFERROR(VLOOKUP(G21,'2026 Ranking'!$D:$F,3,0),0) -> 185 | H10: =IFERROR(VLOOKUP(H21,'2026 Ranking'!$D:$F,3,0),0) -> 53 | I10: =IFERROR(VLOOKUP(I21,'2026 Ranking'!$D:$F,3,0),0) -> 0 | J10: =IFERROR(VLOOKUP(J21,'2026 Ranking'!$D:$F,3,0),0) -> 40 | K10: =IFERROR(VLOOKUP(K21,'2026 Ranking'!$D:$F,3,0),0) -> 21 | L10: =IFERROR(VLOOKUP(L21,'2026 Ranking'!$D:$F,3,0),0) -> 23
D12: Manager | E12: 1 | F12: 2 | G12: 3 | H12: 4 | I12: 5 | J12: 6 | K12: 7 | L12: 8
A13: =D13 -> Nick | D13: Nick | E13: AYUSO Juan | F13: VINGEGAARD Jonas | G13: VINE Jay | H13: NARVÁEZ Jhonatan | I13: TARLING Joshua | J13: WILLIAMS Stephen | K13: FORTUNATO Lorenzo | L13: O'CONNOR Ben
A14: =D14 -> Tim | D14: Tim | E14: PHILIPSEN Jasper | F14: KOOIJ Olav | G14: MERLIER Tim | H14: PEDERSEN Mads | I14: STRONG Corbin | J14: CHRISTEN Jan | K14: BLACKMORE Joseph | L14: HINDLEY Jai
A15: =D15 -> Cameron | D15: Cameron | E15: HEALY Ben | F15: JORGENSON Matteo | G15: PIDCOCK Thomas | H15: ONLEY Oscar | I15: ROGLIČ Primož | J15: ARENSMAN Thymen | K15: GANNA Filippo | L15: ALAPHILIPPE Julian
A16: =D16 -> Campbell | D16: Campbell | E16: VAN AERT Wout | F16: LIPOWITZ Florian | G16: MILAN Jonathan | H16: SCARONI Christian | I16: WRIGHT Fred | J16: PELLIZZARI Giulio | K16: STORER Michael | L16: DEL GROSSO Tibor
A17: =D17 -> Dave | D17: Dave | E17: VAUQUELIN Kévin | F17: CICCONE Giulio | G17: GALL Felix | H17: DEL TORO Isaac | I17: MARTINEZ Lenny | J17: POWLESS Neilson | K17: GIRMAY Biniam | L17: JEANNIÈRE Emilien
A18: =D18 -> Mike | D18: Mike | E18: DE LIE Arnaud | F18: SKJELMOSE Mattias | G18: MAGNIER Paul | H18: VAN DER POEL Mathieu | I18: CARAPAZ Richard | J18: NYS Thibau | K18: SEIXAS Paul | L18: GEE-WEST Derek
A19: =D19 -> Andy | D19: Andy | E19: EVENEPOEL Remco | F19: BRENNAN Matthew | G19: MCNULTY Brandon | H19: ALMEIDA João | I19: GRÉGOIRE Romain | J19: MOSCHETTI Matteo | K19: YATES Adam | L19: UIJTDEBROEKS Cian
A20: =D20 -> Joe | D20: Joe | E20: PIDCOCK Joseph | F20: CRAPS Lars | G20: JAKOBSEN Fabio | H20: SÖDERQVIST Jakob | I20: WIDAR Jarno | J20: HIRSCHI Marc | K20: WANG Gustav | L20: POGAČAR Tadej
A21: =D21 -> Geminiani's Hipsters | D21: Geminiani's Hipsters | E21: BISIAUX Léo | F21: NORDHAGEN Jørgen | G21: LAMPERTI Luke | H21: AUGUST Andrew | I21: AGOSTINACCHIO Filippo | J21: FINN Lorenzo | K21: TULETT Ben | L21: ABRAHAMSEN Jonas

Sheet 2026 Ranking
A1: Rank | B1: Prev. Rank | C1: Rank Diff. | D1: Rider | E1: Team | F1: Points | I1: Manager
A2: 1 | B2: 2 | C2: ▲1 | D2: DEL TORO Isaac | E2: UAE Team Emirates - XRG | F2: 852 | I2: {=INDEX('2026 Points'!$D$13:$D$21,MATCH(1,MMULT(--('2026 Points'!$E$13:$L$21=D2),TRANSPOSE(COLUMN('2026 Points'!$E$13:$L$21)^0)),0))} -> Dave
A3: 2 | B3: 65 | C3: ▲63 | D3: SCHMID Mauro | E3: Team Jayco AlUla | F3: 540 | I3: {=INDEX('2026 Points'!$D$13:$D$21,MATCH(1,MMULT(--('2026 Points'!$E$13:$L$21=D3),TRANSPOSE(COLUMN('2026 Points'!$E$13:$L$21)^0)),0))} -> #N/A
A4: 3 | B4: 40 | C4: ▲37 | D4: ANDRESEN Tobias Lund | E4: Decathlon CMA CGM Team | F4: 525 | I4: {=INDEX('2026 Points'!$D$13:$D$21,MATCH(1,MMULT(--('2026 Points'!$E$13:$L$21=D4),TRANSPOSE(COLUMN('2026 Points'!$E$13:$L$21)^0)),0))} -> #N/A
A5: 4 | B5: 14 | C5: ▲10 | D5: SCARONI Christian | E5: XDS Astana Team | F5: 523 | I5: {=INDEX('2026 Points'!$D$13:$D$21,MATCH(1,MMULT(--('2026 Points'!$E$13:$L$21=D5),TRANSPOSE(COLUMN('2026 Points'!$E$13:$L$21)^0)),0))} -> Campbell
A6: 5 | B6: 6 | C6: ▲1 | D6: EVENEPOEL Remco | E6: Red Bull - BORA - hansgrohe | F6: 520 | I6: {=INDEX('2026 Points'!$D$13:$D$21,MATCH(1,MMULT(--('2026 Points'!$E$13:$L$21=D6),TRANSPOSE(COLUMN('2026 Points'!$E$13:$L$21)^0)),0))} -> Andy
A7: 6 | B7: 78 | C7: ▲72 | D7: TIBERI Antonio | E7: Bahrain - Victorious | F7: 465 | I7: {=INDEX('2026 Points'!$D$13:$D$21,MATCH(1,MMULT(--('2026 Points'!$E$13:$L$21=D7),TRANSPOSE(COLUMN('2026 Points'!$E$13:$L$21)^0)),0))} -> #N/A
A8: 7 | B8: 49 | C8: ▲42 | D8: CHRISTEN Jan | E8: UAE Team Emirates - XRG | F8: 454 | I8: {=INDEX('2026 Points'!$D$13:$D$21,MATCH(1,MMULT(--('2026 Points'!$E$13:$L$21=D8),TRANSPOSE(COLUMN('2026 Points'!$E$13:$L$21)^0)),0))} -> Tim
A9: 8 | B9: 99 | C9: ▲91 | D9: SEIXAS Paul | E9: Decathlon CMA CGM Team | F9: 434 | I9: {=INDEX('2026 Points'!$D$13:$D$21,MATCH(1,MMULT(--('2026 Points'!$E$13:$L$21=D9),TRANSPOSE(COLUMN('2026 Points'!$E$13:$L$21)^0)),0))} -> Mike
A10: 9 | B10: 26 | C10: ▲17 | D10: JORGENSON Matteo | E10: Team Visma | Lease a Bike | F10: 411 | I10: {=INDEX('2026 Points'!$D$13:$D$21,MATCH(1,MMULT(--('2026 Points'!$E$13:$L$21=D10),TRANSPOSE(COLUMN('2026 Points'!$E$13:$L$21)^0)),0))} -> Cameron
A11: 10 | B11: 3 | C11: ▼7 | D11: VINGEGAARD Jonas | E11: Team Visma | Lease a Bike | F11: 388 | I11: {=INDEX('2026 Points'!$D$13:$D$21,MATCH(1,MMULT(--('2026 Points'!$E$13:$L$21=D11),TRANSPOSE(COLUMN('2026 Points'!$E$13:$L$21)^0)),0))} -> Nick
A12: 11 | B12: 28 | C12: ▲17 | D12: GRÉGOIRE Romain | E12: Groupama - FDJ United | F12: 386 | I12: {=INDEX('2026 Points'!$D$13:$D$21,MATCH(1,MMULT(--('2026 Points'!$E$13:$L$21=D12),TRANSPOSE(COLUMN('2026 Points'!$E$13:$L$21)^0)),0))} -> Andy
A13: 12 | B13: 89 | C13: ▲77 | D13: MORGADO António | E13: UAE Team Emirates - XRG | F13: 380 | I13: {=INDEX('2026 Points'!$D$13:$D$21,MATCH(1,MMULT(--('2026 Points'!$E$13:$L$21=D13),TRANSPOSE(COLUMN('2026 Points'!$E$13:$L$21)^0)),0))} -> #N/A
... A144: 143 | B144: 548 | C144: ▲405 | D144: GUALDI Simone | E144: Lotto Intermarché | F144: 77 | I144: {=INDEX('2026 Points'!$D$13:$D$21,MATCH(1,MMULT(--('2026 Points'!$E$13:$L$21=D144),TRANSPOSE(COLUMN('2026 Points'!$E$13:$L$21)^0)),0))} -> #N/A
A145: 144 | C145: ▲new | D145: POULARD Athit | E145: Roojai Insurance Winspace | F145: 76 | I145: {=INDEX('2026 Points'!$D$13:$D$21,MATCH(1,MMULT(--('2026 Points'!$E$13:$L$21=D145),TRANSPOSE(COLUMN('2026 Points'!$E$13:$L$21)^0)),0))} -> #N/A
A146: 145 | B146: 488 | C146: ▲343 | D146: POLITT Nils | E146: UAE Team Emirates - XRG | F146: 76 | I146: {=INDEX('2026 Points'!$D$13:$D$21,MATCH(1,MMULT(--('2026 Points'!$E$13:$L$21=D146),TRANSPOSE(COLUMN('2026 Points'!$E$13:$L$21)^0)),0))} -> #N/A
A147: 146 | B147: 243 | C147: ▲97 | D147: HARPER Chris | E147: Pinarello Q36.5 Pro Cycling Team | F147: 75 | I147: {=INDEX('2026 Points'!$D$13:$D$21,MATCH(1,MMULT(--('2026 Points'!$E$13:$L$21=D147),TRANSPOSE(COLUMN('2026 Points'!$E$13:$L$21)^0)),0))} -> #N/A
A148: 147 | B148: 434 | C148: ▲287 | D148: HATHERLY Alan | E148: Team Jayco AlUla | F148: 75 | I148: {=INDEX('2026 Points'!$D$13:$D$21,MATCH(1,MMULT(--('2026 Points'!$E$13:$L$21=D148),TRANSPOSE(COLUMN('2026 Points'!$E$13:$L$21)^0)),0))} -> #N/A
A149: 148 | B149: 115 | C149: ▼33 | D149: DOUBLE Paul | E149: Team Jayco AlUla | F149: 74 | I149: {=INDEX('2026 Points'!$D$13:$D$21,MATCH(1,MMULT(--('2026 Points'!$E$13:$L$21=D149),TRANSPOSE(COLUMN('2026 Points'!$E$13:$L$21)^0)),0))} -> #N/A
A150: 149 | B150: 430 | C150: ▲281 | D150: KOERDT Bjorn | E150: Team Picnic PostNL | F150: 73 | I150: {=INDEX('2026 Points'!$D$13:$D$21,MATCH(1,MMULT(--('2026 Points'!$E$13:$L$21=D150),TRANSPOSE(COLUMN('2026 Points'!$E$13:$L$21)^0)),0))} -> #N/A
A151: 150 | B151: 79 | C151: ▼71 | D151: GATE Aaron | E151: XDS Astana Team | F151: 72 | I151: {=INDEX('2026 Points'!$D$13:$D$21,MATCH(1,MMULT(--('2026 Points'!$E$13:$L$21=D151),TRANSPOSE(COLUMN('2026 Points'!$E$13:$L$21)^0)),0))} -> #N/A
A152: 151 | B152: 328 | C152: ▲177 | D152: ZANONCELLO Enrico | E152: Bardiani CSF 7 Saber | F152: 72 | I152: {=INDEX('2026 Points'!$D$13:$D$21,MATCH(1,MMULT(--('2026 Points'!$E$13:$L$21=D152),TRANSPOSE(COLUMN('2026 Points'!$E$13:$L$21)^0)),0))} -> #N/A
A153: 152 | B153: 1023 | C153: ▲871 | D153: LAU Wan Yau Vincent | E153: Roojai Insurance Winspace | F153: 72 | I153: {=INDEX('2026 Points'!$D$13:$D$21,MATCH(1,MMULT(--('2026 Points'!$E$13:$L$21=D153),TRANSPOSE(COLUMN('2026 Points'!$E$13:$L$21)^0)),0))} -> #N/A
A154: 153 | B154: 185 | C154: ▲32 | D154: PLUIMERS Rick | E154: Tudor Pro Cycling Team | F154: 71 | I154: {=INDEX('2026 Points'!$D$13:$D$21,MATCH(1,MMULT(--('2026 Points'!$E$13:$L$21=D154),TRANSPOSE(COLUMN('2026 Points'!$E$13:$L$21)^0)),0))} -> #N/A
A155: 154 | B155: 108 | C155: ▼46 | D155: TEUNISSEN Mike | E155: XDS Astana Team | F155: 71 | I155: {=INDEX('2026 Points'!$D$13:$D$21,MATCH(1,MMULT(--('2026 Points'!$E$13:$L$21=D155),TRANSPOSE(COLUMN('2026 Points'!$E$13:$L$21)^0)),0))} -> #N/A
A156: 155 | B156: 507 | C156: ▲352 | D156: VERRE Alessandro | E156: MBH Bank CSB Telecom Fort | F156: 71 | I156: {=INDEX('2026 Points'!$D$13:$D$21,MATCH(1,MMULT(--('2026 Points'!$E$13:$L$21=D156),TRANSPOSE(COLUMN('2026 Points'!$E$13:$L$21)^0)),0))} -> #N/A
A157: 156 | C157: ▲new | D157: BEISEMBAY Mansur | E157: XDS Astana Development Team | F157: 71 | I157: {=INDEX('2026 Points'!$D$13:$D$21,MATCH(1,MMULT(--('2026 Points'!$E$13:$L$21=D157),TRANSPOSE(COLUMN('2026 Points'!$E$13:$L$21)^0)),0))} -> #N/A
A158: 157 | B158: 163 | C158: ▲6 | D158: HERMANS Quinten | E158: Pinarello Q36.5 Pro Cycling Team | F158: 71 | I158: {=INDEX('2026 Points'!$D$13:$D$21,MATCH(1,MMULT(--('2026 Points'!$E$13:$L$21=D158),TRANSPOSE(COLUMN('2026 Points'!$E$13:$L$21)^0)),0))} -> #N/A
A159: 158 | B159: 149 | C159: ▼9 | D159: CASTRILLO Pablo | E159: Movistar Team | F159: 70 | I159: {=INDEX('2026 Points'!$D$13:$D$21,MATCH(1,MMULT(--('2026 Points'!$E$13:$L$21=D159),TRANSPOSE(COLUMN('2026 Points'!$E$13:$L$21)^0)),0))} -> #N/A
A160: 159 | B160: 646 | C160: ▲487 | D160: GUDMESTAD Tord | E160: Decathlon CMA CGM Team | F160: 70 | I160: {=INDEX('2026 Points'!$D$13:$D$21,MATCH(1,MMULT(--('2026 Points'!$E$13:$L$21=D160),TRANSPOSE(COLUMN('2026 Points'!$E$13:$L$21)^0)),0))} -> #N/A
A161: 160 | B161: 37 | C161: ▼123 | D161: JEANNIÈRE Emilien | E161: TotalEnergies | F161: 70 | I161: {=INDEX('2026 Points'!$D$13:$D$21,MATCH(1,MMULT(--('2026 Points'!$E$13:$L$21=D161),TRANSPOSE(COLUMN('2026 Points'!$E$13:$L$21)^0)),0))} -> Dave
A162: 161 | B162: 562 | C162: ▲401 | D162: MUNTON Byron | E162: Modern Adventure Pro Cycling | F162: 70 | I162: {=INDEX('2026 Points'!$D$13:$D$21,MATCH(1,MMULT(--('2026 Points'!$E$13:$L$21=D162),TRANSPOSE(COLUMN('2026 Points'!$E$13:$L$21)^0)),0))} -> #N/A
A163: 162 | B163: 498 | C163: ▲336 | D163: GOVEKAR Matevž | E163: Bahrain - Victorious | F163: 70 | I163: {=INDEX('2026 Points'!$D$13:$D$21,MATCH(1,MMULT(--('2026 Points'!$E$13:$L$21=D163),TRANSPOSE(COLUMN('2026 Points'!$E$13:$L$21)^0)),0))} -> #N/A
A164: 163 | B164: 635 | C164: ▲472 | D164: BERWICK Sebastian | E164: Caja Rural - Seguros RGA | F164: 69 | I164: {=INDEX('2026 Points'!$D$13:$D$21,MATCH(1,MMULT(--('2026 Points'!$E$13:$L$21=D164),TRANSPOSE(COLUMN('2026 Points'!$E$13:$L$21)^0)),0))} -> #N/A
A165: 164 | B165: 71 | C165: ▼93 | D165: VAN WILDER Ilan | E165: Soudal Quick-Step | F165: 69 | I165: {=INDEX('2026 Points'!$D$13:$D$21,MATCH(1,MMULT(--('2026 Points'!$E$13:$L$21=D165),TRANSPOSE(COLUMN('2026 Points'!$E$13:$L$21)^0)),0))} -> #N/A
A166: 165 | B166: 207 | C166: ▲42 | D166: MIQUEL Pau | E166: Bahrain - Victorious | F166: 68 | I166: {=INDEX('2026 Points'!$D$13:$D$21,MATCH(1,MMULT(--('2026 Points'!$E$13:$L$21=D166),TRANSPOSE(COLUMN('2026 Points'!$E$13:$L$21)^0)),0))} -> #N/A
A167: 166 | B167: 704 | C167: ▲538 | D167: GLIVAR Gal | E167: Alpecin-Premier Tech | F167: 68 | I167: {=INDEX('2026 Points'!$D$13:$D$21,MATCH(1,MMULT(--('2026 Points'!$E$13:$L$21=D167),TRANSPOSE(COLUMN('2026 Points'!$E$13:$L$21)^0)),0))} -> #N/A
A168: 167 | B168: 139 | C168: ▼28 | D168: TURNER Ben | E168: INEOS Grenadiers | F168: 68 | I168: {=INDEX('2026 Points'!$D$13:$D$21,MATCH(1,MMULT(--('2026 Points'!$E$13:$L$21=D168),TRANSPOSE(COLUMN('2026 Points'!$E$13:$L$21)^0)),0))} -> #N/A
A169: 168 | B169: 1529 | C169: ▲1361 | D169: GRISEL Matys | E169: Lotto Intermarché | F169: 68 | I169: {=INDEX('2026 Points'!$D$13:$D$21,MATCH(1,MMULT(--('2026 Points'!$E$13:$L$21=D169),TRANSPOSE(COLUMN('2026 Points'!$E$13:$L$21)^0)),0))} -> #N/A
... A240: 239 | B240: 1891 | C240: ▲1652 | D240: MUÑOZ Hodei | E240: Soudal Quick-Step Devo Team | F240: 46 | I240: {=INDEX('2026 Points'!$D$13:$D$21,MATCH(1,MMULT(--('2026 Points'!$E$13:$L$21=D240),TRANSPOSE(COLUMN('2026 Points'!$E$13:$L$21)^0)),0))} -> #N/A
A241: 240 | C241: ▲new | D241: MAGAGNOTTI Alessio | E241: Red Bull - BORA - hansgrohe Rookies | F241: 46 | I241: {=INDEX('2026 Points'!$D$13:$D$21,MATCH(1,MMULT(--('2026 Points'!$E$13:$L$21=D241),TRANSPOSE(COLUMN('2026 Points'!$E$13:$L$21)^0)),0))} -> #N/A
A242: 241 | B242: 345 | C242: ▲104 | D242: LEMMEN Bart | E242: Team Visma | Lease a Bike | F242: 46 | I242: {=INDEX('2026 Points'!$D$13:$D$21,MATCH(1,MMULT(--('2026 Points'!$E$13:$L$21=D242),TRANSPOSE(COLUMN('2026 Points'!$E$13:$L$21)^0)),0))} -> #N/A
A243: 242 | B243: 114 | C243: ▼128 | D243: JOHANNESSEN Anders Halland | E243: Uno-X Mobility | F243: 46 | I243: {=INDEX('2026 Points'!$D$13:$D$21,MATCH(1,MMULT(--('2026 Points'!$E$13:$L$21=D243),TRANSPOSE(COLUMN('2026 Points'!$E$13:$L$21)^0)),0))} -> #N/A
A244: 243 | B244: 403 | C244: ▲160 | D244: BUDZIŃSKI Marcin | E244: MBH Bank CSB Telecom Fort | F244: 45 | I244: {=INDEX('2026 Points'!$D$13:$D$21,MATCH(1,MMULT(--('2026 Points'!$E$13:$L$21=D244),TRANSPOSE(COLUMN('2026 Points'!$E$13:$L$21)^0)),0))} -> #N/A
A245: 244 | B245: 718 | C245: ▲474 | D245: OOMEN Sam | E245: Lidl - Trek | F245: 45 | I245: {=INDEX('2026 Points'!$D$13:$D$21,MATCH(1,MMULT(--('2026 Points'!$E$13:$L$21=D245),TRANSPOSE(COLUMN('2026 Points'!$E$13:$L$21)^0)),0))} -> #N/A
A246: 245 | B246: 1044 | C246: ▲799 | D246: VEISTROFFER Baptiste | E246: Lotto Intermarché | F246: 45 | I246: {=INDEX('2026 Points'!$D$13:$D$21,MATCH(1,MMULT(--('2026 Points'!$E$13:$L$21=D246),TRANSPOSE(COLUMN('2026 Points'!$E$13:$L$21)^0)),0))} -> #N/A
A247: 246 | B247: 289 | C247: ▲43 | D247: ACKERMANN Pascal | E247: Team Jayco AlUla | F247: 45 | I247: {=INDEX('2026 Points'!$D$13:$D$21,MATCH(1,MMULT(--('2026 Points'!$E$13:$L$21=D247),TRANSPOSE(COLUMN('2026 Points'!$E$13:$L$21)^0)),0))} -> #N/A
A248: 247 | B248: 655 | C248: ▲408 | D248: MOSCON Gianni | E248: Red Bull - BORA - hansgrohe | F248: 45 | I248: {=INDEX('2026 Points'!$D$13:$D$21,MATCH(1,MMULT(--('2026 Points'!$E$13:$L$21=D248),TRANSPOSE(COLUMN('2026 Points'!$E$13:$L$21)^0)),0))} -> #N/A
A249: 248 | B249: 165 | C249: ▼83 | D249: LARSEN Niklas | E249: Unibet Rose Rockets | F249: 45 | I249: {=INDEX('2026 Points'!$D$13:$D$21,MATCH(1,MMULT(--('2026 Points'!$E$13:$L$21=D249),TRANSPOSE(COLUMN('2026 Points'!$E$13:$L$21)^0)),0))} -> #N/A
A250: 249 | B250: 126 | C250: ▼123 | D250: DUJARDIN Sandy | E250: TotalEnergies | F250: 45 | I250: {=INDEX('2026 Points'!$D$13:$D$21,MATCH(1,MMULT(--('2026 Points'!$E$13:$L$21=D250),TRANSPOSE(COLUMN('2026 Points'!$E$13:$L$21)^0)),0))} -> #N/A
A251: 250 | B251: 468 | C251: ▲218 | D251: ROULAND Louis | E251: Cofidis | F251: 45 | I251: {=INDEX('2026 Points'!$D$13:$D$21,MATCH(1,MMULT(--('2026 Points'!$E$13:$L$21=D251),TRANSPOSE(COLUMN('2026 Points'!$E$13:$L$21)^0)),0))} -> #N/A
A252: 251 | C252: ▲new | D252: YU Yuanfeng | E252: China Anta - Mentech Cycling Team | F252: 45 | I252: {=INDEX('2026 Points'!$D$13:$D$21,MATCH(1,MMULT(--('2026 Points'!$E$13:$L$21=D252),TRANSPOSE(COLUMN('2026 Points'!$E$13:$L$21)^0)),0))} -> #N/A
A253: 252 | B253: 29 | C253: ▼223 | D253: SKJELMOSE Mattias | E253: Lidl - Trek | F253: 45 | I253: {=INDEX('2026 Points'!$D$13:$D$21,MATCH(1,MMULT(--('2026 Points'!$E$13:$L$21=D253),TRANSPOSE(COLUMN('2026 Points'!$E$13:$L$21)^0)),0))} -> Mike
A254: 253 | B254: 1278 | C254: ▲1025 | D254: HERREGODTS Rune | E254: UAE Team Emirates - XRG | F254: 44 | I254: {=INDEX('2026 Points'!$D$13:$D$21,MATCH(1,MMULT(--('2026 Points'!$E$13:$L$21=D254),TRANSPOSE(COLUMN('2026 Points'!$E$13:$L$21)^0)),0))} -> #N/A
A255: 254 | B255: 861 | C255: ▲607 | D255: SÜTTERLIN Jasha | E255: Team Jayco AlUla | F255: 44 | I255: {=INDEX('2026 Points'!$D$13:$D$21,MATCH(1,MMULT(--('2026 Points'!$E$13:$L$21=D255),TRANSPOSE(COLUMN('2026 Points'!$E$13:$L$21)^0)),0))} -> #N/A
A256: 255 | B256: 216 | C256: ▼39 | D256: KOPECKÝ Matyáš | E256: Unibet Rose Rockets | F256: 44 | I256: {=INDEX('2026 Points'!$D$13:$D$21,MATCH(1,MMULT(--('2026 Points'!$E$13:$L$21=D256),TRANSPOSE(COLUMN('2026 Points'!$E$13:$L$21)^0)),0))} -> #N/A
A257: 256 | B257: 532 | C257: ▲276 | D257: GAVIRIA Fernando | E257: Caja Rural - Seguros RGA | F257: 43 | I257: {=INDEX('2026 Points'!$D$13:$D$21,MATCH(1,MMULT(--('2026 Points'!$E$13:$L$21=D257),TRANSPOSE(COLUMN('2026 Points'!$E$13:$L$21)^0)),0))} -> #N/A
A258: 257 | B258: 436 | C258: ▲179 | D258: BRAET Vito | E258: Lotto Intermarché | F258: 43 | I258: {=INDEX('2026 Points'!$D$13:$D$21,MATCH(1,MMULT(--('2026 Points'!$E$13:$L$21=D258),TRANSPOSE(COLUMN('2026 Points'!$E$13:$L$21)^0)),0))} -> #N/A
A259: 258 | B259: 650 | C259: ▲392 | D259: REINDERS Elmar | E259: Unibet Rose Rockets | F259: 42 | I259: {=INDEX('2026 Points'!$D$13:$D$21,MATCH(1,MMULT(--('2026 Points'!$E$13:$L$21=D259),TRANSPOSE(COLUMN('2026 Points'!$E$13:$L$21)^0)),0))} -> #N/A
A260: 259 | B260: 333 | C260: ▲74 | D260: CAPIOT Amaury | E260: Team Jayco AlUla | F260: 42 | I260: {=INDEX('2026 Points'!$D$13:$D$21,MATCH(1,MMULT(--('2026 Points'!$E$13:$L$21=D260),TRANSPOSE(COLUMN('2026 Points'!$E$13:$L$21)^0)),0))} -> #N/A
A261: 260 | B261: 520 | C261: ▲260 | D261: DAUPHIN Florian | E261: TotalEnergies | F261: 42 | I261: {=INDEX('2026 Points'!$D$13:$D$21,MATCH(1,MMULT(--('2026 Points'!$E$13:$L$21=D261),TRANSPOSE(COLUMN('2026 Points'!$E$13:$L$21)^0)),0))} -> #N/A
A262: 261 | B262: 291 | C262: ▲30 | D262: MILESI Lorenzo | E262: Movistar Team | F262: 42 | I262: {=INDEX('2026 Points'!$D$13:$D$21,MATCH(1,MMULT(--('2026 Points'!$E$13:$L$21=D262),TRANSPOSE(COLUMN('2026 Points'!$E$13:$L$21)^0)),0))} -> #N/A
A263: 262 | B263: 409 | C263: ▲147 | D263: CRESCIOLI Ludovico | E263: Team Polti VisitMalta | F263: 42 | I263: {=INDEX('2026 Points'!$D$13:$D$21,MATCH(1,MMULT(--('2026 Points'!$E$13:$L$21=D263),TRANSPOSE(COLUMN('2026 Points'!$E$13:$L$21)^0)),0))} -> #N/A
A264: 263 | B264: 195 | C264: ▼68 | D264: BIERMANS Jenthe | E264: Cofidis | F264: 42 | I264: {=INDEX('2026 Points'!$D$13:$D$21,MATCH(1,MMULT(--('2026 Points'!$E$13:$L$21=D264),TRANSPOSE(COLUMN('2026 Points'!$E$13:$L$21)^0)),0))} -> #N/A
... A305: 304 | B305: 1148 | C305: ▲844 | D305: RODRIGUEZ Juan Felipe | E305: EF Education - Aevolo | F305: 34 | I305: {=INDEX('2026 Points'!$D$13:$D$21,MATCH(1,MMULT(--('2026 Points'!$E$13:$L$21=D305),TRANSPOSE(COLUMN('2026 Points'!$E$13:$L$21)^0)),0))} -> #N/A
A306: 305 | C306: ▲new | D306: CISNEROS Jose Said | E306: Soudal Quick-Step Devo Team | F306: 34 | I306: {=INDEX('2026 Points'!$D$13:$D$21,MATCH(1,MMULT(--('2026 Points'!$E$13:$L$21=D306),TRANSPOSE(COLUMN('2026 Points'!$E$13:$L$21)^0)),0))} -> #N/A
A307: 306 | B307: 447 | C307: ▲141 | D307: PACHER Quentin | E307: Groupama - FDJ United | F307: 34 | I307: {=INDEX('2026 Points'!$D$13:$D$21,MATCH(1,MMULT(--('2026 Points'!$E$13:$L$21=D307),TRANSPOSE(COLUMN('2026 Points'!$E$13:$L$21)^0)),0))} -> #N/A
A308: 307 | B308: 965 | C308: ▲658 | D308: BOWER Lewis | E308: Groupama - FDJ United | F308: 33 | I308: {=INDEX('2026 Points'!$D$13:$D$21,MATCH(1,MMULT(--('2026 Points'!$E$13:$L$21=D308),TRANSPOSE(COLUMN('2026 Points'!$E$13:$L$21)^0)),0))} -> #N/A
A309: 308 | B309: 1270 | C309: ▲962 | D309: BELLETTA Dario Igor | E309: Team Polti VisitMalta | F309: 33 | I309: {=INDEX('2026 Points'!$D$13:$D$21,MATCH(1,MMULT(--('2026 Points'!$E$13:$L$21=D309),TRANSPOSE(COLUMN('2026 Points'!$E$13:$L$21)^0)),0))} -> #N/A
A310: 309 | B310: 1184 | C310: ▲875 | D310: OLIVER Ben | E310: Modern Adventure Pro Cycling | F310: 33 | I310: {=INDEX('2026 Points'!$D$13:$D$21,MATCH(1,MMULT(--('2026 Points'!$E$13:$L$21=D310),TRANSPOSE(COLUMN('2026 Points'!$E$13:$L$21)^0)),0))} -> #N/A
A311: 310 | B311: 201 | C311: ▼109 | D311: GAUDU David | E311: Groupama - FDJ United | F311: 33 | I311: {=INDEX('2026 Points'!$D$13:$D$21,MATCH(1,MMULT(--('2026 Points'!$E$13:$L$21=D311),TRANSPOSE(COLUMN('2026 Points'!$E$13:$L$21)^0)),0))} -> #N/A
A312: 311 | B312: 288 | C312: ▼23 | D312: KOGUT Oded | E312: NSN Cycling Team | F312: 33 | I312: {=INDEX('2026 Points'!$D$13:$D$21,MATCH(1,MMULT(--('2026 Points'!$E$13:$L$21=D312),TRANSPOSE(COLUMN('2026 Points'!$E$13:$L$21)^0)),0))} -> #N/A
A313: 312 | B313: 338 | C313: ▲26 | D313: KELDERMAN Wilco | E313: Team Visma | Lease a Bike | F313: 33 | I313: {=INDEX('2026 Points'!$D$13:$D$21,MATCH(1,MMULT(--('2026 Points'!$E$13:$L$21=D313),TRANSPOSE(COLUMN('2026 Points'!$E$13:$L$21)^0)),0))} -> #N/A
A314: 313 | B314: 50 | C314: ▼263 | D314: CARAPAZ Richard | E314: EF Education - EasyPost | F314: 33 | I314: {=INDEX('2026 Points'!$D$13:$D$21,MATCH(1,MMULT(--('2026 Points'!$E$13:$L$21=D314),TRANSPOSE(COLUMN('2026 Points'!$E$13:$L$21)^0)),0))} -> Mike
A315: 314 | B315: 525 | C315: ▲211 | D315: BENNETT George | E315: NSN Cycling Team | F315: 32 | I315: {=INDEX('2026 Points'!$D$13:$D$21,MATCH(1,MMULT(--('2026 Points'!$E$13:$L$21=D315),TRANSPOSE(COLUMN('2026 Points'!$E$13:$L$21)^0)),0))} -> #N/A
A316: 315 | B316: 506 | C316: ▲191 | D316: CHRISTOPHERSEN Cedrik Bakke | E316: Unibet Rose Rockets | F316: 32 | I316: {=INDEX('2026 Points'!$D$13:$D$21,MATCH(1,MMULT(--('2026 Points'!$E$13:$L$21=D316),TRANSPOSE(COLUMN('2026 Points'!$E$13:$L$21)^0)),0))} -> #N/A
A317: 316 | B317: 727 | C317: ▲411 | D317: OLIVEIRA Nelson | E317: Movistar Team | F317: 32 | I317: {=INDEX('2026 Points'!$D$13:$D$21,MATCH(1,MMULT(--('2026 Points'!$E$13:$L$21=D317),TRANSPOSE(COLUMN('2026 Points'!$E$13:$L$21)^0)),0))} -> #N/A
A318: 317 | B318: 74 | C318: ▼243 | D318: MAS Enric | E318: Movistar Team | F318: 32 | I318: {=INDEX('2026 Points'!$D$13:$D$21,MATCH(1,MMULT(--('2026 Points'!$E$13:$L$21=D318),TRANSPOSE(COLUMN('2026 Points'!$E$13:$L$21)^0)),0))} -> #N/A
... A340: 339 | B340: 1210 | C340: ▲871 | D340: FROIDEVAUX Robin | E340: Tudor Pro Cycling Team | F340: 30 | I340: {=INDEX('2026 Points'!$D$13:$D$21,MATCH(1,MMULT(--('2026 Points'!$E$13:$L$21=D340),TRANSPOSE(COLUMN('2026 Points'!$E$13:$L$21)^0)),0))} -> #N/A
A341: 340 | B341: 1737 | C341: ▲1397 | D341: CHIKWAKA Andrew | F341: 30 | I341: {=INDEX('2026 Points'!$D$13:$D$21,MATCH(1,MMULT(--('2026 Points'!$E$13:$L$21=D341),TRANSPOSE(COLUMN('2026 Points'!$E$13:$L$21)^0)),0))} -> #N/A
A342: 341 | B342: 219 | C342: ▼122 | D342: MOHORIČ Matej | E342: Bahrain - Victorious | F342: 30 | I342: {=INDEX('2026 Points'!$D$13:$D$21,MATCH(1,MMULT(--('2026 Points'!$E$13:$L$21=D342),TRANSPOSE(COLUMN('2026 Points'!$E$13:$L$21)^0)),0))} -> #N/A
A343: 342 | B343: 485 | C343: ▲143 | D343: BERNARD Julien | E343: Lidl - Trek | F343: 30 | I343: {=INDEX('2026 Points'!$D$13:$D$21,MATCH(1,MMULT(--('2026 Points'!$E$13:$L$21=D343),TRANSPOSE(COLUMN('2026 Points'!$E$13:$L$21)^0)),0))} -> #N/A
A344: 343 | B344: 44 | C344: ▼299 | D344: WÆRENSKJOLD Søren | E344: Uno-X Mobility | F344: 30 | I344: {=INDEX('2026 Points'!$D$13:$D$21,MATCH(1,MMULT(--('2026 Points'!$E$13:$L$21=D344),TRANSPOSE(COLUMN('2026 Points'!$E$13:$L$21)^0)),0))} -> #N/A
A345: 344 | B345: 983 | C345: ▲639 | D345: VAN KERCKHOVE Matisse | E345: Team Visma | Lease a Bike Development | F345: 30 | I345: {=INDEX('2026 Points'!$D$13:$D$21,MATCH(1,MMULT(--('2026 Points'!$E$13:$L$21=D345),TRANSPOSE(COLUMN('2026 Points'!$E$13:$L$21)^0)),0))} -> #N/A
A346: 345 | B346: 367 | C346: ▲22 | D346: ALLENO Clément | E346: Burgos Burpellet BH | F346: 29 | I346: {=INDEX('2026 Points'!$D$13:$D$21,MATCH(1,MMULT(--('2026 Points'!$E$13:$L$21=D346),TRANSPOSE(COLUMN('2026 Points'!$E$13:$L$21)^0)),0))} -> #N/A
A347: 346 | B347: 604 | C347: ▲258 | D347: PALETTI Luca | E347: Bardiani CSF 7 Saber | F347: 29 | I347: {=INDEX('2026 Points'!$D$13:$D$21,MATCH(1,MMULT(--('2026 Points'!$E$13:$L$21=D347),TRANSPOSE(COLUMN('2026 Points'!$E$13:$L$21)^0)),0))} -> #N/A
A348: 347 | B348: 446 | C348: ▲99 | D348: UHLIG Henri | E348: Alpecin-Premier Tech | F348: 29 | I348: {=INDEX('2026 Points'!$D$13:$D$21,MATCH(1,MMULT(--('2026 Points'!$E$13:$L$21=D348),TRANSPOSE(COLUMN('2026 Points'!$E$13:$L$21)^0)),0))} -> #N/A
A349: 348 | B349: 206 | C349: ▼142 | D349: ADRIÀ Roger | E349: Movistar Team | F349: 29 | I349: {=INDEX('2026 Points'!$D$13:$D$21,MATCH(1,MMULT(--('2026 Points'!$E$13:$L$21=D349),TRANSPOSE(COLUMN('2026 Points'!$E$13:$L$21)^0)),0))} -> #N/A
A350: 349 | B350: 92 | C350: ▼257 | D350: DELETTRE Alexandre | E350: TotalEnergies | F350: 29 | I350: {=INDEX('2026 Points'!$D$13:$D$21,MATCH(1,MMULT(--('2026 Points'!$E$13:$L$21=D350),TRANSPOSE(COLUMN('2026 Points'!$E$13:$L$21)^0)),0))} -> #N/A
A351: 350 | B351: 433 | C351: ▲83 | D351: VALTER Attila | E351: Bahrain - Victorious | F351: 29 | I351: {=INDEX('2026 Points'!$D$13:$D$21,MATCH(1,MMULT(--('2026 Points'!$E$13:$L$21=D351),TRANSPOSE(COLUMN('2026 Points'!$E$13:$L$21)^0)),0))} -> #N/A
A352: 351 | B352: 465 | C352: ▲114 | D352: CUYLITS Mauro | E352: Lotto - Groupe Wanty | F352: 29 | I352: {=INDEX('2026 Points'!$D$13:$D$21,MATCH(1,MMULT(--('2026 Points'!$E$13:$L$21=D352),TRANSPOSE(COLUMN('2026 Points'!$E$13:$L$21)^0)),0))} -> #N/A
A353: 352 | C353: ▲new | D353: ZEMKE Jermaine | E353: REMBE | rad-net | F353: 29 | I353: {=INDEX('2026 Points'!$D$13:$D$21,MATCH(1,MMULT(--('2026 Points'!$E$13:$L$21=D353),TRANSPOSE(COLUMN('2026 Points'!$E$13:$L$21)^0)),0))} -> #N/A
A354: 353 | B354: 960 | C354: ▲607 | D354: FOX Matthew | E354: Lotto Intermarché | F354: 28 | I354: {=INDEX('2026 Points'!$D$13:$D$21,MATCH(1,MMULT(--('2026 Points'!$E$13:$L$21=D354),TRANSPOSE(COLUMN('2026 Points'!$E$13:$L$21)^0)),0))} -> #N/A
A355: 354 | B355: 422 | C355: ▲68 | D355: CONCI Nicola | E355: XDS Astana Team | F355: 28 | I355: {=INDEX('2026 Points'!$D$13:$D$21,MATCH(1,MMULT(--('2026 Points'!$E$13:$L$21=D355),TRANSPOSE(COLUMN('2026 Points'!$E$13:$L$21)^0)),0))} -> #N/A
A356: 355 | B356: 242 | C356: ▼113 | D356: ETXEBERRIA Haimar | E356: Red Bull - BORA - hansgrohe | F356: 28 | I356: {=INDEX('2026 Points'!$D$13:$D$21,MATCH(1,MMULT(--('2026 Points'!$E$13:$L$21=D356),TRANSPOSE(COLUMN('2026 Points'!$E$13:$L$21)^0)),0))} -> #N/A
A357: 356 | B357: 307 | C357: ▼49 | D357: HALLER Marco | E357: Tudor Pro Cycling Team | F357: 28 | I357: {=INDEX('2026 Points'!$D$13:$D$21,MATCH(1,MMULT(--('2026 Points'!$E$13:$L$21=D357),TRANSPOSE(COLUMN('2026 Points'!$E$13:$L$21)^0)),0))} -> #N/A
A358: 357 | B358: 804 | C358: ▲447 | D358: KLUCKERS Arthur | E358: Tudor Pro Cycling Team | F358: 28 | I358: {=INDEX('2026 Points'!$D$13:$D$21,MATCH(1,MMULT(--('2026 Points'!$E$13:$L$21=D358),TRANSPOSE(COLUMN('2026 Points'!$E$13:$L$21)^0)),0))} -> #N/A
A359: 358 | B359: 378 | C359: ▲20 | D359: GENIETS Kevin | E359: Groupama - FDJ United | F359: 28 | I359: {=INDEX('2026 Points'!$D$13:$D$21,MATCH(1,MMULT(--('2026 Points'!$E$13:$L$21=D359),TRANSPOSE(COLUMN('2026 Points'!$E$13:$L$21)^0)),0))} -> #N/A
A360: 359 | B360: 450 | C360: ▲91 | D360: MAESTRI Mirco | E360: Team Polti VisitMalta | F360: 28 | I360: {=INDEX('2026 Points'!$D$13:$D$21,MATCH(1,MMULT(--('2026 Points'!$E$13:$L$21=D360),TRANSPOSE(COLUMN('2026 Points'!$E$13:$L$21)^0)),0))} -> #N/A
A361: 360 | B361: 1245 | C361: ▲885 | D361: CHU Tsun Wai | E361: HKSI Pro Cycling Team | F361: 28 | I361: {=INDEX('2026 Points'!$D$13:$D$21,MATCH(1,MMULT(--('2026 Points'!$E$13:$L$21=D361),TRANSPOSE(COLUMN('2026 Points'!$E$13:$L$21)^0)),0))} -> #N/A
...

Sheet 2026 Draft
A1: Nick | C1: Tim | E1: Cameron | G1: Andrew | I1: Dave | L1: Riders - 2025 Final Ranking Order
A2: Budget remaining | B2: =1000-SUM(B5:B12) -> 3 | C2: Budget remaining | D2: =1000-SUM(D5:D12) -> 14 | E2: Budget remaining | F2: =1000-SUM(F5:F12) -> 35 | G2: Budget remaining | H2: =1000-SUM(H5:H12) -> 25 | I2: Budget remaining | J2: =1000-SUM(J5:J12) -> 5 | L2: POGAČAR Tadej
A3: Spaces remaining | B3: =COUNTBLANK(A5:A12) -> 0 | C3: Spaces remaining | D3: =COUNTBLANK(C5:C12) -> 0 | E3: Spaces remaining | F3: =COUNTBLANK(E5:E12) -> 0 | G3: Spaces remaining | H3: =COUNTBLANK(G5:G12) -> 0 | I3: Spaces remaining | J3: =COUNTBLANK(I5:I12) -> 0 | L3: DEL TORO Isaac
A4: Rider | B4: Spend | C4: Rider | D4: Spend | E4: Rider | F4: Spend | G4: Rider | H4: Spend | I4: Rider | J4: Spend | L4: VINGEGAARD Jonas
A5: AYUSO Juan | B5: 280 | C5: PHILIPSEN Jasper | D5: 230 | E5: HEALY Ben | F5: 150 | G5: EVENEPOEL Remco | H5: 520 | I5: VAUQUELIN Kévin | J5: 160 | L5: ALMEIDA João
A6: VINGEGAARD Jonas | B6: 600 | C6: KOOIJ Olav | D6: 190 | E6: JORGENSON Matteo | F6: 170 | G6: BRENNAN Matthew | H6: 220 | I6: CICCONE Giulio | J6: 120 | L6: PEDERSEN Mads
A7: VINE Jay | B7: 110 | C7: MERLIER Tim | D7: 210 | E7: PIDCOCK Thomas | F7: 250 | G7: MCNULTY Brandon | H7: 30 | I7: GALL Felix | J7: 115 | L7: EVENEPOEL Remco
A8: NARVÁEZ Jhonatan | B8: 1 | C8: PEDERSEN Mads | D8: 340 | E8: ONLEY Oscar | F8: 170 | G8: ALMEIDA João | H8: 88 | I8: DEL TORO Isaac | J8: 475 | L8: PIDCOCK Thomas
A9: TARLING Joshua | B9: 1 | C9: STRONG Corbin | D9: 5 | E9: ROGLIČ Primož | F9: 118 | G9: GRÉGOIRE Romain | H9: 30 | I9: MARTINEZ Lenny | J9: 40 | L9: VAN DER POEL Mathieu
A10: WILLIAMS Stephen | B10: 3 | C10: CHRISTEN Jan | D10: 1 | E10: ARENSMAN Thymen | F10: 55 | G10: MOSCHETTI Matteo | H10: 1 | I10: POWLESS Neilson | J10: 10 | L10: ONLEY Oscar
A11: FORTUNATO Lorenzo | B11: 1 | C11: BLACKMORE Joseph | D11: 5 | E11: GANNA Filippo | F11: 40 | G11: YATES Adam | H11: 66 | I11: GIRMAY Biniam | J11: 50 | L11: DE LIE Arnaud
A12: O'CONNOR Ben | B12: 1 | C12: HINDLEY Jai | D12: 5 | E12: ALAPHILIPPE Julian | F12: 12 | G12: UIJTDEBROEKS Cian | H12: 20 | I12: JEANNIÈRE Emilien | J12: 25 | L12: MAGNIER Paul
A13: Mike | C13: Campbell | E13: Joe | G13: Gemini's Hipsters | L13: AYUSO Juan
A14: Budget remaining | B14: =1000-SUM(B17:B24) -> 50 | C14: Budget remaining | D14: =1000-SUM(D17:D24) -> 49 | E14: Budget remaining | F14: =1000-SUM(F17:F24) -> 1000 | G14: Budget remaining | H14: =1000-SUM(H17:H24) -> 1000 | I14: Budget remaining | J14: =1000-SUM(J17:J24) -> 1000 | L14: CICCONE Giulio
A15: Spaces remaining | B15: =COUNTBLANK(A17:A24) -> 0 | C15: Spaces remaining | D15: =COUNTBLANK(C17:C24) -> 0 | E15: Spaces remaining | F15: =COUNTBLANK(E17:E24) -> 0 | G15: Spaces remaining | H15: =COUNTBLANK(G17:G24) -> 0 | I15: Spaces remaining | J15: =COUNTBLANK(I17:I24) -> 8 | L15: SCARONI Christian
A16: Rider | B16: Spend | C16: Rider | D16: Spend | E16: Rider | F16: Spend | G16: Rider | H16: Spend | I16: Rider | J16: Spend | L16: MCNULTY Brandon
A17: DE LIE Arnaud | B17: 260 | C17: VAN AERT Wout | D17: 210 | E17: PIDCOCK Joseph | G17: BISIAUX Léo | L17: VAUQUELIN Kévin
A18: SKJELMOSE Mattias | B18: 155 | C18: LIPOWITZ Florian | D18: 300 | E18: CRAPS Lars | G18: NORDHAGEN Jørgen | L18: MERLIER Tim
A19: MAGNIER Paul | B19: 120 | C19: MILAN Jonathan | D19: 220 | E19: JAKOBSEN Fabio | G19: LAMPERTI Luke | L19: VAN AERT Wout
A20: VAN DER POEL Mathieu | B20: 260 | C20: SCARONI Christian | D20: 160 | E20: SÖDERQVIST Jakob | G20: AUGUST Andrew | L20: MILAN Jonathan
A21: CARAPAZ Richard | B21: 50 | C21: WRIGHT Fred | D21: 30 | E21: WIDAR Jarno | G21: AGOSTINACCHIO Filippo | L21: PHILIPSEN Jasper
A22: NYS Thibau | B22: 40 | C22: PELLIZZARI Giulio | D22: 15 | E22: HIRSCHI Marc | G22: FINN Lorenzo | L22: VINE Jay
A23: SEIXAS Paul | B23: 50 | C23: STORER Michael | D23: 15 | E23: WANG Gustav | G23: TULETT Ben | L23: HEALY Ben
A24: GEE Derek | B24: 15 | C24: DEL GROSSO Tibor | D24: 1 | E24: POGAČAR Tadej | G24: ABRAHAMSEN Jonas | L24: LIPOWITZ Florian
L25: KOOIJ Olav
A26: Budget remaining | B26: =1000-SUM(B29:B36) -> 1000 | C26: Budget remaining | D26: =1000-SUM(D29:D36) -> 1000 | L26: STORER Michael
A27: Spaces remaining | B27: =COUNTBLANK(A29:A36) -> 8 | C27: Spaces remaining | D27: =COUNTBLANK(C29:C36) -> 8 | L27: JORGENSON Matteo
A28: Rider | B28: Spend | C28: Rider | D28: Spend | L28: GALL Felix
L29: GRÉGOIRE Romain
L30: SKJELMOSE Mattias
L31: BRENNAN Matthew
L32: MARTINEZ Lenny
L33: ROGLIČ Primož
L34: NARVÁEZ Jhonatan
L35: ARENSMAN Thymen
L36: GANNA Filippo
L37: STRONG Corbin
L38: JEANNIÈRE Emilien
L39: YATES Simon
L40: POWLESS Neilson
... L2498: SCHUTTE Ryno

Sheet 2025 Draft
A1: Nick | C1: Tim | E1: Cameron | G1: Chris | I1: Dave | L1: Riders | N1: Tim | O1: Nick | P1: Andy | Q1: Dave
A2: Budget remaining | B2: =1000-SUM(B5:B12) -> 0 | C2: Budget remaining | D2: =1000-SUM(D5:D12) -> 110 | E2: Budget remaining | F2: =1000-SUM(F5:F12) -> 92 | G2: Budget remaining | H2: =1000-SUM(H5:H12) -> 250 | I2: Budget remaining | J2: =1000-SUM(J5:J12) -> 0 | L2: POGAČAR Tadej | N2: Brennan (40) | O2: Lipowitz (24) | P2: Buitrago (1) | Q2: Vauquelin
A3: Spaces remaining | B3: =COUNTBLANK(A5:A12) -> 0 | C3: Spaces remaining | D3: =COUNTBLANK(C5:C12) -> 0 | E3: Spaces remaining | F3: =COUNTBLANK(E5:E12) -> 0 | G3: Spaces remaining | H3: =COUNTBLANK(G5:G12) -> 0 | I3: Spaces remaining | J3: =COUNTBLANK(I5:I12) -> 0 | L3: EVENEPOEL Remco | N3: Magnier (40) | O3: Tim Wellens (1) | P3: Egan Bernal (1)
A4: Rider | B4: Spend | C4: Rider | D4: Spend | E4: Rider | F4: Spend | G4: Rider | H4: Spend | I4: Rider | J4: Spend | L4: PHILIPSEN Jasper
A5: NARVÁEZ Jhonatan | B5: 75 | C5: GIRMAY Biniam | D5: 200 | E5: GAUDU David | F5: 15 | G5: ALMEIDA João | H5: 225 | I5: VAN AERT Wout | J5: 375 | L5: HIRSCHI Marc
A6: VINGEGAARD Jonas | B6: 650 | C6: PHILIPSEN Jasper | D6: 350 | E6: EVENEPOEL Remco | F6: 700 | G6: MERLIER Tim | H6: 110 | I6: VAN DER POEL Mathieu | J6: 490 | L6: VINGEGAARD Jonas
A7: CARAPAZ Richard | B7: 90 | C7: MCNULTY Brandon | D7: 70 | E7: MATTHEWS Michael | F7: 30 | G7: YATES Adam | H7: 50 | I7: POWLESS Neilson | J7: 25 | L7: O'CONNOR Ben
A8: EWAN Caleb | B8: 10 | C8: HIRSCHI Marc | D8: 80 | E8: BARDET Romain | F8: 25 | G8: VLASOV Aleksandr | H8: 55 | I8: GROENEWEGEN Dylan | J8: 30 | L8: GIRMAY Biniam
A9: O'CONNOR Ben | B9: 85 | C9: VAN EETVELT Lennert | D9: 40 | E9: COSNEFROY Benoît | F9: 95 | G9: JORGENSON Matteo | H9: 150 | I9: LANDA Mikel | J9: 30 | L9: VAN DER POEL Mathieu
A10: WILLIAMS Stephen | B10: 15 | C10: VAN GILS Maxim | D10: 90 | E10: ABRAHAMSEN Jonas | F10: 20 | G10: RODRÍGUEZ Carlos | H10: 50 | I10: KÜNG Stefan | J10: 10 | L10: ROGLIČ Primož
A11: PIDCOCK Thomas | B11: 40 | C11: GANNA Filippo | D11: 40 | E11: SHEFFIELD Magnus | F11: 13 | G11: AYUSO Juan | H11: 90 | I11: MARTINEZ Lenny | J11: 30 | L11: MERLIER Tim
A12: MAS Enric | B12: 35 | C12: ONLEY Oscar | D12: 20 | E12: ARENSMAN Thymen | F12: 10 | G12: YATES Simon | H12: 20 | I12: CICCONE Giulio | J12: 10 | L12: PEDERSEN Mads
A13: Mike | C13: Andy | E13: Campbell | G13: Joe | L13: JORGENSON Matteo
A14: Budget remaining | B14: =1000-SUM(B17:B24) -> 40 | C14: Budget remaining | D14: =1000-SUM(D17:D24) -> 0 | E14: Budget remaining | F14: =1000-SUM(F17:F24) -> 0 | G14: Budget remaining | H14: =1000-SUM(H17:H24) -> 0 | I14: Budget remaining | J14: =1000-SUM(J17:J24) -> 1000 | L14: VAN AERT Wout
A15: Spaces remaining | B15: =COUNTBLANK(A17:A24) -> 0 | C15: Spaces remaining | D15: =COUNTBLANK(C17:C24) -> 0 | E15: Spaces remaining | F15: =COUNTBLANK(E17:E24) -> 7 | G15: Spaces remaining | H15: =COUNTBLANK(G17:G24) -> 7 | I15: Spaces remaining | J15: =COUNTBLANK(I17:I24) -> 8 | L15: DE LIE Arnaud
A16: Rider | B16: Spend | C16: Rider | D16: Spend | E16: Rider | F16: Spend | G16: Rider | H16: Spend | I16: Rider | J16: Spend | L16: MCNULTY Brandon
A17: DE LIE Arnaud | B17: 130 | C17: POGAČAR Tadej | D17: 993 | E17: POGAČAR Tadej | F17: 993 | G17: POGAČAR Tadej | H17: 993 | L17: YATES Adam
A18: PEDERSEN Mads | B18: 235 | C18: PITHIE Laurence | D18: 1 | F18: 1 | H18: 1 | L18: MAS Enric
A19: MILAN Jonathan | B19: 135 | C19: MADOUAS Valentin | D19: 1 | F19: 1 | H19: 1 | L19: MILAN Jonathan
A20: ROGLIČ Primož | B20: 290 | C20: MOHORIČ Matej | D20: 1 | F20: 1 | H20: 1 | L20: RODRÍGUEZ Carlos
A21: SKJELMOSE Mattias | B21: 70 | C21: HINDLEY Jai | D21: 1 | F21: 1 | H21: 1 | L21: AYUSO Juan
A22: NYS Thibau | B22: 50 | C22: GROENEWEGEN Dylan | D22: 1 | F22: 1 | H22: 1 | L22: VLASOV Aleksandr
A23: KOOIJ Olav | B23: 40 | C23: CORT Magnus | D23: 1 | F23: 1 | H23: 1 | L23: VAN GILS Maxim
A24: DEL TORO Isaac | B24: 10 | C24: GEE Derek | D24: 1 | F24: 1 | H24: 1 | L24: SKJELMOSE Mattias
L25: CARAPAZ Richard
A26: Budget remaining | B26: =1000-SUM(B29:B36) -> 1000 | C26: Budget remaining | D26: =1000-SUM(D29:D36) -> 1000 | L26: ULISSI Diego
A27: Spaces remaining | B27: =COUNTBLANK(A29:A36) -> 8 | C27: Spaces remaining | D27: =COUNTBLANK(C29:C36) -> 8 | L27: ALMEIDA João
A28: Rider | B28: Spend | C28: Rider | D28: Spend | L28: LANDA Mikel
L29: VAN EETVELT Lennert
L30: KOOIJ Olav
L31: PIDCOCK Thomas
L32: COSNEFROY Benoît
L33: WELLENS Tim
L34: KRISTOFF Alexander
L35: KÜNG Stefan
L36: WILLIAMS Stephen
L37: ZINGLE Axel
L38: ONLEY Oscar
L39: ALAPHILIPPE Julian
L40: STRONG Corbin
... L2501: RODRIGUEZ Ruddy

Sheet Current 2025 Points
A1: Team | B1: Rank | C1: Null | D1: Total | E1: Pre Transfer | F1: Post Transfer
A2: Nick | B2: =rank(D2,D$2:D$8) -> 4 | C2: =countif(G2:N2, 0) -> 0 | D2: =E2+F2 -> 8352 | E2: 3619 | F2: =sum(G2:N2) -> 4733 | G2: =IFERROR(VLOOKUP(G11,'Current 2025 Ranking'!$D:$K,8,0),0) -> 612 | H2: =IFERROR(VLOOKUP(H11,'Current 2025 Ranking'!$D:$K,8,0),0) -> 1826 | I2: =IFERROR(VLOOKUP(I11,'Current 2025 Ranking'!$D:$K,8,0),0) -> 173 | J2: =IFERROR(VLOOKUP(J11,'Current 2025 Ranking'!$D:$K,8,0),0) -> 557 | K2: =IFERROR(VLOOKUP(K11,'Current 2025 Ranking'!$D:$K,8,0),0) -> 365 | L2: =IFERROR(VLOOKUP(L11,'Current 2025 Ranking'!$D:$K,8,0),0) -> 359 | M2: =IFERROR(VLOOKUP(M11,'Current 2025 Ranking'!$D:$K,8,0),0) -> 813 | N2: =IFERROR(VLOOKUP(N11,'Current 2025 Ranking'!$D:$K,8,0),0) -> 28
A3: Tim | B3: =rank(D3,D$2:D$8) -> 5 | C3: =countif(G3:N3, 0) -> 1 | D3: =E3+F3 -> 8203 | E3: 4074 | F3: =sum(G3:N3) -> 4129 | G3: =IFERROR(VLOOKUP(G12,'Current 2025 Ranking'!$D:$K,8,0),0) -> 399 | H3: =IFERROR(VLOOKUP(H12,'Current 2025 Ranking'!$D:$K,8,0),0) -> 642 | I3: =IFERROR(VLOOKUP(I12,'Current 2025 Ranking'!$D:$K,8,0),0) -> 931 | J3: =IFERROR(VLOOKUP(J12,'Current 2025 Ranking'!$D:$K,8,0),0) -> 388 | K3: =IFERROR(VLOOKUP(K12,'Current 2025 Ranking'!$D:$K,8,0),0) -> 0 | L3: =IFERROR(VLOOKUP(L12,'Current 2025 Ranking'!$D:$K,8,0),0) -> 861 | M3: =IFERROR(VLOOKUP(M12,'Current 2025 Ranking'!$D:$K,8,0),0) -> 168 | N3: =IFERROR(VLOOKUP(N12,'Current 2025 Ranking'!$D:$K,8,0),0) -> 740
A4: Cameron | B4: =rank(D4,D$2:D$8) -> 7 | C4: =countif(G4:N4, 0) -> 2 | D4: =E4+F4 -> 5714 | E4: 2974 | F4: =sum(G4:N4) -> 2740 | G4: =IFERROR(VLOOKUP(G13,'Current 2025 Ranking'!$D:$K,8,0),0) -> 147 | H4: =IFERROR(VLOOKUP(H13,'Current 2025 Ranking'!$D:$K,8,0),0) -> 1196 | I4: =IFERROR(VLOOKUP(I13,'Current 2025 Ranking'!$D:$K,8,0),0) -> 283 | J4: =IFERROR(VLOOKUP(J13,'Current 2025 Ranking'!$D:$K,8,0),0) -> 0 | K4: =IFERROR(VLOOKUP(K13,'Current 2025 Ranking'!$D:$K,8,0),0) -> 0 | L4: =IFERROR(VLOOKUP(L13,'Current 2025 Ranking'!$D:$K,8,0),0) -> 515 | M4: =IFERROR(VLOOKUP(M13,'Current 2025 Ranking'!$D:$K,8,0),0) -> 68 | N4: =IFERROR(VLOOKUP(N13,'Current 2025 Ranking'!$D:$K,8,0),0) -> 531
A5: Chris | B5: =rank(D5,D$2:D$8) -> 3 | C5: =countif(G5:N5, 0) -> 0 | D5: =E5+F5 -> 8357 | E5: 5485 | F5: =sum(G5:N5) -> 2872 | G5: =IFERROR(VLOOKUP(G14,'Current 2025 Ranking'!$D:$K,8,0),0) -> 636 | H5: =IFERROR(VLOOKUP(H14,'Current 2025 Ranking'!$D:$K,8,0),0) -> 476 | I5: =IFERROR(VLOOKUP(I14,'Current 2025 Ranking'!$D:$K,8,0),0) -> 427 | J5: =IFERROR(VLOOKUP(J14,'Current 2025 Ranking'!$D:$K,8,0),0) -> 108 | K5: =IFERROR(VLOOKUP(K14,'Current 2025 Ranking'!$D:$K,8,0),0) -> 494 | L5: =IFERROR(VLOOKUP(L14,'Current 2025 Ranking'!$D:$K,8,0),0) -> 14 | M5: =IFERROR(VLOOKUP(M14,'Current 2025 Ranking'!$D:$K,8,0),0) -> 425 | N5: =IFERROR(VLOOKUP(N14,'Current 2025 Ranking'!$D:$K,8,0),0) -> 292
A6: Dave | B6: =rank(D6,D$2:D$8) -> 6 | C6: =countif(G6:N6, 0) -> 0 | D6: =E6+F6 -> 7864 | E6: 4972 | F6: =sum(G6:N6) -> 2892 | G6: =IFERROR(VLOOKUP(G15,'Current 2025 Ranking'!$D:$K,8,0),0) -> 415 | H6: =IFERROR(VLOOKUP(H15,'Current 2025 Ranking'!$D:$K,8,0),0) -> 508 | I6: =IFERROR(VLOOKUP(I15,'Current 2025 Ranking'!$D:$K,8,0),0) -> 239 | J6: =IFERROR(VLOOKUP(J15,'Current 2025 Ranking'!$D:$K,8,0),0) -> 212 | K6: =IFERROR(VLOOKUP(K15,'Current 2025 Ranking'!$D:$K,8,0),0) -> 137 | L6: =IFERROR(VLOOKUP(L15,'Current 2025 Ranking'!$D:$K,8,0),0) -> 392 | M6: =IFERROR(VLOOKUP(M15,'Current 2025 Ranking'!$D:$K,8,0),0) -> 304 | N6: =IFERROR(VLOOKUP(N15,'Current 2025 Ranking'!$D:$K,8,0),0) -> 685
A7: Mike | B7: =rank(D7,D$2:D$8) -> 1 | C7: =countif(G7:N7, 0) -> 0 | D7: =E7+F7 -> 11586 | E7: 5616 | F7: =sum(G7:N7) -> 5970 | G7: =IFERROR(VLOOKUP(G16,'Current 2025 Ranking'!$D:$K,8,0),0) -> 1415 | H7: =IFERROR(VLOOKUP(H16,'Current 2025 Ranking'!$D:$K,8,0),0) -> 601 | I7: =IFERROR(VLOOKUP(I16,'Current 2025 Ranking'!$D:$K,8,0),0) -> 574 | J7: =IFERROR(VLOOKUP(J16,'Current 2025 Ranking'!$D:$K,8,0),0) -> 501 | K7: =IFERROR(VLOOKUP(K16,'Current 2025 Ranking'!$D:$K,8,0),0) -> 515 | L7: =IFERROR(VLOOKUP(L16,'Current 2025 Ranking'!$D:$K,8,0),0) -> 41 | M7: =IFERROR(VLOOKUP(M16,'Current 2025 Ranking'!$D:$K,8,0),0) -> 554 | N7: =IFERROR(VLOOKUP(N16,'Current 2025 Ranking'!$D:$K,8,0),0) -> 1769
A8: Andy | B8: =rank(D8,D$2:D$8) -> 2 | C8: =countif(G8:N8, 0) -> 1 | D8: =E8+F8 -> 8606 | E8: 4578 | F8: =sum(G8:N8) -> 4028 | G8: =IFERROR(VLOOKUP(G17,'Current 2025 Ranking'!$D:$K,8,0),0) -> 2621 | H8: =IFERROR(VLOOKUP(H17,'Current 2025 Ranking'!$D:$K,8,0),0) -> 37 | I8: =IFERROR(VLOOKUP(I17,'Current 2025 Ranking'!$D:$K,8,0),0) -> 232 | J8: =IFERROR(VLOOKUP(J17,'Current 2025 Ranking'!$D:$K,8,0),0) -> 227 | K8: =IFERROR(VLOOKUP(K17,'Current 2025 Ranking'!$D:$K,8,0),0) -> 450 | L8: =IFERROR(VLOOKUP(L17,'Current 2025 Ranking'!$D:$K,8,0),0) -> 436 | M8: =IFERROR(VLOOKUP(M17,'Current 2025 Ranking'!$D:$K,8,0),0) -> 25 | N8: =IFERROR(VLOOKUP(N17,'Current 2025 Ranking'!$D:$K,8,0),0) -> 0
F10: Manager | G10: 1 | H10: 2 | I10: 3 | J10: 4 | K10: 5 | L10: 6 | M10: 7 | N10: 8
A11: Nick | F11: Nick | G11: NARVÁEZ Jhonatan | H11: VINGEGAARD Jonas | I11: CARAPAZ Richard | J11: LIPOWITZ Florian | K11: O'CONNOR Ben | L11: WELLENS Tim | M11: PIDCOCK Thomas | N11: MAS Enric
A12: Tim | F12: Tim | G12: GIRMAY Biniam | H12: PHILIPSEN Jasper | I12: MCNULTY Brandon | J12: BRENNAN Matthew | K12: VAN EETVELT Lennert | L12: MAGNIER Paul | M12: GANNA Filippo | N12: ONLEY Oscar
A13: Cameron | F13: Cameron | G13: GAUDU David | H13: EVENEPOEL Remco | I13: MATTHEWS Michael | J13: BARDET Romain | K13: COSNEFROY Benoît | L13: ABRAHAMSEN Jonas | M13: SHEFFIELD Magnus | N13: ARENSMAN Thymen
A14: Chris | F14: Chris | G14: ALMEIDA João | H14: MERLIER Tim | I14: YATES Adam | J14: VLASOV Aleksandr | K14: JORGENSON Matteo | L14: RODRÍGUEZ Carlos | M14: AYUSO Juan | N14: YATES Simon
A15: Dave | F15: Dave | G15: VAN AERT Wout | H15: VAN DER POEL Mathieu | I15: POWLESS Neilson | J15: GROENEWEGEN Dylan | K15: LANDA Mikel | L15: VAUQUELIN Kévin | M15: MARTINEZ Lenny | N15: CICCONE Giulio
A16: Mike | F16: Mike | G16: DE LIE Arnaud | H16: PEDERSEN Mads | I16: MILAN Jonathan | J16: ROGLIČ Primož | K16: SKJELMOSE Mattias | L16: NYS Thibau | M16: KOOIJ Olav | N16: DEL TORO Isaac
A17: Andy | F17: Andy | G17: POGAČAR Tadej | H17: PITHIE Laurence | I17: MADOUAS Valentin | J17: BUITRAGO Santiago | K17: HINDLEY Jai | L17: BERNAL Egan | M17: CORT Magnus | N17: GEE Derek

Sheet Current 2025 Ranking
A1: Rank | B1: Prev. Rank | C1: Rank Diff. | D1: Rider | E1: Team | F1: Points | I1: Manager | K1: Adjusted points | L1: In pre-transfer team? | M1: In post-transfer team?
A2: 1 | B2: 1 | C2: - | D2: POGAČAR Tadej | E2: UAE Team Emirates - XRG | F2: 4921 | I2: {=INDEX('Current 2025 Points'!$F$11:$F$77,MATCH(1,MMULT(--('Current 2025 Points'!$G$11:$N$17=D2),TRANSPOSE(COLUMN('Current 2025 Points'!$G$11:$N$17)^0)),0))} -> Andy | K2: =F2-IFERROR(VLOOKUP(D2,'Pre-transfer 2025 Ranking'!$D:$F,3,0),0) -> 2621 | L2: =countif('Pre-transfer 2025 Points'!$E$11:$L$17,D2) -> 1 | M2: =countif('Current 2025 Points'!$G$11:$N$17,D2) -> 1
A3: 2 | B3: 48 | C3: ▲46 | D3: DEL TORO Isaac | E3: UAE Team Emirates - XRG | F3: 2755 | I3: {=INDEX('Current 2025 Points'!$F$11:$F$77,MATCH(1,MMULT(--('Current 2025 Points'!$G$11:$N$17=D3),TRANSPOSE(COLUMN('Current 2025 Points'!$G$11:$N$17)^0)),0))} -> Mike | K3: =F3-IFERROR(VLOOKUP(D3,'Pre-transfer 2025 Ranking'!$D:$F,3,0),0) -> 1769 | L3: =countif('Pre-transfer 2025 Points'!$E$11:$L$17,D3) -> 1 | M3: =countif('Current 2025 Points'!$G$11:$N$17,D3) -> 1
A4: 3 | B4: 5 | C4: ▲2 | D4: VINGEGAARD Jonas | E4: Team Visma | Lease a Bike | F4: 2399 | I4: {=INDEX('Current 2025 Points'!$F$11:$F$77,MATCH(1,MMULT(--('Current 2025 Points'!$G$11:$N$17=D4),TRANSPOSE(COLUMN('Current 2025 Points'!$G$11:$N$17)^0)),0))} -> Nick | K4: =F4-IFERROR(VLOOKUP(D4,'Pre-transfer 2025 Ranking'!$D:$F,3,0),0) -> 1826 | L4: =countif('Pre-transfer 2025 Points'!$E$11:$L$17,D4) -> 1 | M4: =countif('Current 2025 Points'!$G$11:$N$17,D4) -> 1
A5: 4 | B5: 26 | C5: ▲22 | D5: ALMEIDA João | E5: UAE Team Emirates - XRG | F5: 2270 | I5: {=INDEX('Current 2025 Points'!$F$11:$F$77,MATCH(1,MMULT(--('Current 2025 Points'!$G$11:$N$17=D5),TRANSPOSE(COLUMN('Current 2025 Points'!$G$11:$N$17)^0)),0))} -> Chris | K5: =F5-IFERROR(VLOOKUP(D5,'Pre-transfer 2025 Ranking'!$D:$F,3,0),0) -> 636 | L5: =countif('Pre-transfer 2025 Points'!$E$11:$L$17,D5) -> 1 | M5: =countif('Current 2025 Points'!$G$11:$N$17,D5) -> 1
A6: 5 | B6: 11 | C6: ▲6 | D6: PEDERSEN Mads | E6: Lidl - Trek | F6: 2233 | I6: {=INDEX('Current 2025 Points'!$F$11:$F$77,MATCH(1,MMULT(--('Current 2025 Points'!$G$11:$N$17=D6),TRANSPOSE(COLUMN('Current 2025 Points'!$G$11:$N$17)^0)),0))} -> Mike | K6: =F6-IFERROR(VLOOKUP(D6,'Pre-transfer 2025 Ranking'!$D:$F,3,0),0) -> 601 | L6: =countif('Pre-transfer 2025 Points'!$E$11:$L$17,D6) -> 1 | M6: =countif('Current 2025 Points'!$G$11:$N$17,D6) -> 1
A7: 6 | B7: 2 | C7: ▼4 | D7: EVENEPOEL Remco | E7: Soudal Quick-Step | F7: 1924 | I7: {=INDEX('Current 2025 Points'!$F$11:$F$77,MATCH(1,MMULT(--('Current 2025 Points'!$G$11:$N$17=D7),TRANSPOSE(COLUMN('Current 2025 Points'!$G$11:$N$17)^0)),0))} -> Cameron | K7: =F7-IFERROR(VLOOKUP(D7,'Pre-transfer 2025 Ranking'!$D:$F,3,0),0) -> 1196 | L7: =countif('Pre-transfer 2025 Points'!$E$11:$L$17,D7) -> 1 | M7: =countif('Current 2025 Points'!$G$11:$N$17,D7) -> 1
A8: 7 | B8: 30 | C8: ▲23 | D8: PIDCOCK Thomas | E8: Q36.5 Pro Cycling Team | F8: 1855 | I8: {=INDEX('Current 2025 Points'!$F$11:$F$77,MATCH(1,MMULT(--('Current 2025 Points'!$G$11:$N$17=D8),TRANSPOSE(COLUMN('Current 2025 Points'!$G$11:$N$17)^0)),0))} -> Nick | K8: =F8-IFERROR(VLOOKUP(D8,'Pre-transfer 2025 Ranking'!$D:$F,3,0),0) -> 813 | L8: =countif('Pre-transfer 2025 Points'!$E$11:$L$17,D8) -> 1 | M8: =countif('Current 2025 Points'!$G$11:$N$17,D8) -> 1
A9: 8 | B9: 8 | C9: - | D9: VAN DER POEL Mathieu | E9: Alpecin - Deceuninck | F9: 1621 | I9: {=INDEX('Current 2025 Points'!$F$11:$F$77,MATCH(1,MMULT(--('Current 2025 Points'!$G$11:$N$17=D9),TRANSPOSE(COLUMN('Current 2025 Points'!$G$11:$N$17)^0)),0))} -> Dave | K9: =F9-IFERROR(VLOOKUP(D9,'Pre-transfer 2025 Ranking'!$D:$F,3,0),0) -> 508 | L9: =countif('Pre-transfer 2025 Points'!$E$11:$L$17,D9) -> 1 | M9: =countif('Current 2025 Points'!$G$11:$N$17,D9) -> 1
A10: 9 | B10: 37 | C10: ▲28 | D10: ONLEY Oscar | E10: Team Picnic PostNL | F10: 1620 | I10: {=INDEX('Current 2025 Points'!$F$11:$F$77,MATCH(1,MMULT(--('Current 2025 Points'!$G$11:$N$17=D10),TRANSPOSE(COLUMN('Current 2025 Points'!$G$11:$N$17)^0)),0))} -> Tim | K10: =F10-IFERROR(VLOOKUP(D10,'Pre-transfer 2025 Ranking'!$D:$F,3,0),0) -> 740 | L10: =countif('Pre-transfer 2025 Points'!$E$11:$L$17,D10) -> 1 | M10: =countif('Current 2025 Points'!$G$11:$N$17,D10) -> 1
A11: 10 | B11: 14 | C11: ▲4 | D11: DE LIE Arnaud | E11: Lotto | F11: 1615 | I11: {=INDEX('Current 2025 Points'!$F$11:$F$77,MATCH(1,MMULT(--('Current 2025 Points'!$G$11:$N$17=D11),TRANSPOSE(COLUMN('Current 2025 Points'!$G$11:$N$17)^0)),0))} -> Mike | K11: =F11-IFERROR(VLOOKUP(D11,'Pre-transfer 2025 Ranking'!$D:$F,3,0),0) -> 1415 | L11: =countif('Pre-transfer 2025 Points'!$E$11:$L$17,D11) -> 1 | M11: =countif('Current 2025 Points'!$G$11:$N$17,D11) -> 1
A12: 11 | B12: 144 | C12: ▲133 | D12: MAGNIER Paul | E12: Soudal Quick-Step | F12: 1552 | I12: {=INDEX('Current 2025 Points'!$F$11:$F$77,MATCH(1,MMULT(--('Current 2025 Points'!$G$11:$N$17=D12),TRANSPOSE(COLUMN('Current 2025 Points'!$G$11:$N$17)^0)),0))} -> Tim | K12: =F12-IFERROR(VLOOKUP(D12,'Pre-transfer 2025 Ranking'!$D:$F,3,0),0) -> 861 | L12: =countif('Pre-transfer 2025 Points'!$E$11:$L$17,D12) -> 0 | M12: =countif('Current 2025 Points'!$G$11:$N$17,D12) -> 1
A13: 12 | B13: 20 | C13: ▲8 | D13: AYUSO Juan | E13: UAE Team Emirates - XRG | F13: 1414 | I13: {=INDEX('Current 2025 Points'!$F$11:$F$77,MATCH(1,MMULT(--('Current 2025 Points'!$G$11:$N$17=D13),TRANSPOSE(COLUMN('Current 2025 Points'!$G$11:$N$17)^0)),0))} -> Chris | K13: =F13-IFERROR(VLOOKUP(D13,'Pre-transfer 2025 Ranking'!$D:$F,3,0),0) -> 425 | L13: =countif('Pre-transfer 2025 Points'!$E$11:$L$17,D13) -> 1 | M13: =countif('Current 2025 Points'!$G$11:$N$17,D13) -> 1
... A59: 58 | B59: 102 | C59: ▲44 | D59: JOHANNESSEN Tobias Halland | E59: Uno-X Mobility | F59: 737 | I59: {=INDEX('Current 2025 Points'!$F$11:$F$77,MATCH(1,MMULT(--('Current 2025 Points'!$G$11:$N$17=D59),TRANSPOSE(COLUMN('Current 2025 Points'!$G$11:$N$17)^0)),0))} -> #N/A | K59: =F59-IFERROR(VLOOKUP(D59,'Pre-transfer 2025 Ranking'!$D:$F,3,0),0) -> 414 | L59: =countif('Pre-transfer 2025 Points'!$E$11:$L$17,D59) -> 0 | M59: =countif('Current 2025 Points'!$G$11:$N$17,D59) -> 0
A60: 59 | B60: 77 | C60: ▲18 | D60: GEE Derek | F60: 731 | I60: {=INDEX('Current 2025 Points'!$F$11:$F$77,MATCH(1,MMULT(--('Current 2025 Points'!$G$11:$N$17=D60),TRANSPOSE(COLUMN('Current 2025 Points'!$G$11:$N$17)^0)),0))} -> Andy | K60: =F60-IFERROR(VLOOKUP(D60,'Pre-transfer 2025 Ranking'!$D:$F,3,0),0) -> 0 | L60: =countif('Pre-transfer 2025 Points'!$E$11:$L$17,D60) -> 1 | M60: =countif('Current 2025 Points'!$G$11:$N$17,D60) -> 1
A61: 60 | B61: 59 | C61: ▼1 | D61: BUITRAGO Santiago | E61: Bahrain - Victorious | F61: 728 | I61: {=INDEX('Current 2025 Points'!$F$11:$F$77,MATCH(1,MMULT(--('Current 2025 Points'!$G$11:$N$17=D61),TRANSPOSE(COLUMN('Current 2025 Points'!$G$11:$N$17)^0)),0))} -> Andy | K61: =F61-IFERROR(VLOOKUP(D61,'Pre-transfer 2025 Ranking'!$D:$F,3,0),0) -> 227 | L61: =countif('Pre-transfer 2025 Points'!$E$11:$L$17,D61) -> 0 | M61: =countif('Current 2025 Points'!$G$11:$N$17,D61) -> 1
A62: 61 | B62: 95 | C62: ▲34 | D62: HINDLEY Jai | E62: Red Bull - BORA - hansgrohe | F62: 714 | I62: {=INDEX('Current 2025 Points'!$F$11:$F$77,MATCH(1,MMULT(--('Current 2025 Points'!$G$11:$N$17=D62),TRANSPOSE(COLUMN('Current 2025 Points'!$G$11:$N$17)^0)),0))} -> Andy | K62: =F62-IFERROR(VLOOKUP(D62,'Pre-transfer 2025 Ranking'!$D:$F,3,0),0) -> 450 | L62: =countif('Pre-transfer 2025 Points'!$E$11:$L$17,D62) -> 1 | M62: =countif('Current 2025 Points'!$G$11:$N$17,D62) -> 1
A63: 62 | B63: 138 | C63: ▲76 | D63: PELLIZZARI Giulio | E63: Red Bull - BORA - hansgrohe | F63: 714 | I63: {=INDEX('Current 2025 Points'!$F$11:$F$77,MATCH(1,MMULT(--('Current 2025 Points'!$G$11:$N$17=D63),TRANSPOSE(COLUMN('Current 2025 Points'!$G$11:$N$17)^0)),0))} -> #N/A | K63: =F63-IFERROR(VLOOKUP(D63,'Pre-transfer 2025 Ranking'!$D:$F,3,0),0) -> 416 | L63: =countif('Pre-transfer 2025 Points'!$E$11:$L$17,D63) -> 0 | M63: =countif('Current 2025 Points'!$G$11:$N$17,D63) -> 0
A64: 63 | B64: 283 | C64: ▲220 | D64: LÓPEZ Harold Martín | E64: XDS Astana Team | F64: 709 | I64: {=INDEX('Current 2025 Points'!$F$11:$F$77,MATCH(1,MMULT(--('Current 2025 Points'!$G$11:$N$17=D64),TRANSPOSE(COLUMN('Current 2025 Points'!$G$11:$N$17)^0)),0))} -> #N/A | K64: =F64-IFERROR(VLOOKUP(D64,'Pre-transfer 2025 Ranking'!$D:$F,3,0),0) -> 172 | L64: =countif('Pre-transfer 2025 Points'!$E$11:$L$17,D64) -> 0 | M64: =countif('Current 2025 Points'!$G$11:$N$17,D64) -> 0
A65: 64 | B65: 123 | C65: ▲59 | D65: CHAMPOUSSIN Clément | E65: XDS Astana Team | F65: 699 | I65: {=INDEX('Current 2025 Points'!$F$11:$F$77,MATCH(1,MMULT(--('Current 2025 Points'!$G$11:$N$17=D65),TRANSPOSE(COLUMN('Current 2025 Points'!$G$11:$N$17)^0)),0))} -> #N/A | K65: =F65-IFERROR(VLOOKUP(D65,'Pre-transfer 2025 Ranking'!$D:$F,3,0),0) -> 135 | L65: =countif('Pre-transfer 2025 Points'!$E$11:$L$17,D65) -> 0 | M65: =countif('Current 2025 Points'!$G$11:$N$17,D65) -> 0
A66: 65 | B66: 158 | C66: ▲93 | D66: SCHMID Mauro | E66: Team Jayco AlUla | F66: 698 | I66: {=INDEX('Current 2025 Points'!$F$11:$F$77,MATCH(1,MMULT(--('Current 2025 Points'!$G$11:$N$17=D66),TRANSPOSE(COLUMN('Current 2025 Points'!$G$11:$N$17)^0)),0))} -> #N/A | K66: =F66-IFERROR(VLOOKUP(D66,'Pre-transfer 2025 Ranking'!$D:$F,3,0),0) -> 244 | L66: =countif('Pre-transfer 2025 Points'!$E$11:$L$17,D66) -> 0 | M66: =countif('Current 2025 Points'!$G$11:$N$17,D66) -> 0
A67: 66 | B67: 122 | C67: ▲56 | D67: GODON Dorian | E67: Decathlon AG2R La Mondiale Team | F67: 689 | I67: {=INDEX('Current 2025 Points'!$F$11:$F$77,MATCH(1,MMULT(--('Current 2025 Points'!$G$11:$N$17=D67),TRANSPOSE(COLUMN('Current 2025 Points'!$G$11:$N$17)^0)),0))} -> #N/A | K67: =F67-IFERROR(VLOOKUP(D67,'Pre-transfer 2025 Ranking'!$D:$F,3,0),0) -> 457 | L67: =countif('Pre-transfer 2025 Points'!$E$11:$L$17,D67) -> 0 | M67: =countif('Current 2025 Points'!$G$11:$N$17,D67) -> 0
A68: 67 | B68: 1087 | C68: ▲1020 | D68: TULETT Ben | E68: Team Visma | Lease a Bike | F68: 686 | I68: {=INDEX('Current 2025 Points'!$F$11:$F$77,MATCH(1,MMULT(--('Current 2025 Points'!$G$11:$N$17=D68),TRANSPOSE(COLUMN('Current 2025 Points'!$G$11:$N$17)^0)),0))} -> #N/A | K68: =F68-IFERROR(VLOOKUP(D68,'Pre-transfer 2025 Ranking'!$D:$F,3,0),0) -> 238 | L68: =countif('Pre-transfer 2025 Points'!$E$11:$L$17,D68) -> 0 | M68: =countif('Current 2025 Points'!$G$11:$N$17,D68) -> 0
A69: 68 | B69: 68 | C69: - | D69: SIVAKOV Pavel | E69: UAE Team Emirates - XRG | F69: 677 | I69: {=INDEX('Current 2025 Points'!$F$11:$F$77,MATCH(1,MMULT(--('Current 2025 Points'!$G$11:$N$17=D69),TRANSPOSE(COLUMN('Current 2025 Points'!$G$11:$N$17)^0)),0))} -> #N/A | K69: =F69-IFERROR(VLOOKUP(D69,'Pre-transfer 2025 Ranking'!$D:$F,3,0),0) -> 446 | L69: =countif('Pre-transfer 2025 Points'!$E$11:$L$17,D69) -> 0 | M69: =countif('Current 2025 Points'!$G$11:$N$17,D69) -> 0
A70: 69 | B70: 6 | C70: ▼63 | D70: O'CONNOR Ben | E70: Team Jayco AlUla | F70: 675 | I70: {=INDEX('Current 2025 Points'!$F$11:$F$77,MATCH(1,MMULT(--('Current 2025 Points'!$G$11:$N$17=D70),TRANSPOSE(COLUMN('Current 2025 Points'!$G$11:$N$17)^0)),0))} -> Nick | K70: =F70-IFERROR(VLOOKUP(D70,'Pre-transfer 2025 Ranking'!$D:$F,3,0),0) -> 365 | L70: =countif('Pre-transfer 2025 Points'!$E$11:$L$17,D70) -> 1 | M70: =countif('Current 2025 Points'!$G$11:$N$17,D70) -> 1
A71: 70 | B71: 32 | C71: ▼38 | D71: WELLENS Tim | E71: UAE Team Emirates - XRG | F71: 675 | I71: {=INDEX('Current 2025 Points'!$F$11:$F$77,MATCH(1,MMULT(--('Current 2025 Points'!$G$11:$N$17=D71),TRANSPOSE(COLUMN('Current 2025 Points'!$G$11:$N$17)^0)),0))} -> Nick | K71: =F71-IFERROR(VLOOKUP(D71,'Pre-transfer 2025 Ranking'!$D:$F,3,0),0) -> 359 | L71: =countif('Pre-transfer 2025 Points'!$E$11:$L$17,D71) -> 0 | M71: =countif('Current 2025 Points'!$G$11:$N$17,D71) -> 1
A72: 71 | B72: 70 | C72: ▼1 | D72: VAN WILDER Ilan | E72: Soudal Quick-Step | F72: 668 | I72: {=INDEX('Current 2025 Points'!$F$11:$F$77,MATCH(1,MMULT(--('Current 2025 Points'!$G$11:$N$17=D72),TRANSPOSE(COLUMN('Current 2025 Points'!$G$11:$N$17)^0)),0))} -> #N/A | K72: =F72-IFERROR(VLOOKUP(D72,'Pre-transfer 2025 Ranking'!$D:$F,3,0),0) -> 299 | L72: =countif('Pre-transfer 2025 Points'!$E$11:$L$17,D72) -> 0 | M72: =countif('Current 2025 Points'!$G$11:$N$17,D72) -> 0
... A99: 98 | B99: 45 | C99: ▼53 | D99: SKUJIŅŠ Toms | E99: Lidl - Trek | F99: 547 | I99: {=INDEX('Current 2025 Points'!$F$11:$F$77,MATCH(1,MMULT(--('Current 2025 Points'!$G$11:$N$17=D99),TRANSPOSE(COLUMN('Current 2025 Points'!$G$11:$N$17)^0)),0))} -> #N/A | K99: =F99-IFERROR(VLOOKUP(D99,'Pre-transfer 2025 Ranking'!$D:$F,3,0),0) -> 406 | L99: =countif('Pre-transfer 2025 Points'!$E$11:$L$17,D99) -> 0 | M99: =countif('Current 2025 Points'!$G$11:$N$17,D99) -> 0
A100: 99 | C100: ▲new | D100: SEIXAS Paul | E100: Decathlon AG2R La Mondiale Team | F100: 544 | I100: {=INDEX('Current 2025 Points'!$F$11:$F$77,MATCH(1,MMULT(--('Current 2025 Points'!$G$11:$N$17=D100),TRANSPOSE(COLUMN('Current 2025 Points'!$G$11:$N$17)^0)),0))} -> #N/A | K100: =F100-IFERROR(VLOOKUP(D100,'Pre-transfer 2025 Ranking'!$D:$F,3,0),0) -> 279 | L100: =countif('Pre-transfer 2025 Points'!$E$11:$L$17,D100) -> 0 | M100: =countif('Current 2025 Points'!$G$11:$N$17,D100) -> 0
A101: 100 | B101: 111 | C101: ▲11 | D101: PARET-PEINTRE Aurélien | E101: Decathlon AG2R La Mondiale Team | F101: 539 | I101: {=INDEX('Current 2025 Points'!$F$11:$F$77,MATCH(1,MMULT(--('Current 2025 Points'!$G$11:$N$17=D101),TRANSPOSE(COLUMN('Current 2025 Points'!$G$11:$N$17)^0)),0))} -> #N/A | K101: =F101-IFERROR(VLOOKUP(D101,'Pre-transfer 2025 Ranking'!$D:$F,3,0),0) -> 285 | L101: =countif('Pre-transfer 2025 Points'!$E$11:$L$17,D101) -> 0 | M101: =countif('Current 2025 Points'!$G$11:$N$17,D101) -> 0
A102: 101 | B102: 52 | C102: ▼49 | D102: GROENEWEGEN Dylan | E102: Team Jayco AlUla | F102: 538 | I102: {=INDEX('Current 2025 Points'!$F$11:$F$77,MATCH(1,MMULT(--('Current 2025 Points'!$G$11:$N$17=D102),TRANSPOSE(COLUMN('Current 2025 Points'!$G$11:$N$17)^0)),0))} -> Dave | K102: =F102-IFERROR(VLOOKUP(D102,'Pre-transfer 2025 Ranking'!$D:$F,3,0),0) -> 212 | L102: =countif('Pre-transfer 2025 Points'!$E$11:$L$17,D102) -> 2 | M102: =countif('Current 2025 Points'!$G$11:$N$17,D102) -> 1
A103: 102 | B103: 400 | C103: ▲298 | D103: ASKEY Lewis | E103: Groupama - FDJ | F103: 535 | I103: {=INDEX('Current 2025 Points'!$F$11:$F$77,MATCH(1,MMULT(--('Current 2025 Points'!$G$11:$N$17=D103),TRANSPOSE(COLUMN('Current 2025 Points'!$G$11:$N$17)^0)),0))} -> #N/A | K103: =F103-IFERROR(VLOOKUP(D103,'Pre-transfer 2025 Ranking'!$D:$F,3,0),0) -> 39 | L103: =countif('Pre-transfer 2025 Points'!$E$11:$L$17,D103) -> 0 | M103: =countif('Current 2025 Points'!$G$11:$N$17,D103) -> 0
A104: 103 | B104: 143 | C104: ▲40 | D104: SILVA Guillermo Thomas | E104: Caja Rural - Seguros RGA | F104: 531 | I104: {=INDEX('Current 2025 Points'!$F$11:$F$77,MATCH(1,MMULT(--('Current 2025 Points'!$G$11:$N$17=D104),TRANSPOSE(COLUMN('Current 2025 Points'!$G$11:$N$17)^0)),0))} -> #N/A | K104: =F104-IFERROR(VLOOKUP(D104,'Pre-transfer 2025 Ranking'!$D:$F,3,0),0) -> 223 | L104: =countif('Pre-transfer 2025 Points'!$E$11:$L$17,D104) -> 0 | M104: =countif('Current 2025 Points'!$G$11:$N$17,D104) -> 0
A105: 104 | B105: 490 | C105: ▲386 | D105: KULSET Johannes | E105: Uno-X Mobility | F105: 527 | I105: {=INDEX('Current 2025 Points'!$F$11:$F$77,MATCH(1,MMULT(--('Current 2025 Points'!$G$11:$N$17=D105),TRANSPOSE(COLUMN('Current 2025 Points'!$G$11:$N$17)^0)),0))} -> #N/A | K105: =F105-IFERROR(VLOOKUP(D105,'Pre-transfer 2025 Ranking'!$D:$F,3,0),0) -> 247 | L105: =countif('Pre-transfer 2025 Points'!$E$11:$L$17,D105) -> 0 | M105: =countif('Current 2025 Points'!$G$11:$N$17,D105) -> 0
A106: 105 | B106: 128 | C106: ▲23 | D106: KUSS Sepp | E106: Team Visma | Lease a Bike | F106: 527 | I106: {=INDEX('Current 2025 Points'!$F$11:$F$77,MATCH(1,MMULT(--('Current 2025 Points'!$G$11:$N$17=D106),TRANSPOSE(COLUMN('Current 2025 Points'!$G$11:$N$17)^0)),0))} -> #N/A | K106: =F106-IFERROR(VLOOKUP(D106,'Pre-transfer 2025 Ranking'!$D:$F,3,0),0) -> 462 | L106: =countif('Pre-transfer 2025 Points'!$E$11:$L$17,D106) -> 0 | M106: =countif('Current 2025 Points'!$G$11:$N$17,D106) -> 0
A107: 106 | B107: 506 | C107: ▲400 | D107: BAGIOLI Andrea | E107: Lidl - Trek | F107: 524 | I107: {=INDEX('Current 2025 Points'!$F$11:$F$77,MATCH(1,MMULT(--('Current 2025 Points'!$G$11:$N$17=D107),TRANSPOSE(COLUMN('Current 2025 Points'!$G$11:$N$17)^0)),0))} -> #N/A | K107: =F107-IFERROR(VLOOKUP(D107,'Pre-transfer 2025 Ranking'!$D:$F,3,0),0) -> 169 | L107: =countif('Pre-transfer 2025 Points'!$E$11:$L$17,D107) -> 0 | M107: =countif('Current 2025 Points'!$G$11:$N$17,D107) -> 0
A108: 107 | B108: 202 | C108: ▲95 | D108: PLAPP Luke | E108: Team Jayco AlUla | F108: 516 | I108: {=INDEX('Current 2025 Points'!$F$11:$F$77,MATCH(1,MMULT(--('Current 2025 Points'!$G$11:$N$17=D108),TRANSPOSE(COLUMN('Current 2025 Points'!$G$11:$N$17)^0)),0))} -> #N/A | K108: =F108-IFERROR(VLOOKUP(D108,'Pre-transfer 2025 Ranking'!$D:$F,3,0),0) -> 251 | L108: =countif('Pre-transfer 2025 Points'!$E$11:$L$17,D108) -> 0 | M108: =countif('Current 2025 Points'!$G$11:$N$17,D108) -> 0
A109: 108 | B109: 146 | C109: ▲38 | D109: TEUNISSEN Mike | E109: XDS Astana Team | F109: 515 | I109: {=INDEX('Current 2025 Points'!$F$11:$F$77,MATCH(1,MMULT(--('Current 2025 Points'!$G$11:$N$17=D109),TRANSPOSE(COLUMN('Current 2025 Points'!$G$11:$N$17)^0)),0))} -> #N/A | K109: =F109-IFERROR(VLOOKUP(D109,'Pre-transfer 2025 Ranking'!$D:$F,3,0),0) -> 183 | L109: =countif('Pre-transfer 2025 Points'!$E$11:$L$17,D109) -> 0 | M109: =countif('Current 2025 Points'!$G$11:$N$17,D109) -> 0
A110: 109 | B110: 258 | C110: ▲149 | D110: MOSCHETTI Matteo | E110: Q36.5 Pro Cycling Team | F110: 514 | I110: {=INDEX('Current 2025 Points'!$F$11:$F$77,MATCH(1,MMULT(--('Current 2025 Points'!$G$11:$N$17=D110),TRANSPOSE(COLUMN('Current 2025 Points'!$G$11:$N$17)^0)),0))} -> #N/A | K110: =F110-IFERROR(VLOOKUP(D110,'Pre-transfer 2025 Ranking'!$D:$F,3,0),0) -> 93 | L110: =countif('Pre-transfer 2025 Points'!$E$11:$L$17,D110) -> 0 | M110: =countif('Current 2025 Points'!$G$11:$N$17,D110) -> 0
A111: 110 | B111: 61 | C111: ▼49 | D111: TRENTIN Matteo | E111: Tudor Pro Cycling Team | F111: 512 | I111: {=INDEX('Current 2025 Points'!$F$11:$F$77,MATCH(1,MMULT(--('Current 2025 Points'!$G$11:$N$17=D111),TRANSPOSE(COLUMN('Current 2025 Points'!$G$11:$N$17)^0)),0))} -> #N/A | K111: =F111-IFERROR(VLOOKUP(D111,'Pre-transfer 2025 Ranking'!$D:$F,3,0),0) -> 346 | L111: =countif('Pre-transfer 2025 Points'!$E$11:$L$17,D111) -> 0 | M111: =countif('Current 2025 Points'!$G$11:$N$17,D111) -> 0
A112: 111 | B112: 243 | C112: ▲132 | D112: SIMMONS Quinn | E112: Lidl - Trek | F112: 512 | I112: {=INDEX('Current 2025 Points'!$F$11:$F$77,MATCH(1,MMULT(--('Current 2025 Points'!$G$11:$N$17=D112),TRANSPOSE(COLUMN('Current 2025 Points'!$G$11:$N$17)^0)),0))} -> #N/A | K112: =F112-IFERROR(VLOOKUP(D112,'Pre-transfer 2025 Ranking'!$D:$F,3,0),0) -> 344 | L112: =countif('Pre-transfer 2025 Points'!$E$11:$L$17,D112) -> 0 | M112: =countif('Current 2025 Points'!$G$11:$N$17,D112) -> 0
... A151: 150 | B151: 80 | C151: ▼70 | D151: NYS Thibau | E151: Lidl - Trek | F151: 415 | I151: {=INDEX('Current 2025 Points'!$F$11:$F$77,MATCH(1,MMULT(--('Current 2025 Points'!$G$11:$N$17=D151),TRANSPOSE(COLUMN('Current 2025 Points'!$G$11:$N$17)^0)),0))} -> Mike | K151: =F151-IFERROR(VLOOKUP(D151,'Pre-transfer 2025 Ranking'!$D:$F,3,0),0) -> 41 | L151: =countif('Pre-transfer 2025 Points'!$E$11:$L$17,D151) -> 1 | M151: =countif('Current 2025 Points'!$G$11:$N$17,D151) -> 1
A152: 151 | C152: ▲new | D152: WITHEN PHILIPSEN Albert | E152: Lidl - Trek | F152: 413 | I152: {=INDEX('Current 2025 Points'!$F$11:$F$77,MATCH(1,MMULT(--('Current 2025 Points'!$G$11:$N$17=D152),TRANSPOSE(COLUMN('Current 2025 Points'!$G$11:$N$17)^0)),0))} -> #N/A | K152: =F152-IFERROR(VLOOKUP(D152,'Pre-transfer 2025 Ranking'!$D:$F,3,0),0) -> 167 | L152: =countif('Pre-transfer 2025 Points'!$E$11:$L$17,D152) -> 0 | M152: =countif('Current 2025 Points'!$G$11:$N$17,D152) -> 0
A153: 152 | B153: 261 | C153: ▲109 | D153: VERNON Ethan | E153: Israel - Premier Tech | F153: 413 | I153: {=INDEX('Current 2025 Points'!$F$11:$F$77,MATCH(1,MMULT(--('Current 2025 Points'!$G$11:$N$17=D153),TRANSPOSE(COLUMN('Current 2025 Points'!$G$11:$N$17)^0)),0))} -> #N/A | K153: =F153-IFERROR(VLOOKUP(D153,'Pre-transfer 2025 Ranking'!$D:$F,3,0),0) -> 207 | L153: =countif('Pre-transfer 2025 Points'!$E$11:$L$17,D153) -> 0 | M153: =countif('Current 2025 Points'!$G$11:$N$17,D153) -> 0
A154: 153 | B154: 127 | C154: ▼26 | D154: RUBIO Einer | E154: Movistar Team | F154: 412 | I154: {=INDEX('Current 2025 Points'!$F$11:$F$77,MATCH(1,MMULT(--('Current 2025 Points'!$G$11:$N$17=D154),TRANSPOSE(COLUMN('Current 2025 Points'!$G$11:$N$17)^0)),0))} -> #N/A | K154: =F154-IFERROR(VLOOKUP(D154,'Pre-transfer 2025 Ranking'!$D:$F,3,0),0) -> 101 | L154: =countif('Pre-transfer 2025 Points'!$E$11:$L$17,D154) -> 0 | M154: =countif('Current 2025 Points'!$G$11:$N$17,D154) -> 0
A155: 154 | B155: 573 | C155: ▲419 | D155: BLIKRA Erlend | E155: Uno-X Mobility | F155: 410 | I155: {=INDEX('Current 2025 Points'!$F$11:$F$77,MATCH(1,MMULT(--('Current 2025 Points'!$G$11:$N$17=D155),TRANSPOSE(COLUMN('Current 2025 Points'!$G$11:$N$17)^0)),0))} -> #N/A | K155: =F155-IFERROR(VLOOKUP(D155,'Pre-transfer 2025 Ranking'!$D:$F,3,0),0) -> 121 | L155: =countif('Pre-transfer 2025 Points'!$E$11:$L$17,D155) -> 0 | M155: =countif('Current 2025 Points'!$G$11:$N$17,D155) -> 0
A156: 155 | B156: 55 | C156: ▼100 | D156: MADOUAS Valentin | E156: Groupama - FDJ | F156: 409 | I156: {=INDEX('Current 2025 Points'!$F$11:$F$77,MATCH(1,MMULT(--('Current 2025 Points'!$G$11:$N$17=D156),TRANSPOSE(COLUMN('Current 2025 Points'!$G$11:$N$17)^0)),0))} -> Andy | K156: =F156-IFERROR(VLOOKUP(D156,'Pre-transfer 2025 Ranking'!$D:$F,3,0),0) -> 232 | L156: =countif('Pre-transfer 2025 Points'!$E$11:$L$17,D156) -> 1 | M156: =countif('Current 2025 Points'!$G$11:$N$17,D156) -> 1
A157: 156 | B157: 423 | C157: ▲267 | D157: BALLERINI Davide | E157: XDS Astana Team | F157: 408 | I157: {=INDEX('Current 2025 Points'!$F$11:$F$77,MATCH(1,MMULT(--('Current 2025 Points'!$G$11:$N$17=D157),TRANSPOSE(COLUMN('Current 2025 Points'!$G$11:$N$17)^0)),0))} -> #N/A | K157: =F157-IFERROR(VLOOKUP(D157,'Pre-transfer 2025 Ranking'!$D:$F,3,0),0) -> 228 | L157: =countif('Pre-transfer 2025 Points'!$E$11:$L$17,D157) -> 0 | M157: =countif('Current 2025 Points'!$G$11:$N$17,D157) -> 0
A158: 157 | B158: 428 | C158: ▲271 | D158: CARUSO Damiano | E158: Bahrain - Victorious | F158: 407 | I158: {=INDEX('Current 2025 Points'!$F$11:$F$77,MATCH(1,MMULT(--('Current 2025 Points'!$G$11:$N$17=D158),TRANSPOSE(COLUMN('Current 2025 Points'!$G$11:$N$17)^0)),0))} -> #N/A | K158: =F158-IFERROR(VLOOKUP(D158,'Pre-transfer 2025 Ranking'!$D:$F,3,0),0) -> 44 | L158: =countif('Pre-transfer 2025 Points'!$E$11:$L$17,D158) -> 0 | M158: =countif('Current 2025 Points'!$G$11:$N$17,D158) -> 0
A159: 158 | B159: 189 | C159: ▲31 | D159: DVERSNES Fredrik | E159: Uno-X Mobility | F159: 405 | I159: {=INDEX('Current 2025 Points'!$F$11:$F$77,MATCH(1,MMULT(--('Current 2025 Points'!$G$11:$N$17=D159),TRANSPOSE(COLUMN('Current 2025 Points'!$G$11:$N$17)^0)),0))} -> #N/A | K159: =F159-IFERROR(VLOOKUP(D159,'Pre-transfer 2025 Ranking'!$D:$F,3,0),0) -> 111 | L159: =countif('Pre-transfer 2025 Points'!$E$11:$L$17,D159) -> 0 | M159: =countif('Current 2025 Points'!$G$11:$N$17,D159) -> 0
A160: 159 | B160: 107 | C160: ▼52 | D160: STUYVEN Jasper | E160: Lidl - Trek | F160: 405 | I160: {=INDEX('Current 2025 Points'!$F$11:$F$77,MATCH(1,MMULT(--('Current 2025 Points'!$G$11:$N$17=D160),TRANSPOSE(COLUMN('Current 2025 Points'!$G$11:$N$17)^0)),0))} -> #N/A | K160: =F160-IFERROR(VLOOKUP(D160,'Pre-transfer 2025 Ranking'!$D:$F,3,0),0) -> 166 | L160: =countif('Pre-transfer 2025 Points'!$E$11:$L$17,D160) -> 0 | M160: =countif('Current 2025 Points'!$G$11:$N$17,D160) -> 0
A161: 160 | B161: 192 | C161: ▲32 | D161: HOELGAARD Markus | E161: Uno-X Mobility | F161: 404 | I161: {=INDEX('Current 2025 Points'!$F$11:$F$77,MATCH(1,MMULT(--('Current 2025 Points'!$G$11:$N$17=D161),TRANSPOSE(COLUMN('Current 2025 Points'!$G$11:$N$17)^0)),0))} -> #N/A | K161: =F161-IFERROR(VLOOKUP(D161,'Pre-transfer 2025 Ranking'!$D:$F,3,0),0) -> 178 | L161: =countif('Pre-transfer 2025 Points'!$E$11:$L$17,D161) -> 0 | M161: =countif('Current 2025 Points'!$G$11:$N$17,D161) -> 0
A162: 161 | B162: 435 | C162: ▲274 | D162: COVI Alessandro | E162: UAE Team Emirates - XRG | F162: 399 | I162: {=INDEX('Current 2025 Points'!$F$11:$F$77,MATCH(1,MMULT(--('Current 2025 Points'!$G$11:$N$17=D162),TRANSPOSE(COLUMN('Current 2025 Points'!$G$11:$N$17)^0)),0))} -> #N/A | K162: =F162-IFERROR(VLOOKUP(D162,'Pre-transfer 2025 Ranking'!$D:$F,3,0),0) -> 39 | L162: =countif('Pre-transfer 2025 Points'!$E$11:$L$17,D162) -> 0 | M162: =countif('Current 2025 Points'!$G$11:$N$17,D162) -> 0
A163: 162 | B163: 236 | C163: ▲74 | D163: HOFSTETTER Hugo | E163: Israel - Premier Tech | F163: 399 | I163: {=INDEX('Current 2025 Points'!$F$11:$F$77,MATCH(1,MMULT(--('Current 2025 Points'!$G$11:$N$17=D163),TRANSPOSE(COLUMN('Current 2025 Points'!$G$11:$N$17)^0)),0))} -> #N/A | K163: =F163-IFERROR(VLOOKUP(D163,'Pre-transfer 2025 Ranking'!$D:$F,3,0),0) -> 24 | L163: =countif('Pre-transfer 2025 Points'!$E$11:$L$17,D163) -> 0 | M163: =countif('Current 2025 Points'!$G$11:$N$17,D163) -> 0
A164: 163 | B164: 169 | C164: ▲6 | D164: HERMANS Quinten | E164: Alpecin - Deceuninck | F164: 397 | I164: {=INDEX('Current 2025 Points'!$F$11:$F$77,MATCH(1,MMULT(--('Current 2025 Points'!$G$11:$N$17=D164),TRANSPOSE(COLUMN('Current 2025 Points'!$G$11:$N$17)^0)),0))} -> #N/A | K164: =F164-IFERROR(VLOOKUP(D164,'Pre-transfer 2025 Ranking'!$D:$F,3,0),0) -> 224 | L164: =countif('Pre-transfer 2025 Points'!$E$11:$L$17,D164) -> 0 | M164: =countif('Current 2025 Points'!$G$11:$N$17,D164) -> 0
... A290: 289 | B290: 116 | C290: ▼173 | D290: ACKERMANN Pascal | E290: Israel - Premier Tech | F290: 226 | I290: {=INDEX('Current 2025 Points'!$F$11:$F$77,MATCH(1,MMULT(--('Current 2025 Points'!$G$11:$N$17=D290),TRANSPOSE(COLUMN('Current 2025 Points'!$G$11:$N$17)^0)),0))} -> #N/A | K290: =F290-IFERROR(VLOOKUP(D290,'Pre-transfer 2025 Ranking'!$D:$F,3,0),0) -> 94 | L290: =countif('Pre-transfer 2025 Points'!$E$11:$L$17,D290) -> 0 | M290: =countif('Current 2025 Points'!$G$11:$N$17,D290) -> 0
A291: 290 | B291: 40 | C291: ▼250 | D291: BARDET Romain | F291: 224 | I291: {=INDEX('Current 2025 Points'!$F$11:$F$77,MATCH(1,MMULT(--('Current 2025 Points'!$G$11:$N$17=D291),TRANSPOSE(COLUMN('Current 2025 Points'!$G$11:$N$17)^0)),0))} -> Cameron | K291: =F291-IFERROR(VLOOKUP(D291,'Pre-transfer 2025 Ranking'!$D:$F,3,0),0) -> 0 | L291: =countif('Pre-transfer 2025 Points'!$E$11:$L$17,D291) -> 1 | M291: =countif('Current 2025 Points'!$G$11:$N$17,D291) -> 1
A292: 291 | B292: 466 | C292: ▲175 | D292: MILESI Lorenzo | E292: Movistar Team | F292: 224 | I292: {=INDEX('Current 2025 Points'!$F$11:$F$77,MATCH(1,MMULT(--('Current 2025 Points'!$G$11:$N$17=D292),TRANSPOSE(COLUMN('Current 2025 Points'!$G$11:$N$17)^0)),0))} -> #N/A | K292: =F292-IFERROR(VLOOKUP(D292,'Pre-transfer 2025 Ranking'!$D:$F,3,0),0) -> 169 | L292: =countif('Pre-transfer 2025 Points'!$E$11:$L$17,D292) -> 0 | M292: =countif('Current 2025 Points'!$G$11:$N$17,D292) -> 0
A293: 292 | B293: 211 | C293: ▼81 | D293: LÓPEZ Juan Pedro | E293: Lidl - Trek | F293: 223 | I293: {=INDEX('Current 2025 Points'!$F$11:$F$77,MATCH(1,MMULT(--('Current 2025 Points'!$G$11:$N$17=D293),TRANSPOSE(COLUMN('Current 2025 Points'!$G$11:$N$17)^0)),0))} -> #N/A | K293: =F293-IFERROR(VLOOKUP(D293,'Pre-transfer 2025 Ranking'!$D:$F,3,0),0) -> 5 | L293: =countif('Pre-transfer 2025 Points'!$E$11:$L$17,D293) -> 0 | M293: =countif('Current 2025 Points'!$G$11:$N$17,D293) -> 0
A294: 293 | B294: 546 | C294: ▲253 | D294: HERRADA Jesús | E294: Cofidis | F294: 222 | I294: {=INDEX('Current 2025 Points'!$F$11:$F$77,MATCH(1,MMULT(--('Current 2025 Points'!$G$11:$N$17=D294),TRANSPOSE(COLUMN('Current 2025 Points'!$G$11:$N$17)^0)),0))} -> #N/A | K294: =F294-IFERROR(VLOOKUP(D294,'Pre-transfer 2025 Ranking'!$D:$F,3,0),0) -> 90 | L294: =countif('Pre-transfer 2025 Points'!$E$11:$L$17,D294) -> 0 | M294: =countif('Current 2025 Points'!$G$11:$N$17,D294) -> 0
A295: 294 | B295: 278 | C295: ▼16 | D295: DONOVAN Mark | E295: Q36.5 Pro Cycling Team | F295: 222 | I295: {=INDEX('Current 2025 Points'!$F$11:$F$77,MATCH(1,MMULT(--('Current 2025 Points'!$G$11:$N$17=D295),TRANSPOSE(COLUMN('Current 2025 Points'!$G$11:$N$17)^0)),0))} -> #N/A | K295: =F295-IFERROR(VLOOKUP(D295,'Pre-transfer 2025 Ranking'!$D:$F,3,0),0) -> 98 | L295: =countif('Pre-transfer 2025 Points'!$E$11:$L$17,D295) -> 0 | M295: =countif('Current 2025 Points'!$G$11:$N$17,D295) -> 0
A296: 295 | B296: 922 | C296: ▲627 | D296: GLOAG Thomas | E296: Team Visma | Lease a Bike | F296: 221 | I296: {=INDEX('Current 2025 Points'!$F$11:$F$77,MATCH(1,MMULT(--('Current 2025 Points'!$G$11:$N$17=D296),TRANSPOSE(COLUMN('Current 2025 Points'!$G$11:$N$17)^0)),0))} -> #N/A | K296: =F296-IFERROR(VLOOKUP(D296,'Pre-transfer 2025 Ranking'!$D:$F,3,0),0) -> 112 | L296: =countif('Pre-transfer 2025 Points'!$E$11:$L$17,D296) -> 0 | M296: =countif('Current 2025 Points'!$G$11:$N$17,D296) -> 0
A297: 296 | B297: 395 | C297: ▲99 | D297: KWIATKOWSKI Michał | E297: INEOS Grenadiers | F297: 221 | I297: {=INDEX('Current 2025 Points'!$F$11:$F$77,MATCH(1,MMULT(--('Current 2025 Points'!$G$11:$N$17=D297),TRANSPOSE(COLUMN('Current 2025 Points'!$G$11:$N$17)^0)),0))} -> #N/A | K297: =F297-IFERROR(VLOOKUP(D297,'Pre-transfer 2025 Ranking'!$D:$F,3,0),0) -> 110 | L297: =countif('Pre-transfer 2025 Points'!$E$11:$L$17,D297) -> 0 | M297: =countif('Current 2025 Points'!$G$11:$N$17,D297) -> 0
A298: 297 | B298: 845 | C298: ▲548 | D298: SVESTAD-BÅRDSENG Embret | E298: Arkéa - B&B Hotels | F298: 220 | I298: {=INDEX('Current 2025 Points'!$F$11:$F$77,MATCH(1,MMULT(--('Current 2025 Points'!$G$11:$N$17=D298),TRANSPOSE(COLUMN('Current 2025 Points'!$G$11:$N$17)^0)),0))} -> #N/A | K298: =F298-IFERROR(VLOOKUP(D298,'Pre-transfer 2025 Ranking'!$D:$F,3,0),0) -> 83 | L298: =countif('Pre-transfer 2025 Points'!$E$11:$L$17,D298) -> 0 | M298: =countif('Current 2025 Points'!$G$11:$N$17,D298) -> 0
A299: 298 | B299: 473 | C299: ▲175 | D299: STAUNE-MITTET Johannes | E299: Decathlon AG2R La Mondiale Team | F299: 220 | I299: {=INDEX('Current 2025 Points'!$F$11:$F$77,MATCH(1,MMULT(--('Current 2025 Points'!$G$11:$N$17=D299),TRANSPOSE(COLUMN('Current 2025 Points'!$G$11:$N$17)^0)),0))} -> #N/A | K299: =F299-IFERROR(VLOOKUP(D299,'Pre-transfer 2025 Ranking'!$D:$F,3,0),0) -> 93 | L299: =countif('Pre-transfer 2025 Points'!$E$11:$L$17,D299) -> 0 | M299: =countif('Current 2025 Points'!$G$11:$N$17,D299) -> 0
A300: 299 | B300: 577 | C300: ▲278 | D300: PEÑA Jesús David | E300: APHotels & Resorts / Tavira / SC Farense | F300: 218 | I300: {=INDEX('Current 2025 Points'!$F$11:$F$77,MATCH(1,MMULT(--('Current 2025 Points'!$G$11:$N$17=D300),TRANSPOSE(COLUMN('Current 2025 Points'!$G$11:$N$17)^0)),0))} -> #N/A | K300: =F300-IFERROR(VLOOKUP(D300,'Pre-transfer 2025 Ranking'!$D:$F,3,0),0) -> 98 | L300: =countif('Pre-transfer 2025 Points'!$E$11:$L$17,D300) -> 0 | M300: =countif('Current 2025 Points'!$G$11:$N$17,D300) -> 0
A301: 300 | B301: 159 | C301: ▼141 | D301: RYAN Archie | E301: EF Education - EasyPost | F301: 217 | I301: {=INDEX('Current 2025 Points'!$F$11:$F$77,MATCH(1,MMULT(--('Current 2025 Points'!$G$11:$N$17=D301),TRANSPOSE(COLUMN('Current 2025 Points'!$G$11:$N$17)^0)),0))} -> #N/A | K301: =F301-IFERROR(VLOOKUP(D301,'Pre-transfer 2025 Ranking'!$D:$F,3,0),0) -> 155 | L301: =countif('Pre-transfer 2025 Points'!$E$11:$L$17,D301) -> 0 | M301: =countif('Current 2025 Points'!$G$11:$N$17,D301) -> 0
A302: 301 | B302: 341 | C302: ▲40 | D302: CARBONI Giovanni | E302: Unibet Tietema Rockets | F302: 215 | I302: {=INDEX('Current 2025 Points'!$F$11:$F$77,MATCH(1,MMULT(--('Current 2025 Points'!$G$11:$N$17=D302),TRANSPOSE(COLUMN('Current 2025 Points'!$G$11:$N$17)^0)),0))} -> #N/A | K302: =F302-IFERROR(VLOOKUP(D302,'Pre-transfer 2025 Ranking'!$D:$F,3,0),0) -> 15 | L302: =countif('Pre-transfer 2025 Points'!$E$11:$L$17,D302) -> 0 | M302: =countif('Current 2025 Points'!$G$11:$N$17,D302) -> 0
A303: 302 | C303: ▲new | D303: FINN Lorenzo | E303: Red Bull - BORA - hansgrohe Rookies | F303: 212 | I303: {=INDEX('Current 2025 Points'!$F$11:$F$77,MATCH(1,MMULT(--('Current 2025 Points'!$G$11:$N$17=D303),TRANSPOSE(COLUMN('Current 2025 Points'!$G$11:$N$17)^0)),0))} -> #N/A | K303: =F303-IFERROR(VLOOKUP(D303,'Pre-transfer 2025 Ranking'!$D:$F,3,0),0) -> 127 | L303: =countif('Pre-transfer 2025 Points'!$E$11:$L$17,D303) -> 0 | M303: =countif('Current 2025 Points'!$G$11:$N$17,D303) -> 0
A304: 303 | B304: 162 | C304: ▼141 | D304: MOLLEMA Bauke | E304: Lidl - Trek | F304: 211 | I304: {=INDEX('Current 2025 Points'!$F$11:$F$77,MATCH(1,MMULT(--('Current 2025 Points'!$G$11:$N$17=D304),TRANSPOSE(COLUMN('Current 2025 Points'!$G$11:$N$17)^0)),0))} -> #N/A | K304: =F304-IFERROR(VLOOKUP(D304,'Pre-transfer 2025 Ranking'!$D:$F,3,0),0) -> 146 | L304: =countif('Pre-transfer 2025 Points'!$E$11:$L$17,D304) -> 0 | M304: =countif('Current 2025 Points'!$G$11:$N$17,D304) -> 0
A305: 304 | B305: 366 | C305: ▲62 | D305: BUCHMANN Emanuel | E305: Cofidis | F305: 211 | I305: {=INDEX('Current 2025 Points'!$F$11:$F$77,MATCH(1,MMULT(--('Current 2025 Points'!$G$11:$N$17=D305),TRANSPOSE(COLUMN('Current 2025 Points'!$G$11:$N$17)^0)),0))} -> #N/A | K305: =F305-IFERROR(VLOOKUP(D305,'Pre-transfer 2025 Ranking'!$D:$F,3,0),0) -> 75 | L305: =countif('Pre-transfer 2025 Points'!$E$11:$L$17,D305) -> 0 | M305: =countif('Current 2025 Points'!$G$11:$N$17,D305) -> 0
A306: 305 | B306: 265 | C306: ▼40 | D306: DEHAIRS Simon | E306: Alpecin - Deceuninck | F306: 210 | I306: {=INDEX('Current 2025 Points'!$F$11:$F$77,MATCH(1,MMULT(--('Current 2025 Points'!$G$11:$N$17=D306),TRANSPOSE(COLUMN('Current 2025 Points'!$G$11:$N$17)^0)),0))} -> #N/A | K306: =F306-IFERROR(VLOOKUP(D306,'Pre-transfer 2025 Ranking'!$D:$F,3,0),0) -> 22 | L306: =countif('Pre-transfer 2025 Points'!$E$11:$L$17,D306) -> 0 | M306: =countif('Current 2025 Points'!$G$11:$N$17,D306) -> 0
A307: 306 | B307: 21 | C307: ▼285 | D307: VLASOV Aleksandr | E307: Red Bull - BORA - hansgrohe | F307: 210 | I307: {=INDEX('Current 2025 Points'!$F$11:$F$77,MATCH(1,MMULT(--('Current 2025 Points'!$G$11:$N$17=D307),TRANSPOSE(COLUMN('Current 2025 Points'!$G$11:$N$17)^0)),0))} -> Chris | K307: =F307-IFERROR(VLOOKUP(D307,'Pre-transfer 2025 Ranking'!$D:$F,3,0),0) -> 108 | L307: =countif('Pre-transfer 2025 Points'!$E$11:$L$17,D307) -> 1 | M307: =countif('Current 2025 Points'!$G$11:$N$17,D307) -> 1
A308: 307 | B308: 282 | C308: ▼25 | D308: HALLER Marco | E308: Tudor Pro Cycling Team | F308: 209 | I308: {=INDEX('Current 2025 Points'!$F$11:$F$77,MATCH(1,MMULT(--('Current 2025 Points'!$G$11:$N$17=D308),TRANSPOSE(COLUMN('Current 2025 Points'!$G$11:$N$17)^0)),0))} -> #N/A | K308: =F308-IFERROR(VLOOKUP(D308,'Pre-transfer 2025 Ranking'!$D:$F,3,0),0) -> 101 | L308: =countif('Pre-transfer 2025 Points'!$E$11:$L$17,D308) -> 0 | M308: =countif('Current 2025 Points'!$G$11:$N$17,D308) -> 0
A309: 308 | B309: 285 | C309: ▼23 | D309: VAN MOER Brent | E309: Lotto | F309: 208 | I309: {=INDEX('Current 2025 Points'!$F$11:$F$77,MATCH(1,MMULT(--('Current 2025 Points'!$G$11:$N$17=D309),TRANSPOSE(COLUMN('Current 2025 Points'!$G$11:$N$17)^0)),0))} -> #N/A | K309: =F309-IFERROR(VLOOKUP(D309,'Pre-transfer 2025 Ranking'!$D:$F,3,0),0) -> 38 | L309: =countif('Pre-transfer 2025 Points'!$E$11:$L$17,D309) -> 0 | M309: =countif('Current 2025 Points'!$G$11:$N$17,D309) -> 0
A310: 309 | B310: 317 | C310: ▲8 | D310: PARRA José Félix | E310: Equipo Kern Pharma | F310: 207 | I310: {=INDEX('Current 2025 Points'!$F$11:$F$77,MATCH(1,MMULT(--('Current 2025 Points'!$G$11:$N$17=D310),TRANSPOSE(COLUMN('Current 2025 Points'!$G$11:$N$17)^0)),0))} -> #N/A | K310: =F310-IFERROR(VLOOKUP(D310,'Pre-transfer 2025 Ranking'!$D:$F,3,0),0) -> 49 | L310: =countif('Pre-transfer 2025 Points'!$E$11:$L$17,D310) -> 0 | M310: =countif('Current 2025 Points'!$G$11:$N$17,D310) -> 0
A311: 310 | B311: 276 | C311: ▼34 | D311: LAAS Martin | E311: Quick Pro Team | F311: 207 | I311: {=INDEX('Current 2025 Points'!$F$11:$F$77,MATCH(1,MMULT(--('Current 2025 Points'!$G$11:$N$17=D311),TRANSPOSE(COLUMN('Current 2025 Points'!$G$11:$N$17)^0)),0))} -> #N/A | K311: =F311-IFERROR(VLOOKUP(D311,'Pre-transfer 2025 Ranking'!$D:$F,3,0),0) -> 153 | L311: =countif('Pre-transfer 2025 Points'!$E$11:$L$17,D311) -> 0 | M311: =countif('Current 2025 Points'!$G$11:$N$17,D311) -> 0
A312: 311 | B312: 309 | C312: ▼2 | D312: HOWSON Damien | E312: Q36.5 Pro Cycling Team | F312: 206 | I312: {=INDEX('Current 2025 Points'!$F$11:$F$77,MATCH(1,MMULT(--('Current 2025 Points'!$G$11:$N$17=D312),TRANSPOSE(COLUMN('Current 2025 Points'!$G$11:$N$17)^0)),0))} -> #N/A | K312: =F312-IFERROR(VLOOKUP(D312,'Pre-transfer 2025 Ranking'!$D:$F,3,0),0) -> 49 | L312: =countif('Pre-transfer 2025 Points'!$E$11:$L$17,D312) -> 0 | M312: =countif('Current 2025 Points'!$G$11:$N$17,D312) -> 0
A313: 312 | B313: 620 | C313: ▲308 | D313: BREGNHØJ Mathias | E313: Terengganu Cycling Team | F313: 206 | I313: {=INDEX('Current 2025 Points'!$F$11:$F$77,MATCH(1,MMULT(--('Current 2025 Points'!$G$11:$N$17=D313),TRANSPOSE(COLUMN('Current 2025 Points'!$G$11:$N$17)^0)),0))} -> #N/A | K313: =F313-IFERROR(VLOOKUP(D313,'Pre-transfer 2025 Ranking'!$D:$F,3,0),0) -> 99 | L313: =countif('Pre-transfer 2025 Points'!$E$11:$L$17,D313) -> 0 | M313: =countif('Current 2025 Points'!$G$11:$N$17,D313) -> 0
A314: 313 | B314: 83 | C314: ▼230 | D314: THIJSSEN Gerben | E314: Intermarché - Wanty | F314: 205 | I314: {=INDEX('Current 2025 Points'!$F$11:$F$77,MATCH(1,MMULT(--('Current 2025 Points'!$G$11:$N$17=D314),TRANSPOSE(COLUMN('Current 2025 Points'!$G$11:$N$17)^0)),0))} -> #N/A | K314: =F314-IFERROR(VLOOKUP(D314,'Pre-transfer 2025 Ranking'!$D:$F,3,0),0) -> 96 | L314: =countif('Pre-transfer 2025 Points'!$E$11:$L$17,D314) -> 0 | M314: =countif('Current 2025 Points'!$G$11:$N$17,D314) -> 0
A315: 314 | B315: 235 | C315: ▼79 | D315: MEINTJES Louis | E315: Intermarché - Wanty | F315: 205 | I315: {=INDEX('Current 2025 Points'!$F$11:$F$77,MATCH(1,MMULT(--('Current 2025 Points'!$G$11:$N$17=D315),TRANSPOSE(COLUMN('Current 2025 Points'!$G$11:$N$17)^0)),0))} -> #N/A | K315: =F315-IFERROR(VLOOKUP(D315,'Pre-transfer 2025 Ranking'!$D:$F,3,0),0) -> 90 | L315: =countif('Pre-transfer 2025 Points'!$E$11:$L$17,D315) -> 0 | M315: =countif('Current 2025 Points'!$G$11:$N$17,D315) -> 0
... A320: 319 | B320: 370 | C320: ▲51 | D320: CHARMIG Anthon | E320: XDS Astana Team | F320: 200 | I320: {=INDEX('Current 2025 Points'!$F$11:$F$77,MATCH(1,MMULT(--('Current 2025 Points'!$G$11:$N$17=D320),TRANSPOSE(COLUMN('Current 2025 Points'!$G$11:$N$17)^0)),0))} -> #N/A | K320: =F320-IFERROR(VLOOKUP(D320,'Pre-transfer 2025 Ranking'!$D:$F,3,0),0) -> 126 | L320: =countif('Pre-transfer 2025 Points'!$E$11:$L$17,D320) -> 0 | M320: =countif('Current 2025 Points'!$G$11:$N$17,D320) -> 0
A321: 320 | C321: ▲new | D321: CAVIA Daniel | E321: Burgos Burpellet BH | F321: 199 | I321: {=INDEX('Current 2025 Points'!$F$11:$F$77,MATCH(1,MMULT(--('Current 2025 Points'!$G$11:$N$17=D321),TRANSPOSE(COLUMN('Current 2025 Points'!$G$11:$N$17)^0)),0))} -> #N/A | K321: =F321-IFERROR(VLOOKUP(D321,'Pre-transfer 2025 Ranking'!$D:$F,3,0),0) -> 133 | L321: =countif('Pre-transfer 2025 Points'!$E$11:$L$17,D321) -> 0 | M321: =countif('Current 2025 Points'!$G$11:$N$17,D321) -> 0
A322: 321 | B322: 346 | C322: ▲25 | D322: PINARELLO Alessandro | E322: VF Group - Bardiani CSF - Faizanè | F322: 198 | I322: {=INDEX('Current 2025 Points'!$F$11:$F$77,MATCH(1,MMULT(--('Current 2025 Points'!$G$11:$N$17=D322),TRANSPOSE(COLUMN('Current 2025 Points'!$G$11:$N$17)^0)),0))} -> #N/A | K322: =F322-IFERROR(VLOOKUP(D322,'Pre-transfer 2025 Ranking'!$D:$F,3,0),0) -> 87 | L322: =countif('Pre-transfer 2025 Points'!$E$11:$L$17,D322) -> 0 | M322: =countif('Current 2025 Points'!$G$11:$N$17,D322) -> 0
A323: 322 | B323: 536 | C323: ▲214 | D323: CHUMIL Sergio Geovani | E323: Burgos Burpellet BH | F323: 197 | I323: {=INDEX('Current 2025 Points'!$F$11:$F$77,MATCH(1,MMULT(--('Current 2025 Points'!$G$11:$N$17=D323),TRANSPOSE(COLUMN('Current 2025 Points'!$G$11:$N$17)^0)),0))} -> #N/A | K323: =F323-IFERROR(VLOOKUP(D323,'Pre-transfer 2025 Ranking'!$D:$F,3,0),0) -> 70 | L323: =countif('Pre-transfer 2025 Points'!$E$11:$L$17,D323) -> 0 | M323: =countif('Current 2025 Points'!$G$11:$N$17,D323) -> 0
A324: 323 | B324: 174 | C324: ▼149 | D324: DUNBAR Eddie | E324: Team Jayco AlUla | F324: 197 | I324: {=INDEX('Current 2025 Points'!$F$11:$F$77,MATCH(1,MMULT(--('Current 2025 Points'!$G$11:$N$17=D324),TRANSPOSE(COLUMN('Current 2025 Points'!$G$11:$N$17)^0)),0))} -> #N/A | K324: =F324-IFERROR(VLOOKUP(D324,'Pre-transfer 2025 Ranking'!$D:$F,3,0),0) -> 135 | L324: =countif('Pre-transfer 2025 Points'!$E$11:$L$17,D324) -> 0 | M324: =countif('Current 2025 Points'!$G$11:$N$17,D324) -> 0
A325: 324 | C325: ▲new | D325: OMRZEL Jakob | E325: Bahrain Victorious Development Team | F325: 195 | I325: {=INDEX('Current 2025 Points'!$F$11:$F$77,MATCH(1,MMULT(--('Current 2025 Points'!$G$11:$N$17=D325),TRANSPOSE(COLUMN('Current 2025 Points'!$G$11:$N$17)^0)),0))} -> #N/A | K325: =F325-IFERROR(VLOOKUP(D325,'Pre-transfer 2025 Ranking'!$D:$F,3,0),0) -> 49 | L325: =countif('Pre-transfer 2025 Points'!$E$11:$L$17,D325) -> 0 | M325: =countif('Current 2025 Points'!$G$11:$N$17,D325) -> 0
A326: 325 | B326: 203 | C326: ▼122 | D326: NERURKAR Lukas | E326: EF Education - EasyPost | F326: 193 | I326: {=INDEX('Current 2025 Points'!$F$11:$F$77,MATCH(1,MMULT(--('Current 2025 Points'!$G$11:$N$17=D326),TRANSPOSE(COLUMN('Current 2025 Points'!$G$11:$N$17)^0)),0))} -> #N/A | K326: =F326-IFERROR(VLOOKUP(D326,'Pre-transfer 2025 Ranking'!$D:$F,3,0),0) -> 152 | L326: =countif('Pre-transfer 2025 Points'!$E$11:$L$17,D326) -> 0 | M326: =countif('Current 2025 Points'!$G$11:$N$17,D326) -> 0
A327: 326 | B327: 181 | C327: ▼145 | D327: VAN UDEN Casper | E327: Team Picnic PostNL | F327: 193 | I327: {=INDEX('Current 2025 Points'!$F$11:$F$77,MATCH(1,MMULT(--('Current 2025 Points'!$G$11:$N$17=D327),TRANSPOSE(COLUMN('Current 2025 Points'!$G$11:$N$17)^0)),0))} -> #N/A | K327: =F327-IFERROR(VLOOKUP(D327,'Pre-transfer 2025 Ranking'!$D:$F,3,0),0) -> 11 | L327: =countif('Pre-transfer 2025 Points'!$E$11:$L$17,D327) -> 0 | M327: =countif('Current 2025 Points'!$G$11:$N$17,D327) -> 0
A328: 327 | C328: ▲new | D328: CASTELLON Jan | E328: Caja Rural - Seguros RGA | F328: 191 | I328: {=INDEX('Current 2025 Points'!$F$11:$F$77,MATCH(1,MMULT(--('Current 2025 Points'!$G$11:$N$17=D328),TRANSPOSE(COLUMN('Current 2025 Points'!$G$11:$N$17)^0)),0))} -> #N/A | K328: =F328-IFERROR(VLOOKUP(D328,'Pre-transfer 2025 Ranking'!$D:$F,3,0),0) -> 0 | L328: =countif('Pre-transfer 2025 Points'!$E$11:$L$17,D328) -> 0 | M328: =countif('Current 2025 Points'!$G$11:$N$17,D328) -> 0
A329: 328 | B329: 303 | C329: ▼25 | D329: ZANONCELLO Enrico | E329: VF Group - Bardiani CSF - Faizanè | F329: 190 | I329: {=INDEX('Current 2025 Points'!$F$11:$F$77,MATCH(1,MMULT(--('Current 2025 Points'!$G$11:$N$17=D329),TRANSPOSE(COLUMN('Current 2025 Points'!$G$11:$N$17)^0)),0))} -> #N/A | K329: =F329-IFERROR(VLOOKUP(D329,'Pre-transfer 2025 Ranking'!$D:$F,3,0),0) -> 102 | L329: =countif('Pre-transfer 2025 Points'!$E$11:$L$17,D329) -> 0 | M329: =countif('Current 2025 Points'!$G$11:$N$17,D329) -> 0
A330: 329 | B330: 225 | C330: ▼104 | D330: BRENNER Marco | E330: Tudor Pro Cycling Team | F330: 190 | I330: {=INDEX('Current 2025 Points'!$F$11:$F$77,MATCH(1,MMULT(--('Current 2025 Points'!$G$11:$N$17=D330),TRANSPOSE(COLUMN('Current 2025 Points'!$G$11:$N$17)^0)),0))} -> #N/A | K330: =F330-IFERROR(VLOOKUP(D330,'Pre-transfer 2025 Ranking'!$D:$F,3,0),0) -> 4 | L330: =countif('Pre-transfer 2025 Points'!$E$11:$L$17,D330) -> 0 | M330: =countif('Current 2025 Points'!$G$11:$N$17,D330) -> 0
A331: 330 | B331: 293 | C331: ▼37 | D331: MAGLI Filippo | E331: VF Group - Bardiani CSF - Faizanè | F331: 190 | I331: {=INDEX('Current 2025 Points'!$F$11:$F$77,MATCH(1,MMULT(--('Current 2025 Points'!$G$11:$N$17=D331),TRANSPOSE(COLUMN('Current 2025 Points'!$G$11:$N$17)^0)),0))} -> #N/A | K331: =F331-IFERROR(VLOOKUP(D331,'Pre-transfer 2025 Ranking'!$D:$F,3,0),0) -> 110 | L331: =countif('Pre-transfer 2025 Points'!$E$11:$L$17,D331) -> 0 | M331: =countif('Current 2025 Points'!$G$11:$N$17,D331) -> 0
A332: 331 | B332: 390 | C332: ▲59 | D332: EIKING Odd Christian | E332: Unibet Tietema Rockets | F332: 190 | I332: {=INDEX('Current 2025 Points'!$F$11:$F$77,MATCH(1,MMULT(--('Current 2025 Points'!$G$11:$N$17=D332),TRANSPOSE(COLUMN('Current 2025 Points'!$G$11:$N$17)^0)),0))} -> #N/A | K332: =F332-IFERROR(VLOOKUP(D332,'Pre-transfer 2025 Ranking'!$D:$F,3,0),0) -> 84 | L332: =countif('Pre-transfer 2025 Points'!$E$11:$L$17,D332) -> 0 | M332: =countif('Current 2025 Points'!$G$11:$N$17,D332) -> 0
A333: 332 | B333: 786 | C333: ▲454 | D333: PELLAUD Simon | E333: Li Ning Star | F333: 189 | I333: {=INDEX('Current 2025 Points'!$F$11:$F$77,MATCH(1,MMULT(--('Current 2025 Points'!$G$11:$N$17=D333),TRANSPOSE(COLUMN('Current 2025 Points'!$G$11:$N$17)^0)),0))} -> #N/A | K333: =F333-IFERROR(VLOOKUP(D333,'Pre-transfer 2025 Ranking'!$D:$F,3,0),0) -> 99 | L333: =countif('Pre-transfer 2025 Points'!$E$11:$L$17,D333) -> 0 | M333: =countif('Current 2025 Points'!$G$11:$N$17,D333) -> 0
A334: 333 | B334: 216 | C334: ▼117 | D334: CAPIOT Amaury | E334: Arkéa - B&B Hotels | F334: 188 | I334: {=INDEX('Current 2025 Points'!$F$11:$F$77,MATCH(1,MMULT(--('Current 2025 Points'!$G$11:$N$17=D334),TRANSPOSE(COLUMN('Current 2025 Points'!$G$11:$N$17)^0)),0))} -> #N/A | K334: =F334-IFERROR(VLOOKUP(D334,'Pre-transfer 2025 Ranking'!$D:$F,3,0),0) -> 51 | L334: =countif('Pre-transfer 2025 Points'!$E$11:$L$17,D334) -> 0 | M334: =countif('Current 2025 Points'!$G$11:$N$17,D334) -> 0
A335: 334 | B335: 263 | C335: ▼71 | D335: BUSATTO Francesco | E335: Intermarché - Wanty | F335: 188 | I335: {=INDEX('Current 2025 Points'!$F$11:$F$77,MATCH(1,MMULT(--('Current 2025 Points'!$G$11:$N$17=D335),TRANSPOSE(COLUMN('Current 2025 Points'!$G$11:$N$17)^0)),0))} -> #N/A | K335: =F335-IFERROR(VLOOKUP(D335,'Pre-transfer 2025 Ranking'!$D:$F,3,0),0) -> 69 | L335: =countif('Pre-transfer 2025 Points'!$E$11:$L$17,D335) -> 0 | M335: =countif('Current 2025 Points'!$G$11:$N$17,D335) -> 0
A336: 335 | B336: 753 | C336: ▲418 | D336: DOUBEY Fabien | E336: Team TotalEnergies | F336: 188 | I336: {=INDEX('Current 2025 Points'!$F$11:$F$77,MATCH(1,MMULT(--('Current 2025 Points'!$G$11:$N$17=D336),TRANSPOSE(COLUMN('Current 2025 Points'!$G$11:$N$17)^0)),0))} -> #N/A | K336: =F336-IFERROR(VLOOKUP(D336,'Pre-transfer 2025 Ranking'!$D:$F,3,0),0) -> 18 | L336: =countif('Pre-transfer 2025 Points'!$E$11:$L$17,D336) -> 0 | M336: =countif('Current 2025 Points'!$G$11:$N$17,D336) -> 0
A337: 336 | B337: 421 | C337: ▲85 | D337: GALVÁN Francisco | E337: Equipo Kern Pharma | F337: 187 | I337: {=INDEX('Current 2025 Points'!$F$11:$F$77,MATCH(1,MMULT(--('Current 2025 Points'!$G$11:$N$17=D337),TRANSPOSE(COLUMN('Current 2025 Points'!$G$11:$N$17)^0)),0))} -> #N/A | K337: =F337-IFERROR(VLOOKUP(D337,'Pre-transfer 2025 Ranking'!$D:$F,3,0),0) -> 16 | L337: =countif('Pre-transfer 2025 Points'!$E$11:$L$17,D337) -> 0 | M337: =countif('Current 2025 Points'!$G$11:$N$17,D337) -> 0
A338: 337 | B338: 500 | C338: ▲163 | D338: LIVYNS Arjen | E338: Lotto | F338: 187 | I338: {=INDEX('Current 2025 Points'!$F$11:$F$77,MATCH(1,MMULT(--('Current 2025 Points'!$G$11:$N$17=D338),TRANSPOSE(COLUMN('Current 2025 Points'!$G$11:$N$17)^0)),0))} -> #N/A | K338: =F338-IFERROR(VLOOKUP(D338,'Pre-transfer 2025 Ranking'!$D:$F,3,0),0) -> 15 | L338: =countif('Pre-transfer 2025 Points'!$E$11:$L$17,D338) -> 0 | M338: =countif('Current 2025 Points'!$G$11:$N$17,D338) -> 0
...

Sheet Pre-transfer 2025 Points
A1: Team | B1: Rank | C1: Null | D1: Points
A2: Nick | B2: =rank(D2,D$2:D$8) -> 6 | C2: =countif(E2:L2, 0) -> 0 | D2: =sum(E2:L2) -> 3619 | E2: =IFERROR(VLOOKUP(E11,'Pre-transfer 2025 Ranking'!$D:$F,3,0),0) -> 389 | F2: =IFERROR(VLOOKUP(F11,'Pre-transfer 2025 Ranking'!$D:$F,3,0),0) -> 573 | G2: =IFERROR(VLOOKUP(G11,'Pre-transfer 2025 Ranking'!$D:$F,3,0),0) -> 612 | H2: =IFERROR(VLOOKUP(H11,'Pre-transfer 2025 Ranking'!$D:$F,3,0),0) -> 70 | I2: =IFERROR(VLOOKUP(I11,'Pre-transfer 2025 Ranking'!$D:$F,3,0),0) -> 310 | J2: =IFERROR(VLOOKUP(J11,'Pre-transfer 2025 Ranking'!$D:$F,3,0),0) -> 10 | K2: =IFERROR(VLOOKUP(K11,'Pre-transfer 2025 Ranking'!$D:$F,3,0),0) -> 1042 | L2: =IFERROR(VLOOKUP(L11,'Pre-transfer 2025 Ranking'!$D:$F,3,0),0) -> 613
A3: Tim | B3: =rank(D3,D$2:D$8) -> 5 | C3: =countif(E3:L3, 0) -> 0 | D3: =sum(E3:L3) -> 4074 | E3: =IFERROR(VLOOKUP(E12,'Pre-transfer 2025 Ranking'!$D:$F,3,0),0) -> 468 | F3: =IFERROR(VLOOKUP(F12,'Pre-transfer 2025 Ranking'!$D:$F,3,0),0) -> 606 | G3: =IFERROR(VLOOKUP(G12,'Pre-transfer 2025 Ranking'!$D:$F,3,0),0) -> 407 | H3: =IFERROR(VLOOKUP(H12,'Pre-transfer 2025 Ranking'!$D:$F,3,0),0) -> 332 | I3: =IFERROR(VLOOKUP(I12,'Pre-transfer 2025 Ranking'!$D:$F,3,0),0) -> 355 | J3: =IFERROR(VLOOKUP(J12,'Pre-transfer 2025 Ranking'!$D:$F,3,0),0) -> 238 | K3: =IFERROR(VLOOKUP(K12,'Pre-transfer 2025 Ranking'!$D:$F,3,0),0) -> 788 | L3: =IFERROR(VLOOKUP(L12,'Pre-transfer 2025 Ranking'!$D:$F,3,0),0) -> 880
A4: Cameron | B4: =rank(D4,D$2:D$8) -> 7 | C4: =countif(E4:L4, 0) -> 0 | D4: =sum(E4:L4) -> 2974 | E4: =IFERROR(VLOOKUP(E13,'Pre-transfer 2025 Ranking'!$D:$F,3,0),0) -> 165 | F4: =IFERROR(VLOOKUP(F13,'Pre-transfer 2025 Ranking'!$D:$F,3,0),0) -> 728 | G4: =IFERROR(VLOOKUP(G13,'Pre-transfer 2025 Ranking'!$D:$F,3,0),0) -> 558 | H4: =IFERROR(VLOOKUP(H13,'Pre-transfer 2025 Ranking'!$D:$F,3,0),0) -> 224 | I4: =IFERROR(VLOOKUP(I13,'Pre-transfer 2025 Ranking'!$D:$F,3,0),0) -> 273 | J4: =IFERROR(VLOOKUP(J13,'Pre-transfer 2025 Ranking'!$D:$F,3,0),0) -> 67 | K4: =IFERROR(VLOOKUP(K13,'Pre-transfer 2025 Ranking'!$D:$F,3,0),0) -> 505 | L4: =IFERROR(VLOOKUP(L13,'Pre-transfer 2025 Ranking'!$D:$F,3,0),0) -> 454
A5: Chris | B5: =rank(D5,D$2:D$8) -> 2 | C5: =countif(E5:L5, 0) -> 0 | D5: =sum(E5:L5) -> 5485 | E5: =IFERROR(VLOOKUP(E14,'Pre-transfer 2025 Ranking'!$D:$F,3,0),0) -> 1634 | F5: =IFERROR(VLOOKUP(F14,'Pre-transfer 2025 Ranking'!$D:$F,3,0),0) -> 799 | G5: =IFERROR(VLOOKUP(G14,'Pre-transfer 2025 Ranking'!$D:$F,3,0),0) -> 419 | H5: =IFERROR(VLOOKUP(H14,'Pre-transfer 2025 Ranking'!$D:$F,3,0),0) -> 102 | I5: =IFERROR(VLOOKUP(I14,'Pre-transfer 2025 Ranking'!$D:$F,3,0),0) -> 633 | J5: =IFERROR(VLOOKUP(J14,'Pre-transfer 2025 Ranking'!$D:$F,3,0),0) -> 273 | K5: =IFERROR(VLOOKUP(K14,'Pre-transfer 2025 Ranking'!$D:$F,3,0),0) -> 989 | L5: =IFERROR(VLOOKUP(L14,'Pre-transfer 2025 Ranking'!$D:$F,3,0),0) -> 636
A6: Dave | B6: =rank(D6,D$2:D$8) -> 3 | C6: =countif(E6:L6, 0) -> 0 | D6: =sum(E6:L6) -> 4972 | E6: =IFERROR(VLOOKUP(E15,'Pre-transfer 2025 Ranking'!$D:$F,3,0),0) -> 859 | F6: =IFERROR(VLOOKUP(F15,'Pre-transfer 2025 Ranking'!$D:$F,3,0),0) -> 1113 | G6: =IFERROR(VLOOKUP(G15,'Pre-transfer 2025 Ranking'!$D:$F,3,0),0) -> 650 | H6: =IFERROR(VLOOKUP(H15,'Pre-transfer 2025 Ranking'!$D:$F,3,0),0) -> 326 | I6: =IFERROR(VLOOKUP(I15,'Pre-transfer 2025 Ranking'!$D:$F,3,0),0) -> 322 | J6: =IFERROR(VLOOKUP(J15,'Pre-transfer 2025 Ranking'!$D:$F,3,0),0) -> 229 | K6: =IFERROR(VLOOKUP(K15,'Pre-transfer 2025 Ranking'!$D:$F,3,0),0) -> 753 | L6: =IFERROR(VLOOKUP(L15,'Pre-transfer 2025 Ranking'!$D:$F,3,0),0) -> 720
A7: Mike | B7: =rank(D7,D$2:D$8) -> 1 | C7: =countif(E7:L7, 0) -> 0 | D7: =sum(E7:L7) -> 5616 | E7: =IFERROR(VLOOKUP(E16,'Pre-transfer 2025 Ranking'!$D:$F,3,0),0) -> 200 | F7: =IFERROR(VLOOKUP(F16,'Pre-transfer 2025 Ranking'!$D:$F,3,0),0) -> 1632 | G7: =IFERROR(VLOOKUP(G16,'Pre-transfer 2025 Ranking'!$D:$F,3,0),0) -> 694 | H7: =IFERROR(VLOOKUP(H16,'Pre-transfer 2025 Ranking'!$D:$F,3,0),0) -> 533 | I7: =IFERROR(VLOOKUP(I16,'Pre-transfer 2025 Ranking'!$D:$F,3,0),0) -> 590 | J7: =IFERROR(VLOOKUP(J16,'Pre-transfer 2025 Ranking'!$D:$F,3,0),0) -> 374 | K7: =IFERROR(VLOOKUP(K16,'Pre-transfer 2025 Ranking'!$D:$F,3,0),0) -> 607 | L7: =IFERROR(VLOOKUP(L16,'Pre-transfer 2025 Ranking'!$D:$F,3,0),0) -> 986
A8: Andy | B8: =rank(D8,D$2:D$8) -> 4 | C8: =countif(E8:L8, 0) -> 0 | D8: =sum(E8:L8) -> 4578 | E8: =IFERROR(VLOOKUP(E17,'Pre-transfer 2025 Ranking'!$D:$F,3,0),0) -> 2300 | F8: =IFERROR(VLOOKUP(F17,'Pre-transfer 2025 Ranking'!$D:$F,3,0),0) -> 197 | G8: =IFERROR(VLOOKUP(G17,'Pre-transfer 2025 Ranking'!$D:$F,3,0),0) -> 177 | H8: =IFERROR(VLOOKUP(H17,'Pre-transfer 2025 Ranking'!$D:$F,3,0),0) -> 126 | I8: =IFERROR(VLOOKUP(I17,'Pre-transfer 2025 Ranking'!$D:$F,3,0),0) -> 264 | J8: =IFERROR(VLOOKUP(J17,'Pre-transfer 2025 Ranking'!$D:$F,3,0),0) -> 326 | K8: =IFERROR(VLOOKUP(K17,'Pre-transfer 2025 Ranking'!$D:$F,3,0),0) -> 457 | L8: =IFERROR(VLOOKUP(L17,'Pre-transfer 2025 Ranking'!$D:$F,3,0),0) -> 731
D10: Manager | E10: 1 | F10: 2 | G10: 3 | H10: 4 | I10: 5 | J10: 6 | K10: 7 | L10: 8
A11: =D11 -> Nick | D11: Nick | E11: NARVÁEZ Jhonatan | F11: VINGEGAARD Jonas | G11: CARAPAZ Richard | H11: EWAN Caleb | I11: O'CONNOR Ben | J11: WILLIAMS Stephen | K11: PIDCOCK Thomas | L11: MAS Enric
A12: =D12 -> Tim | D12: Tim | E12: GIRMAY Biniam | F12: PHILIPSEN Jasper | G12: MCNULTY Brandon | H12: HIRSCHI Marc | I12: VAN EETVELT Lennert | J12: VAN GILS Maxim | K12: GANNA Filippo | L12: ONLEY Oscar
A13: =D13 -> Cameron | D13: Cameron | E13: GAUDU David | F13: EVENEPOEL Remco | G13: MATTHEWS Michael | H13: BARDET Romain | I13: COSNEFROY Benoît | J13: ABRAHAMSEN Jonas | K13: SHEFFIELD Magnus | L13: ARENSMAN Thymen
A14: =D14 -> Chris | D14: Chris | E14: ALMEIDA João | F14: MERLIER Tim | G14: YATES Adam | H14: VLASOV Aleksandr | I14: JORGENSON Matteo | J14: RODRÍGUEZ Carlos | K14: AYUSO Juan | L14: YATES Simon
A15: =D15 -> Dave | D15: Dave | E15: VAN AERT Wout | F15: VAN DER POEL Mathieu | G15: POWLESS Neilson | H15: GROENEWEGEN Dylan | I15: LANDA Mikel | J15: KÜNG Stefan | K15: MARTINEZ Lenny | L15: CICCONE Giulio
A16: =D16 -> Mike | D16: Mike | E16: DE LIE Arnaud | F16: PEDERSEN Mads | G16: MILAN Jonathan | H16: ROGLIČ Primož | I16: SKJELMOSE Mattias | J16: NYS Thibau | K16: KOOIJ Olav | L16: DEL TORO Isaac
A17: =D17 -> Andy | D17: Andy | E17: POGAČAR Tadej | F17: PITHIE Laurence | G17: MADOUAS Valentin | H17: MOHORIČ Matej | I17: HINDLEY Jai | J17: GROENEWEGEN Dylan | K17: CORT Magnus | L17: GEE Derek

Sheet Pre-transfer 2025 Ranking
A1: Rank | B1: Prev. Rank | C1: Rank Diff. | D1: Rider | E1: Team | F1: Points | I1: Manager
A2: 1 | B2: 1 | C2: - | D2: POGAČAR Tadej | E2: UAE Team Emirates - XRG | F2: 2300 | I2: {=INDEX('Pre-transfer 2025 Points'!$D$11:$D$17,MATCH(1,MMULT(--('Pre-transfer 2025 Points'!$E$11:$L$17=D2),TRANSPOSE(COLUMN('Pre-transfer 2025 Points'!$E$11:$L$17)^0)),0))} -> Andy
A3: 2 | B3: 26 | C3: ▲24 | D3: ALMEIDA João | E3: UAE Team Emirates - XRG | F3: 1634 | I3: {=INDEX('Pre-transfer 2025 Points'!$D$11:$D$17,MATCH(1,MMULT(--('Pre-transfer 2025 Points'!$E$11:$L$17=D3),TRANSPOSE(COLUMN('Pre-transfer 2025 Points'!$E$11:$L$17)^0)),0))} -> Chris
A4: 3 | B4: 11 | C4: ▲8 | D4: PEDERSEN Mads | E4: Lidl - Trek | F4: 1632 | I4: {=INDEX('Pre-transfer 2025 Points'!$D$11:$D$17,MATCH(1,MMULT(--('Pre-transfer 2025 Points'!$E$11:$L$17=D4),TRANSPOSE(COLUMN('Pre-transfer 2025 Points'!$E$11:$L$17)^0)),0))} -> Mike
A5: 4 | B5: 8 | C5: ▲4 | D5: VAN DER POEL Mathieu | E5: Alpecin - Deceuninck | F5: 1113 | I5: {=INDEX('Pre-transfer 2025 Points'!$D$11:$D$17,MATCH(1,MMULT(--('Pre-transfer 2025 Points'!$E$11:$L$17=D5),TRANSPOSE(COLUMN('Pre-transfer 2025 Points'!$E$11:$L$17)^0)),0))} -> Dave
A6: 5 | B6: 30 | C6: ▲25 | D6: PIDCOCK Thomas | E6: Q36.5 Pro Cycling Team | F6: 1042 | I6: {=INDEX('Pre-transfer 2025 Points'!$D$11:$D$17,MATCH(1,MMULT(--('Pre-transfer 2025 Points'!$E$11:$L$17=D6),TRANSPOSE(COLUMN('Pre-transfer 2025 Points'!$E$11:$L$17)^0)),0))} -> Nick
A7: 6 | B7: 20 | C7: ▲14 | D7: AYUSO Juan | E7: UAE Team Emirates - XRG | F7: 989 | I7: {=INDEX('Pre-transfer 2025 Points'!$D$11:$D$17,MATCH(1,MMULT(--('Pre-transfer 2025 Points'!$E$11:$L$17=D7),TRANSPOSE(COLUMN('Pre-transfer 2025 Points'!$E$11:$L$17)^0)),0))} -> Chris
A8: 7 | B8: 48 | C8: ▲41 | D8: DEL TORO Isaac | E8: UAE Team Emirates - XRG | F8: 986 | I8: {=INDEX('Pre-transfer 2025 Points'!$D$11:$D$17,MATCH(1,MMULT(--('Pre-transfer 2025 Points'!$E$11:$L$17=D8),TRANSPOSE(COLUMN('Pre-transfer 2025 Points'!$E$11:$L$17)^0)),0))} -> Mike
A9: 8 | B9: 69 | C9: ▲61 | D9: VAUQUELIN Kévin | E9: Arkéa - B&B Hotels | F9: 939 | I9: {=INDEX('Pre-transfer 2025 Points'!$D$11:$D$17,MATCH(1,MMULT(--('Pre-transfer 2025 Points'!$E$11:$L$17=D9),TRANSPOSE(COLUMN('Pre-transfer 2025 Points'!$E$11:$L$17)^0)),0))} -> #N/A
A10: 9 | B10: 37 | C10: ▲28 | D10: ONLEY Oscar | E10: Team Picnic PostNL | F10: 880 | I10: {=INDEX('Pre-transfer 2025 Points'!$D$11:$D$17,MATCH(1,MMULT(--('Pre-transfer 2025 Points'!$E$11:$L$17=D10),TRANSPOSE(COLUMN('Pre-transfer 2025 Points'!$E$11:$L$17)^0)),0))} -> Tim
A11: 10 | B11: 13 | C11: ▲3 | D11: VAN AERT Wout | E11: Team Visma | Lease a Bike | F11: 859 | I11: {=INDEX('Pre-transfer 2025 Points'!$D$11:$D$17,MATCH(1,MMULT(--('Pre-transfer 2025 Points'!$E$11:$L$17=D11),TRANSPOSE(COLUMN('Pre-transfer 2025 Points'!$E$11:$L$17)^0)),0))} -> Dave
A12: 11 | B12: 10 | C12: ▼1 | D12: MERLIER Tim | E12: Soudal Quick-Step | F12: 799 | I12: {=INDEX('Pre-transfer 2025 Points'!$D$11:$D$17,MATCH(1,MMULT(--('Pre-transfer 2025 Points'!$E$11:$L$17=D12),TRANSPOSE(COLUMN('Pre-transfer 2025 Points'!$E$11:$L$17)^0)),0))} -> Chris
A13: 12 | B13: 71 | C13: ▲59 | D13: GANNA Filippo | E13: INEOS Grenadiers | F13: 788 | I13: {=INDEX('Pre-transfer 2025 Points'!$D$11:$D$17,MATCH(1,MMULT(--('Pre-transfer 2025 Points'!$E$11:$L$17=D13),TRANSPOSE(COLUMN('Pre-transfer 2025 Points'!$E$11:$L$17)^0)),0))} -> Tim
... A132: 131 | B132: 202 | C132: ▲71 | D132: PLAPP Luke | E132: Team Jayco AlUla | F132: 265 | I132: {=INDEX('Pre-transfer 2025 Points'!$D$11:$D$17,MATCH(1,MMULT(--('Pre-transfer 2025 Points'!$E$11:$L$17=D132),TRANSPOSE(COLUMN('Pre-transfer 2025 Points'!$E$11:$L$17)^0)),0))} -> #N/A
A133: 132 | C133: ▲new | D133: SEIXAS Paul | E133: Decathlon AG2R La Mondiale Team | F133: 265 | I133: {=INDEX('Pre-transfer 2025 Points'!$D$11:$D$17,MATCH(1,MMULT(--('Pre-transfer 2025 Points'!$E$11:$L$17=D133),TRANSPOSE(COLUMN('Pre-transfer 2025 Points'!$E$11:$L$17)^0)),0))} -> #N/A
A134: 133 | B134: 95 | C134: ▼38 | D134: HINDLEY Jai | E134: Red Bull - BORA - hansgrohe | F134: 264 | I134: {=INDEX('Pre-transfer 2025 Points'!$D$11:$D$17,MATCH(1,MMULT(--('Pre-transfer 2025 Points'!$E$11:$L$17=D134),TRANSPOSE(COLUMN('Pre-transfer 2025 Points'!$E$11:$L$17)^0)),0))} -> Andy
A135: 134 | B135: 121 | C135: ▼13 | D135: VAN POPPEL Danny | E135: Red Bull - BORA - hansgrohe | F135: 262 | I135: {=INDEX('Pre-transfer 2025 Points'!$D$11:$D$17,MATCH(1,MMULT(--('Pre-transfer 2025 Points'!$E$11:$L$17=D135),TRANSPOSE(COLUMN('Pre-transfer 2025 Points'!$E$11:$L$17)^0)),0))} -> #N/A
A136: 135 | B136: 117 | C136: ▼18 | D136: BAUHAUS Phil | E136: Bahrain - Victorious | F136: 261 | I136: {=INDEX('Pre-transfer 2025 Points'!$D$11:$D$17,MATCH(1,MMULT(--('Pre-transfer 2025 Points'!$E$11:$L$17=D136),TRANSPOSE(COLUMN('Pre-transfer 2025 Points'!$E$11:$L$17)^0)),0))} -> #N/A
A137: 136 | B137: 411 | C137: ▲275 | D137: BARRENETXEA Jon | E137: Movistar Team | F137: 261 | I137: {=INDEX('Pre-transfer 2025 Points'!$D$11:$D$17,MATCH(1,MMULT(--('Pre-transfer 2025 Points'!$E$11:$L$17=D137),TRANSPOSE(COLUMN('Pre-transfer 2025 Points'!$E$11:$L$17)^0)),0))} -> #N/A
A138: 137 | B138: 132 | C138: ▼5 | D138: TARLING Joshua | E138: INEOS Grenadiers | F138: 260 | I138: {=INDEX('Pre-transfer 2025 Points'!$D$11:$D$17,MATCH(1,MMULT(--('Pre-transfer 2025 Points'!$E$11:$L$17=D138),TRANSPOSE(COLUMN('Pre-transfer 2025 Points'!$E$11:$L$17)^0)),0))} -> #N/A
A139: 138 | B139: 255 | C139: ▲117 | D139: HARPER Chris | E139: Team Jayco AlUla | F139: 259 | I139: {=INDEX('Pre-transfer 2025 Points'!$D$11:$D$17,MATCH(1,MMULT(--('Pre-transfer 2025 Points'!$E$11:$L$17=D139),TRANSPOSE(COLUMN('Pre-transfer 2025 Points'!$E$11:$L$17)^0)),0))} -> #N/A
A140: 139 | B140: 249 | C140: ▲110 | D140: PLUIMERS Rick | E140: Tudor Pro Cycling Team | F140: 258 | I140: {=INDEX('Pre-transfer 2025 Points'!$D$11:$D$17,MATCH(1,MMULT(--('Pre-transfer 2025 Points'!$E$11:$L$17=D140),TRANSPOSE(COLUMN('Pre-transfer 2025 Points'!$E$11:$L$17)^0)),0))} -> #N/A
A141: 140 | B141: 111 | C141: ▼29 | D141: PARET-PEINTRE Aurélien | E141: Decathlon AG2R La Mondiale Team | F141: 254 | I141: {=INDEX('Pre-transfer 2025 Points'!$D$11:$D$17,MATCH(1,MMULT(--('Pre-transfer 2025 Points'!$E$11:$L$17=D141),TRANSPOSE(COLUMN('Pre-transfer 2025 Points'!$E$11:$L$17)^0)),0))} -> #N/A
A142: 141 | B142: 130 | C142: ▼11 | D142: DE PLUS Laurens | E142: INEOS Grenadiers | F142: 254 | I142: {=INDEX('Pre-transfer 2025 Points'!$D$11:$D$17,MATCH(1,MMULT(--('Pre-transfer 2025 Points'!$E$11:$L$17=D142),TRANSPOSE(COLUMN('Pre-transfer 2025 Points'!$E$11:$L$17)^0)),0))} -> #N/A
A143: 142 | B143: 136 | C143: ▼6 | D143: VENTURINI Clément | E143: Arkéa - B&B Hotels | F143: 253 | I143: {=INDEX('Pre-transfer 2025 Points'!$D$11:$D$17,MATCH(1,MMULT(--('Pre-transfer 2025 Points'!$E$11:$L$17=D143),TRANSPOSE(COLUMN('Pre-transfer 2025 Points'!$E$11:$L$17)^0)),0))} -> #N/A
A144: 143 | B144: 168 | C144: ▲25 | D144: ZIMMERMANN Georg | E144: Intermarché - Wanty | F144: 249 | I144: {=INDEX('Pre-transfer 2025 Points'!$D$11:$D$17,MATCH(1,MMULT(--('Pre-transfer 2025 Points'!$E$11:$L$17=D144),TRANSPOSE(COLUMN('Pre-transfer 2025 Points'!$E$11:$L$17)^0)),0))} -> #N/A
A145: 144 | B145: 187 | C145: ▲43 | D145: BARONCINI Filippo | E145: UAE Team Emirates - XRG | F145: 249 | I145: {=INDEX('Pre-transfer 2025 Points'!$D$11:$D$17,MATCH(1,MMULT(--('Pre-transfer 2025 Points'!$E$11:$L$17=D145),TRANSPOSE(COLUMN('Pre-transfer 2025 Points'!$E$11:$L$17)^0)),0))} -> #N/A
... A148: 147 | B148: 374 | C148: ▲227 | D148: DE LA CRUZ David | E148: Q36.5 Pro Cycling Team | F148: 248 | I148: {=INDEX('Pre-transfer 2025 Points'!$D$11:$D$17,MATCH(1,MMULT(--('Pre-transfer 2025 Points'!$E$11:$L$17=D148),TRANSPOSE(COLUMN('Pre-transfer 2025 Points'!$E$11:$L$17)^0)),0))} -> #N/A
A149: 148 | C149: ▲new | D149: WITHEN PHILIPSEN Albert | E149: Lidl - Trek | F149: 246 | I149: {=INDEX('Pre-transfer 2025 Points'!$D$11:$D$17,MATCH(1,MMULT(--('Pre-transfer 2025 Points'!$E$11:$L$17=D149),TRANSPOSE(COLUMN('Pre-transfer 2025 Points'!$E$11:$L$17)^0)),0))} -> #N/A
A150: 149 | B150: 439 | C150: ▲290 | D150: STORK Florian | E150: Tudor Pro Cycling Team | F150: 246 | I150: {=INDEX('Pre-transfer 2025 Points'!$D$11:$D$17,MATCH(1,MMULT(--('Pre-transfer 2025 Points'!$E$11:$L$17=D150),TRANSPOSE(COLUMN('Pre-transfer 2025 Points'!$E$11:$L$17)^0)),0))} -> #N/A
A151: 150 | B151: 356 | C151: ▲206 | D151: HAYTER Ethan | E151: Soudal Quick-Step | F151: 245 | I151: {=INDEX('Pre-transfer 2025 Points'!$D$11:$D$17,MATCH(1,MMULT(--('Pre-transfer 2025 Points'!$E$11:$L$17=D151),TRANSPOSE(COLUMN('Pre-transfer 2025 Points'!$E$11:$L$17)^0)),0))} -> #N/A
A152: 151 | B152: 256 | C152: ▲105 | D152: DÍAZ José Manuel | E152: Burgos Burpellet BH | F152: 241 | I152: {=INDEX('Pre-transfer 2025 Points'!$D$11:$D$17,MATCH(1,MMULT(--('Pre-transfer 2025 Points'!$E$11:$L$17=D152),TRANSPOSE(COLUMN('Pre-transfer 2025 Points'!$E$11:$L$17)^0)),0))} -> #N/A
A153: 152 | B153: 578 | C153: ▲426 | D153: QUARTUCCI Lorenzo | E153: Team Solution Tech - Vini Fantini | F153: 239 | I153: {=INDEX('Pre-transfer 2025 Points'!$D$11:$D$17,MATCH(1,MMULT(--('Pre-transfer 2025 Points'!$E$11:$L$17=D153),TRANSPOSE(COLUMN('Pre-transfer 2025 Points'!$E$11:$L$17)^0)),0))} -> #N/A
A154: 153 | B154: 107 | C154: ▼46 | D154: STUYVEN Jasper | E154: Lidl - Trek | F154: 239 | I154: {=INDEX('Pre-transfer 2025 Points'!$D$11:$D$17,MATCH(1,MMULT(--('Pre-transfer 2025 Points'!$E$11:$L$17=D154),TRANSPOSE(COLUMN('Pre-transfer 2025 Points'!$E$11:$L$17)^0)),0))} -> #N/A
A155: 154 | B155: 777 | C155: ▲623 | D155: SALBY Alexander | E155: Li Ning Star | F155: 239 | I155: {=INDEX('Pre-transfer 2025 Points'!$D$11:$D$17,MATCH(1,MMULT(--('Pre-transfer 2025 Points'!$E$11:$L$17=D155),TRANSPOSE(COLUMN('Pre-transfer 2025 Points'!$E$11:$L$17)^0)),0))} -> #N/A
A156: 155 | B156: 22 | C156: ▼133 | D156: VAN GILS Maxim | E156: Red Bull - BORA - hansgrohe | F156: 238 | I156: {=INDEX('Pre-transfer 2025 Points'!$D$11:$D$17,MATCH(1,MMULT(--('Pre-transfer 2025 Points'!$E$11:$L$17=D156),TRANSPOSE(COLUMN('Pre-transfer 2025 Points'!$E$11:$L$17)^0)),0))} -> Tim
A157: 156 | B157: 1279 | C157: ▲1123 | D157: GILMORE Brady | E157: Israel Premier Tech Academy | F157: 237 | I157: {=INDEX('Pre-transfer 2025 Points'!$D$11:$D$17,MATCH(1,MMULT(--('Pre-transfer 2025 Points'!$E$11:$L$17=D157),TRANSPOSE(COLUMN('Pre-transfer 2025 Points'!$E$11:$L$17)^0)),0))} -> #N/A
A158: 157 | B158: 623 | C158: ▲466 | D158: TSARENKO Kyrylo | E158: Team Solution Tech - Vini Fantini | F158: 237 | I158: {=INDEX('Pre-transfer 2025 Points'!$D$11:$D$17,MATCH(1,MMULT(--('Pre-transfer 2025 Points'!$E$11:$L$17=D158),TRANSPOSE(COLUMN('Pre-transfer 2025 Points'!$E$11:$L$17)^0)),0))} -> #N/A
A159: 158 | B159: 38 | C159: ▼120 | D159: ALAPHILIPPE Julian | E159: Tudor Pro Cycling Team | F159: 235 | I159: {=INDEX('Pre-transfer 2025 Points'!$D$11:$D$17,MATCH(1,MMULT(--('Pre-transfer 2025 Points'!$E$11:$L$17=D159),TRANSPOSE(COLUMN('Pre-transfer 2025 Points'!$E$11:$L$17)^0)),0))} -> #N/A
A160: 159 | B160: 257 | C160: ▲98 | D160: FEDOROV Yevgeniy | E160: XDS Astana Team | F160: 233 | I160: {=INDEX('Pre-transfer 2025 Points'!$D$11:$D$17,MATCH(1,MMULT(--('Pre-transfer 2025 Points'!$E$11:$L$17=D160),TRANSPOSE(COLUMN('Pre-transfer 2025 Points'!$E$11:$L$17)^0)),0))} -> #N/A
A161: 160 | B161: 122 | C161: ▼38 | D161: GODON Dorian | E161: Decathlon AG2R La Mondiale Team | F161: 232 | I161: {=INDEX('Pre-transfer 2025 Points'!$D$11:$D$17,MATCH(1,MMULT(--('Pre-transfer 2025 Points'!$E$11:$L$17=D161),TRANSPOSE(COLUMN('Pre-transfer 2025 Points'!$E$11:$L$17)^0)),0))} -> #N/A
... A173: 172 | B173: 129 | C173: ▼44 | D173: DELETTRE Alexandre | E173: Team TotalEnergies | F173: 225 | I173: {=INDEX('Pre-transfer 2025 Points'!$D$11:$D$17,MATCH(1,MMULT(--('Pre-transfer 2025 Points'!$E$11:$L$17=D173),TRANSPOSE(COLUMN('Pre-transfer 2025 Points'!$E$11:$L$17)^0)),0))} -> #N/A
A174: 173 | B174: 40 | C174: ▼134 | D174: BARDET Romain | F174: 224 | I174: {=INDEX('Pre-transfer 2025 Points'!$D$11:$D$17,MATCH(1,MMULT(--('Pre-transfer 2025 Points'!$E$11:$L$17=D174),TRANSPOSE(COLUMN('Pre-transfer 2025 Points'!$E$11:$L$17)^0)),0))} -> Cameron
A175: 174 | B175: 262 | C175: ▲87 | D175: MALUCELLI Matteo | E175: XDS Astana Team | F175: 223 | I175: {=INDEX('Pre-transfer 2025 Points'!$D$11:$D$17,MATCH(1,MMULT(--('Pre-transfer 2025 Points'!$E$11:$L$17=D175),TRANSPOSE(COLUMN('Pre-transfer 2025 Points'!$E$11:$L$17)^0)),0))} -> #N/A
A176: 175 | B176: 254 | C176: ▲78 | D176: DAINESE Alberto | E176: Tudor Pro Cycling Team | F176: 223 | I176: {=INDEX('Pre-transfer 2025 Points'!$D$11:$D$17,MATCH(1,MMULT(--('Pre-transfer 2025 Points'!$E$11:$L$17=D176),TRANSPOSE(COLUMN('Pre-transfer 2025 Points'!$E$11:$L$17)^0)),0))} -> #N/A
A177: 176 | B177: 345 | C177: ▲168 | D177: BARCELÓ Fernando | E177: Caja Rural - Seguros RGA | F177: 222 | I177: {=INDEX('Pre-transfer 2025 Points'!$D$11:$D$17,MATCH(1,MMULT(--('Pre-transfer 2025 Points'!$E$11:$L$17=D177),TRANSPOSE(COLUMN('Pre-transfer 2025 Points'!$E$11:$L$17)^0)),0))} -> #N/A
A178: 177 | B178: 180 | C178: ▲2 | D178: MIHKELS Madis | E178: EF Education - EasyPost | F178: 221 | I178: {=INDEX('Pre-transfer 2025 Points'!$D$11:$D$17,MATCH(1,MMULT(--('Pre-transfer 2025 Points'!$E$11:$L$17=D178),TRANSPOSE(COLUMN('Pre-transfer 2025 Points'!$E$11:$L$17)^0)),0))} -> #N/A
A179: 178 | B179: 211 | C179: ▲32 | D179: LÓPEZ Juan Pedro | E179: Lidl - Trek | F179: 218 | I179: {=INDEX('Pre-transfer 2025 Points'!$D$11:$D$17,MATCH(1,MMULT(--('Pre-transfer 2025 Points'!$E$11:$L$17=D179),TRANSPOSE(COLUMN('Pre-transfer 2025 Points'!$E$11:$L$17)^0)),0))} -> #N/A
A180: 179 | B180: 403 | C180: ▲223 | D180: HOOLE Daan | E180: Lidl - Trek | F180: 216 | I180: {=INDEX('Pre-transfer 2025 Points'!$D$11:$D$17,MATCH(1,MMULT(--('Pre-transfer 2025 Points'!$E$11:$L$17=D180),TRANSPOSE(COLUMN('Pre-transfer 2025 Points'!$E$11:$L$17)^0)),0))} -> #N/A
A181: 180 | B181: 166 | C181: ▼15 | D181: VERMEERSCH Gianni | E181: Alpecin - Deceuninck | F181: 215 | I181: {=INDEX('Pre-transfer 2025 Points'!$D$11:$D$17,MATCH(1,MMULT(--('Pre-transfer 2025 Points'!$E$11:$L$17=D181),TRANSPOSE(COLUMN('Pre-transfer 2025 Points'!$E$11:$L$17)^0)),0))} -> #N/A
A182: 181 | B182: 350 | C182: ▲168 | D182: BOL Cees | E182: XDS Astana Team | F182: 214 | I182: {=INDEX('Pre-transfer 2025 Points'!$D$11:$D$17,MATCH(1,MMULT(--('Pre-transfer 2025 Points'!$E$11:$L$17=D182),TRANSPOSE(COLUMN('Pre-transfer 2025 Points'!$E$11:$L$17)^0)),0))} -> #N/A
A183: 182 | B183: 271 | C183: ▲88 | D183: TILLER Rasmus | E183: Uno-X Mobility | F183: 214 | I183: {=INDEX('Pre-transfer 2025 Points'!$D$11:$D$17,MATCH(1,MMULT(--('Pre-transfer 2025 Points'!$E$11:$L$17=D183),TRANSPOSE(COLUMN('Pre-transfer 2025 Points'!$E$11:$L$17)^0)),0))} -> #N/A
A184: 183 | B184: 65 | C184: ▼119 | D184: VACEK Mathias | E184: Lidl - Trek | F184: 212 | I184: {=INDEX('Pre-transfer 2025 Points'!$D$11:$D$17,MATCH(1,MMULT(--('Pre-transfer 2025 Points'!$E$11:$L$17=D184),TRANSPOSE(COLUMN('Pre-transfer 2025 Points'!$E$11:$L$17)^0)),0))} -> #N/A
A185: 184 | B185: 126 | C185: ▼59 | D185: LAMPERTI Luke | E185: Soudal Quick-Step | F185: 210 | I185: {=INDEX('Pre-transfer 2025 Points'!$D$11:$D$17,MATCH(1,MMULT(--('Pre-transfer 2025 Points'!$E$11:$L$17=D185),TRANSPOSE(COLUMN('Pre-transfer 2025 Points'!$E$11:$L$17)^0)),0))} -> #N/A
A186: 185 | B186: 186 | C186: - | D186: BISSEGGER Stefan | E186: Decathlon AG2R La Mondiale Team | F186: 209 | I186: {=INDEX('Pre-transfer 2025 Points'!$D$11:$D$17,MATCH(1,MMULT(--('Pre-transfer 2025 Points'!$E$11:$L$17=D186),TRANSPOSE(COLUMN('Pre-transfer 2025 Points'!$E$11:$L$17)^0)),0))} -> #N/A
... A204: 203 | B204: 209 | C204: ▲4 | D204: ANIOŁKOWSKI Stanisław | E204: Cofidis | F204: 192 | I204: {=INDEX('Pre-transfer 2025 Points'!$D$11:$D$17,MATCH(1,MMULT(--('Pre-transfer 2025 Points'!$E$11:$L$17=D204),TRANSPOSE(COLUMN('Pre-transfer 2025 Points'!$E$11:$L$17)^0)),0))} -> #N/A
A205: 204 | C205: ▲new | D205: CASTELLON Jan | E205: Caja Rural - Seguros RGA | F205: 191 | I205: {=INDEX('Pre-transfer 2025 Points'!$D$11:$D$17,MATCH(1,MMULT(--('Pre-transfer 2025 Points'!$E$11:$L$17=D205),TRANSPOSE(COLUMN('Pre-transfer 2025 Points'!$E$11:$L$17)^0)),0))} -> #N/A
A206: 205 | B206: 94 | C206: ▼113 | D206: ZAMBANINI Edoardo | E206: Bahrain - Victorious | F206: 190 | I206: {=INDEX('Pre-transfer 2025 Points'!$D$11:$D$17,MATCH(1,MMULT(--('Pre-transfer 2025 Points'!$E$11:$L$17=D206),TRANSPOSE(COLUMN('Pre-transfer 2025 Points'!$E$11:$L$17)^0)),0))} -> #N/A
A207: 206 | B207: 241 | C207: ▲76 | D207: TURGIS Anthony | E207: Team TotalEnergies | F207: 189 | I207: {=INDEX('Pre-transfer 2025 Points'!$D$11:$D$17,MATCH(1,MMULT(--('Pre-transfer 2025 Points'!$E$11:$L$17=D207),TRANSPOSE(COLUMN('Pre-transfer 2025 Points'!$E$11:$L$17)^0)),0))} -> #N/A
A208: 207 | B208: 265 | C208: ▲57 | D208: DEHAIRS Simon | E208: Alpecin - Deceuninck | F208: 188 | I208: {=INDEX('Pre-transfer 2025 Points'!$D$11:$D$17,MATCH(1,MMULT(--('Pre-transfer 2025 Points'!$E$11:$L$17=D208),TRANSPOSE(COLUMN('Pre-transfer 2025 Points'!$E$11:$L$17)^0)),0))} -> #N/A
A209: 208 | B209: 89 | C209: ▼120 | D209: ALBANESE Vincenzo | E209: EF Education - EasyPost | F209: 188 | I209: {=INDEX('Pre-transfer 2025 Points'!$D$11:$D$17,MATCH(1,MMULT(--('Pre-transfer 2025 Points'!$E$11:$L$17=D209),TRANSPOSE(COLUMN('Pre-transfer 2025 Points'!$E$11:$L$17)^0)),0))} -> #N/A
A210: 209 | B210: 225 | C210: ▲15 | D210: BRENNER Marco | E210: Tudor Pro Cycling Team | F210: 186 | I210: {=INDEX('Pre-transfer 2025 Points'!$D$11:$D$17,MATCH(1,MMULT(--('Pre-transfer 2025 Points'!$E$11:$L$17=D210),TRANSPOSE(COLUMN('Pre-transfer 2025 Points'!$E$11:$L$17)^0)),0))} -> #N/A
A211: 210 | B211: 101 | C211: ▼110 | D211: BENNETT Sam | E211: Decathlon AG2R La Mondiale Team | F211: 186 | I211: {=INDEX('Pre-transfer 2025 Points'!$D$11:$D$17,MATCH(1,MMULT(--('Pre-transfer 2025 Points'!$E$11:$L$17=D211),TRANSPOSE(COLUMN('Pre-transfer 2025 Points'!$E$11:$L$17)^0)),0))} -> #N/A
A212: 211 | B212: 290 | C212: ▲78 | D212: LOOCKX Lander | E212: Unibet Tietema Rockets | F212: 185 | I212: {=INDEX('Pre-transfer 2025 Points'!$D$11:$D$17,MATCH(1,MMULT(--('Pre-transfer 2025 Points'!$E$11:$L$17=D212),TRANSPOSE(COLUMN('Pre-transfer 2025 Points'!$E$11:$L$17)^0)),0))} -> #N/A
A213: 212 | B213: 160 | C213: ▼53 | D213: GAUTHERAT Pierre | E213: Decathlon AG2R La Mondiale Team | F213: 185 | I213: {=INDEX('Pre-transfer 2025 Points'!$D$11:$D$17,MATCH(1,MMULT(--('Pre-transfer 2025 Points'!$E$11:$L$17=D213),TRANSPOSE(COLUMN('Pre-transfer 2025 Points'!$E$11:$L$17)^0)),0))} -> #N/A
A214: 213 | B214: 205 | C214: ▼9 | D214: RICCITELLO Matthew | E214: Israel - Premier Tech | F214: 184 | I214: {=INDEX('Pre-transfer 2025 Points'!$D$11:$D$17,MATCH(1,MMULT(--('Pre-transfer 2025 Points'!$E$11:$L$17=D214),TRANSPOSE(COLUMN('Pre-transfer 2025 Points'!$E$11:$L$17)^0)),0))} -> #N/A
A215: 214 | B215: 355 | C215: ▲140 | D215: KIELICH Timo | E215: Alpecin - Deceuninck | F215: 183 | I215: {=INDEX('Pre-transfer 2025 Points'!$D$11:$D$17,MATCH(1,MMULT(--('Pre-transfer 2025 Points'!$E$11:$L$17=D215),TRANSPOSE(COLUMN('Pre-transfer 2025 Points'!$E$11:$L$17)^0)),0))} -> #N/A
A216: 215 | B216: 181 | C216: ▼35 | D216: VAN UDEN Casper | E216: Team Picnic PostNL | F216: 182 | I216: {=INDEX('Pre-transfer 2025 Points'!$D$11:$D$17,MATCH(1,MMULT(--('Pre-transfer 2025 Points'!$E$11:$L$17=D216),TRANSPOSE(COLUMN('Pre-transfer 2025 Points'!$E$11:$L$17)^0)),0))} -> #N/A
A217: 216 | B217: 748 | C217: ▲531 | D217: GUERIN Alexis | E217: Anicolor / Tien 21 | F217: 182 | I217: {=INDEX('Pre-transfer 2025 Points'!$D$11:$D$17,MATCH(1,MMULT(--('Pre-transfer 2025 Points'!$E$11:$L$17=D217),TRANSPOSE(COLUMN('Pre-transfer 2025 Points'!$E$11:$L$17)^0)),0))} -> #N/A
... A261: 260 | B261: 376 | C261: ▲116 | D261: LYU Xianjing | E261: China Anta - Mentech Cycling Team | F261: 153 | I261: {=INDEX('Pre-transfer 2025 Points'!$D$11:$D$17,MATCH(1,MMULT(--('Pre-transfer 2025 Points'!$E$11:$L$17=D261),TRANSPOSE(COLUMN('Pre-transfer 2025 Points'!$E$11:$L$17)^0)),0))} -> #N/A
A262: 261 | C262: ▲new | D262: BOGUSŁAWSKI Marceli | E262: ATT Investments | F262: 153 | I262: {=INDEX('Pre-transfer 2025 Points'!$D$11:$D$17,MATCH(1,MMULT(--('Pre-transfer 2025 Points'!$E$11:$L$17=D262),TRANSPOSE(COLUMN('Pre-transfer 2025 Points'!$E$11:$L$17)^0)),0))} -> #N/A
A263: 262 | B263: 694 | C263: ▲432 | D263: MOLENAAR Alex | E263: Caja Rural - Seguros RGA | F263: 149 | I263: {=INDEX('Pre-transfer 2025 Points'!$D$11:$D$17,MATCH(1,MMULT(--('Pre-transfer 2025 Points'!$E$11:$L$17=D263),TRANSPOSE(COLUMN('Pre-transfer 2025 Points'!$E$11:$L$17)^0)),0))} -> #N/A
A264: 263 | C264: ▲new | D264: OMRZEL Jakob | E264: Bahrain Victorious Development Team | F264: 146 | I264: {=INDEX('Pre-transfer 2025 Points'!$D$11:$D$17,MATCH(1,MMULT(--('Pre-transfer 2025 Points'!$E$11:$L$17=D264),TRANSPOSE(COLUMN('Pre-transfer 2025 Points'!$E$11:$L$17)^0)),0))} -> #N/A
A265: 264 | B265: 666 | C265: ▲402 | D265: CHAWCHIANGKWANG Peerapol | E265: Thailand Continental Cycling Team | F265: 145 | I265: {=INDEX('Pre-transfer 2025 Points'!$D$11:$D$17,MATCH(1,MMULT(--('Pre-transfer 2025 Points'!$E$11:$L$17=D265),TRANSPOSE(COLUMN('Pre-transfer 2025 Points'!$E$11:$L$17)^0)),0))} -> #N/A
A266: 265 | B266: 518 | C266: ▲253 | D266: OLIVEIRA Ivo | E266: UAE Team Emirates - XRG | F266: 143 | I266: {=INDEX('Pre-transfer 2025 Points'!$D$11:$D$17,MATCH(1,MMULT(--('Pre-transfer 2025 Points'!$E$11:$L$17=D266),TRANSPOSE(COLUMN('Pre-transfer 2025 Points'!$E$11:$L$17)^0)),0))} -> #N/A
A267: 266 | B267: 115 | C267: ▼151 | D267: CEPEDA Jefferson Alveiro | E267: Movistar Team | F267: 141 | I267: {=INDEX('Pre-transfer 2025 Points'!$D$11:$D$17,MATCH(1,MMULT(--('Pre-transfer 2025 Points'!$E$11:$L$17=D267),TRANSPOSE(COLUMN('Pre-transfer 2025 Points'!$E$11:$L$17)^0)),0))} -> #N/A
A268: 267 | B268: 45 | C268: ▼222 | D268: SKUJIŅŠ Toms | E268: Lidl - Trek | F268: 141 | I268: {=INDEX('Pre-transfer 2025 Points'!$D$11:$D$17,MATCH(1,MMULT(--('Pre-transfer 2025 Points'!$E$11:$L$17=D268),TRANSPOSE(COLUMN('Pre-transfer 2025 Points'!$E$11:$L$17)^0)),0))} -> #N/A
A269: 268 | B269: 86 | C269: ▼182 | D269: MOZZATO Luca | E269: Arkéa - B&B Hotels | F269: 141 | I269: {=INDEX('Pre-transfer 2025 Points'!$D$11:$D$17,MATCH(1,MMULT(--('Pre-transfer 2025 Points'!$E$11:$L$17=D269),TRANSPOSE(COLUMN('Pre-transfer 2025 Points'!$E$11:$L$17)^0)),0))} -> #N/A
A270: 269 | B270: 219 | C270: ▼50 | D270: BARGUIL Warren | E270: Team Picnic PostNL | F270: 140 | I270: {=INDEX('Pre-transfer 2025 Points'!$D$11:$D$17,MATCH(1,MMULT(--('Pre-transfer 2025 Points'!$E$11:$L$17=D270),TRANSPOSE(COLUMN('Pre-transfer 2025 Points'!$E$11:$L$17)^0)),0))} -> #N/A
A271: 270 | B271: 1502 | C271: ▲1232 | D271: MARTINEZ Juan Guillermo | E271: Team Picnic PostNL | F271: 140 | I271: {=INDEX('Pre-transfer 2025 Points'!$D$11:$D$17,MATCH(1,MMULT(--('Pre-transfer 2025 Points'!$E$11:$L$17=D271),TRANSPOSE(COLUMN('Pre-transfer 2025 Points'!$E$11:$L$17)^0)),0))} -> #N/A
A272: 271 | B272: 312 | C272: ▲41 | D272: CATTANEO Mattia | E272: Soudal Quick-Step | F272: 139 | I272: {=INDEX('Pre-transfer 2025 Points'!$D$11:$D$17,MATCH(1,MMULT(--('Pre-transfer 2025 Points'!$E$11:$L$17=D272),TRANSPOSE(COLUMN('Pre-transfer 2025 Points'!$E$11:$L$17)^0)),0))} -> #N/A
A273: 272 | B273: 416 | C273: ▲144 | D273: ZIJLAARD Maikel | E273: Tudor Pro Cycling Team | F273: 138 | I273: {=INDEX('Pre-transfer 2025 Points'!$D$11:$D$17,MATCH(1,MMULT(--('Pre-transfer 2025 Points'!$E$11:$L$17=D273),TRANSPOSE(COLUMN('Pre-transfer 2025 Points'!$E$11:$L$17)^0)),0))} -> #N/A
A274: 273 | B274: 240 | C274: ▼33 | D274: ASGREEN Kasper | E274: EF Education - EasyPost | F274: 138 | I274: {=INDEX('Pre-transfer 2025 Points'!$D$11:$D$17,MATCH(1,MMULT(--('Pre-transfer 2025 Points'!$E$11:$L$17=D274),TRANSPOSE(COLUMN('Pre-transfer 2025 Points'!$E$11:$L$17)^0)),0))} -> #N/A
A275: 274 | B275: 216 | C275: ▼58 | D275: CAPIOT Amaury | E275: Arkéa - B&B Hotels | F275: 137 | I275: {=INDEX('Pre-transfer 2025 Points'!$D$11:$D$17,MATCH(1,MMULT(--('Pre-transfer 2025 Points'!$E$11:$L$17=D275),TRANSPOSE(COLUMN('Pre-transfer 2025 Points'!$E$11:$L$17)^0)),0))} -> #N/A
A276: 275 | B276: 845 | C276: ▲570 | D276: SVESTAD-BÅRDSENG Embret | E276: Arkéa - B&B Hotels | F276: 137 | I276: {=INDEX('Pre-transfer 2025 Points'!$D$11:$D$17,MATCH(1,MMULT(--('Pre-transfer 2025 Points'!$E$11:$L$17=D276),TRANSPOSE(COLUMN('Pre-transfer 2025 Points'!$E$11:$L$17)^0)),0))} -> #N/A
... A294: 293 | B294: 425 | C294: ▲132 | D294: TOWNSEND Rory | E294: Q36.5 Pro Cycling Team | F294: 128 | I294: {=INDEX('Pre-transfer 2025 Points'!$D$11:$D$17,MATCH(1,MMULT(--('Pre-transfer 2025 Points'!$E$11:$L$17=D294),TRANSPOSE(COLUMN('Pre-transfer 2025 Points'!$E$11:$L$17)^0)),0))} -> #N/A
A295: 294 | C295: ▲new | D295: SPARFEL Aubin | E295: Decathlon AG2R La Mondiale Development Team | F295: 128 | I295: {=INDEX('Pre-transfer 2025 Points'!$D$11:$D$17,MATCH(1,MMULT(--('Pre-transfer 2025 Points'!$E$11:$L$17=D295),TRANSPOSE(COLUMN('Pre-transfer 2025 Points'!$E$11:$L$17)^0)),0))} -> #N/A
A296: 295 | B296: 536 | C296: ▲241 | D296: CHUMIL Sergio Geovani | E296: Burgos Burpellet BH | F296: 127 | I296: {=INDEX('Pre-transfer 2025 Points'!$D$11:$D$17,MATCH(1,MMULT(--('Pre-transfer 2025 Points'!$E$11:$L$17=D296),TRANSPOSE(COLUMN('Pre-transfer 2025 Points'!$E$11:$L$17)^0)),0))} -> #N/A
A297: 296 | B297: 801 | C297: ▲505 | D297: JUARISTI Txomin | E297: Euskaltel - Euskadi | F297: 127 | I297: {=INDEX('Pre-transfer 2025 Points'!$D$11:$D$17,MATCH(1,MMULT(--('Pre-transfer 2025 Points'!$E$11:$L$17=D297),TRANSPOSE(COLUMN('Pre-transfer 2025 Points'!$E$11:$L$17)^0)),0))} -> #N/A
A298: 297 | B298: 473 | C298: ▲176 | D298: STAUNE-MITTET Johannes | E298: Decathlon AG2R La Mondiale Team | F298: 127 | I298: {=INDEX('Pre-transfer 2025 Points'!$D$11:$D$17,MATCH(1,MMULT(--('Pre-transfer 2025 Points'!$E$11:$L$17=D298),TRANSPOSE(COLUMN('Pre-transfer 2025 Points'!$E$11:$L$17)^0)),0))} -> #N/A
A299: 298 | B299: 557 | C299: ▲259 | D299: NIZZOLO Giacomo | E299: Q36.5 Pro Cycling Team | F299: 126 | I299: {=INDEX('Pre-transfer 2025 Points'!$D$11:$D$17,MATCH(1,MMULT(--('Pre-transfer 2025 Points'!$E$11:$L$17=D299),TRANSPOSE(COLUMN('Pre-transfer 2025 Points'!$E$11:$L$17)^0)),0))} -> #N/A
A300: 299 | B300: 84 | C300: ▼215 | D300: MOHORIČ Matej | E300: Bahrain - Victorious | F300: 126 | I300: {=INDEX('Pre-transfer 2025 Points'!$D$11:$D$17,MATCH(1,MMULT(--('Pre-transfer 2025 Points'!$E$11:$L$17=D300),TRANSPOSE(COLUMN('Pre-transfer 2025 Points'!$E$11:$L$17)^0)),0))} -> Andy
A301: 300 | B301: 405 | C301: ▲105 | D301: WIDAR Jarno | E301: Lotto Development Team | F301: 125 | I301: {=INDEX('Pre-transfer 2025 Points'!$D$11:$D$17,MATCH(1,MMULT(--('Pre-transfer 2025 Points'!$E$11:$L$17=D301),TRANSPOSE(COLUMN('Pre-transfer 2025 Points'!$E$11:$L$17)^0)),0))} -> #N/A
A302: 301 | B302: 397 | C302: ▲96 | D302: DE GENDT Aimé | E302: Cofidis | F302: 125 | I302: {=INDEX('Pre-transfer 2025 Points'!$D$11:$D$17,MATCH(1,MMULT(--('Pre-transfer 2025 Points'!$E$11:$L$17=D302),TRANSPOSE(COLUMN('Pre-transfer 2025 Points'!$E$11:$L$17)^0)),0))} -> #N/A
A303: 302 | B303: 76 | C303: ▼226 | D303: KELDERMAN Wilco | E303: Team Visma | Lease a Bike | F303: 125 | I303: {=INDEX('Pre-transfer 2025 Points'!$D$11:$D$17,MATCH(1,MMULT(--('Pre-transfer 2025 Points'!$E$11:$L$17=D303),TRANSPOSE(COLUMN('Pre-transfer 2025 Points'!$E$11:$L$17)^0)),0))} -> #N/A
A304: 303 | B304: 278 | C304: ▼25 | D304: DONOVAN Mark | E304: Q36.5 Pro Cycling Team | F304: 124 | I304: {=INDEX('Pre-transfer 2025 Points'!$D$11:$D$17,MATCH(1,MMULT(--('Pre-transfer 2025 Points'!$E$11:$L$17=D304),TRANSPOSE(COLUMN('Pre-transfer 2025 Points'!$E$11:$L$17)^0)),0))} -> #N/A
A305: 304 | B305: 692 | C305: ▲388 | D305: LEITÃO Iúri | E305: Caja Rural - Seguros RGA | F305: 122 | I305: {=INDEX('Pre-transfer 2025 Points'!$D$11:$D$17,MATCH(1,MMULT(--('Pre-transfer 2025 Points'!$E$11:$L$17=D305),TRANSPOSE(COLUMN('Pre-transfer 2025 Points'!$E$11:$L$17)^0)),0))} -> #N/A
A306: 305 | B306: 267 | C306: ▼38 | D306: OLDANI Stefano | E306: Cofidis | F306: 122 | I306: {=INDEX('Pre-transfer 2025 Points'!$D$11:$D$17,MATCH(1,MMULT(--('Pre-transfer 2025 Points'!$E$11:$L$17=D306),TRANSPOSE(COLUMN('Pre-transfer 2025 Points'!$E$11:$L$17)^0)),0))} -> #N/A
A307: 306 | B307: 194 | C307: ▼112 | D307: LUTSENKO Alexey | E307: Israel - Premier Tech | F307: 120 | I307: {=INDEX('Pre-transfer 2025 Points'!$D$11:$D$17,MATCH(1,MMULT(--('Pre-transfer 2025 Points'!$E$11:$L$17=D307),TRANSPOSE(COLUMN('Pre-transfer 2025 Points'!$E$11:$L$17)^0)),0))} -> #N/A
... A342: 341 | B342: 877 | C342: ▲534 | D342: TSVETKOV Nikita | E342: OU7 Cycling Team | F342: 105 | I342: {=INDEX('Pre-transfer 2025 Points'!$D$11:$D$17,MATCH(1,MMULT(--('Pre-transfer 2025 Points'!$E$11:$L$17=D342),TRANSPOSE(COLUMN('Pre-transfer 2025 Points'!$E$11:$L$17)^0)),0))} -> #N/A
...

Sheet 2024 Points
A1: Team | B1: Rank | C1: Null | D1: Points
A2: Nick | B2: =rank(D2,D$2:D$11) -> 8 | C2: =countif(E2:L2, 0) -> 0 | D2: =sum(E2:L2) -> 5629 | E2: =IFERROR(VLOOKUP(E14,'2024 Rankings'!$D:$F,3,0),0) -> 1612 | F2: =IFERROR(VLOOKUP(F14,'2024 Rankings'!$D:$F,3,0),0) -> 1467 | G2: =IFERROR(VLOOKUP(G14,'2024 Rankings'!$D:$F,3,0),0) -> 684 | H2: =IFERROR(VLOOKUP(H14,'2024 Rankings'!$D:$F,3,0),0) -> 460 | I2: =IFERROR(VLOOKUP(I14,'2024 Rankings'!$D:$F,3,0),0) -> 190 | J2: =IFERROR(VLOOKUP(J14,'2024 Rankings'!$D:$F,3,0),0) -> 826 | K2: =IFERROR(VLOOKUP(K14,'2024 Rankings'!$D:$F,3,0),0) -> 149 | L2: =IFERROR(VLOOKUP(L14,'2024 Rankings'!$D:$F,3,0),0) -> 241
A3: Tim | B3: =rank(D3,D$2:D$11) -> 3 | C3: =countif(E3:L3, 0) -> 0 | D3: =sum(E3:L3) -> 7886 | E3: =IFERROR(VLOOKUP(E15,'2024 Rankings'!$D:$F,3,0),0) -> 1702 | F3: =IFERROR(VLOOKUP(F15,'2024 Rankings'!$D:$F,3,0),0) -> 564 | G3: =IFERROR(VLOOKUP(G15,'2024 Rankings'!$D:$F,3,0),0) -> 600 | H3: =IFERROR(VLOOKUP(H15,'2024 Rankings'!$D:$F,3,0),0) -> 1373 | I3: =IFERROR(VLOOKUP(I15,'2024 Rankings'!$D:$F,3,0),0) -> 1156 | J3: =IFERROR(VLOOKUP(J15,'2024 Rankings'!$D:$F,3,0),0) -> 687 | K3: =IFERROR(VLOOKUP(K15,'2024 Rankings'!$D:$F,3,0),0) -> 1695 | L3: =IFERROR(VLOOKUP(L15,'2024 Rankings'!$D:$F,3,0),0) -> 109
A4: Cameron | B4: =rank(D4,D$2:D$11) -> 1 | C4: =countif(E4:L4, 0) -> 0 | D4: =sum(E4:L4) -> 11725 | E4: =IFERROR(VLOOKUP(E16,'2024 Rankings'!$D:$F,3,0),0) -> 4588 | F4: =IFERROR(VLOOKUP(F16,'2024 Rankings'!$D:$F,3,0),0) -> 151 | G4: =IFERROR(VLOOKUP(G16,'2024 Rankings'!$D:$F,3,0),0) -> 1279 | H4: =IFERROR(VLOOKUP(H16,'2024 Rankings'!$D:$F,3,0),0) -> 909 | I4: =IFERROR(VLOOKUP(I16,'2024 Rankings'!$D:$F,3,0),0) -> 775 | J4: =IFERROR(VLOOKUP(J16,'2024 Rankings'!$D:$F,3,0),0) -> 1074 | K4: =IFERROR(VLOOKUP(K16,'2024 Rankings'!$D:$F,3,0),0) -> 2041 | L4: =IFERROR(VLOOKUP(L16,'2024 Rankings'!$D:$F,3,0),0) -> 908
A5: Andrew | B5: =rank(D5,D$2:D$11) -> 4 | C5: =countif(E5:L5, 0) -> 0 | D5: =sum(E5:L5) -> 7574 | E5: =IFERROR(VLOOKUP(E17,'2024 Rankings'!$D:$F,3,0),0) -> 2889 | F5: =IFERROR(VLOOKUP(F17,'2024 Rankings'!$D:$F,3,0),0) -> 633 | G5: =IFERROR(VLOOKUP(G17,'2024 Rankings'!$D:$F,3,0),0) -> 1466 | H5: =IFERROR(VLOOKUP(H17,'2024 Rankings'!$D:$F,3,0),0) -> 1236 | I5: =IFERROR(VLOOKUP(I17,'2024 Rankings'!$D:$F,3,0),0) -> 780 | J5: =IFERROR(VLOOKUP(J17,'2024 Rankings'!$D:$F,3,0),0) -> 179 | K5: =IFERROR(VLOOKUP(K17,'2024 Rankings'!$D:$F,3,0),0) -> 48 | L5: =IFERROR(VLOOKUP(L17,'2024 Rankings'!$D:$F,3,0),0) -> 343
A6: Chris | B6: =rank(D6,D$2:D$11) -> 6 | C6: =countif(E6:L6, 0) -> 0 | D6: =sum(E6:L6) -> 6848 | E6: =IFERROR(VLOOKUP(E18,'2024 Rankings'!$D:$F,3,0),0) -> 1513 | F6: =IFERROR(VLOOKUP(F18,'2024 Rankings'!$D:$F,3,0),0) -> 479 | G6: =IFERROR(VLOOKUP(G18,'2024 Rankings'!$D:$F,3,0),0) -> 1181 | H6: =IFERROR(VLOOKUP(H18,'2024 Rankings'!$D:$F,3,0),0) -> 454 | I6: =IFERROR(VLOOKUP(I18,'2024 Rankings'!$D:$F,3,0),0) -> 207 | J6: =IFERROR(VLOOKUP(J18,'2024 Rankings'!$D:$F,3,0),0) -> 694 | K6: =IFERROR(VLOOKUP(K18,'2024 Rankings'!$D:$F,3,0),0) -> 1485 | L6: =IFERROR(VLOOKUP(L18,'2024 Rankings'!$D:$F,3,0),0) -> 835
A7: Mike | B7: =rank(D7,D$2:D$11) -> 2 | C7: =countif(E7:L7, 0) -> 0 | D7: =sum(E7:L7) -> 9540 | E7: =IFERROR(VLOOKUP(E19,'2024 Rankings'!$D:$F,3,0),0) -> 1058 | F7: =IFERROR(VLOOKUP(F19,'2024 Rankings'!$D:$F,3,0),0) -> 2355 | G7: =IFERROR(VLOOKUP(G19,'2024 Rankings'!$D:$F,3,0),0) -> 1406 | H7: =IFERROR(VLOOKUP(H19,'2024 Rankings'!$D:$F,3,0),0) -> 714 | I7: =IFERROR(VLOOKUP(I19,'2024 Rankings'!$D:$F,3,0),0) -> 964 | J7: =IFERROR(VLOOKUP(J19,'2024 Rankings'!$D:$F,3,0),0) -> 259 | K7: =IFERROR(VLOOKUP(K19,'2024 Rankings'!$D:$F,3,0),0) -> 1666 | L7: =IFERROR(VLOOKUP(L19,'2024 Rankings'!$D:$F,3,0),0) -> 1118
A8: Joe | B8: =rank(D8,D$2:D$11) -> 5 | C8: =countif(E8:L8, 0) -> 0 | D8: =sum(E8:L8) -> 7072 | E8: =IFERROR(VLOOKUP(E20,'2024 Rankings'!$D:$F,3,0),0) -> 1053 | F8: =IFERROR(VLOOKUP(F20,'2024 Rankings'!$D:$F,3,0),0) -> 1100 | G8: =IFERROR(VLOOKUP(G20,'2024 Rankings'!$D:$F,3,0),0) -> 600 | H8: =IFERROR(VLOOKUP(H20,'2024 Rankings'!$D:$F,3,0),0) -> 239 | I8: =IFERROR(VLOOKUP(I20,'2024 Rankings'!$D:$F,3,0),0) -> 1283 | J8: =IFERROR(VLOOKUP(J20,'2024 Rankings'!$D:$F,3,0),0) -> 825 | K8: =IFERROR(VLOOKUP(K20,'2024 Rankings'!$D:$F,3,0),0) -> 630 | L8: =IFERROR(VLOOKUP(L20,'2024 Rankings'!$D:$F,3,0),0) -> 1342
A9: Campbell | B9: =rank(D9,D$2:D$11) -> 7 | C9: =countif(E9:L9, 0) -> 0 | D9: =sum(E9:L9) -> 6123 | E9: =IFERROR(VLOOKUP(E21,'2024 Rankings'!$D:$F,3,0),0) -> 1428 | F9: =IFERROR(VLOOKUP(F21,'2024 Rankings'!$D:$F,3,0),0) -> 745 | G9: =IFERROR(VLOOKUP(G21,'2024 Rankings'!$D:$F,3,0),0) -> 637 | H9: =IFERROR(VLOOKUP(H21,'2024 Rankings'!$D:$F,3,0),0) -> 578 | I9: =IFERROR(VLOOKUP(I21,'2024 Rankings'!$D:$F,3,0),0) -> 557 | J9: =IFERROR(VLOOKUP(J21,'2024 Rankings'!$D:$F,3,0),0) -> 874 | K9: =IFERROR(VLOOKUP(K21,'2024 Rankings'!$D:$F,3,0),0) -> 634 | L9: =IFERROR(VLOOKUP(L21,'2024 Rankings'!$D:$F,3,0),0) -> 670
A10: Dave | B10: =rank(D10,D$2:D$11) -> 10 | C10: =countif(E10:L10, 0) -> 0 | D10: =sum(E10:L10) -> 4613 | E10: =IFERROR(VLOOKUP(E22,'2024 Rankings'!$D:$F,3,0),0) -> 950 | F10: =IFERROR(VLOOKUP(F22,'2024 Rankings'!$D:$F,3,0),0) -> 480 | G10: =IFERROR(VLOOKUP(G22,'2024 Rankings'!$D:$F,3,0),0) -> 763 | H10: =IFERROR(VLOOKUP(H22,'2024 Rankings'!$D:$F,3,0),0) -> 397 | I10: =IFERROR(VLOOKUP(I22,'2024 Rankings'!$D:$F,3,0),0) -> 569 | J10: =IFERROR(VLOOKUP(J22,'2024 Rankings'!$D:$F,3,0),0) -> 114 | K10: =IFERROR(VLOOKUP(K22,'2024 Rankings'!$D:$F,3,0),0) -> 883 | L10: =IFERROR(VLOOKUP(L22,'2024 Rankings'!$D:$F,3,0),0) -> 457
A11: Hipster's Choice | B11: =rank(D11,D$2:D$11) -> 9 | C11: =countif(E11:L11, 0) -> 0 | D11: =sum(E11:L11) -> 4764 | E11: =IFERROR(VLOOKUP(E23,'2024 Rankings'!$D:$F,3,0),0) -> 226 | F11: =IFERROR(VLOOKUP(F23,'2024 Rankings'!$D:$F,3,0),0) -> 831 | G11: =IFERROR(VLOOKUP(G23,'2024 Rankings'!$D:$F,3,0),0) -> 272 | H11: =IFERROR(VLOOKUP(H23,'2024 Rankings'!$D:$F,3,0),0) -> 495 | I11: =IFERROR(VLOOKUP(I23,'2024 Rankings'!$D:$F,3,0),0) -> 1281 | J11: =IFERROR(VLOOKUP(J23,'2024 Rankings'!$D:$F,3,0),0) -> 528 | K11: =IFERROR(VLOOKUP(K23,'2024 Rankings'!$D:$F,3,0),0) -> 834 | L11: =IFERROR(VLOOKUP(L23,'2024 Rankings'!$D:$F,3,0),0) -> 297
D13: Manager | E13: 1 | F13: 2 | G13: 3 | H13: 4 | I13: 5 | J13: 6 | K13: 7 | L13: 8
A14: =D14 -> Nick | D14: Nick | E14: van der Poel Mathieu | F14: Pedersen Mads | G14: Ganna Filippo | H14: Tarling Joshua | I14: Cavendish Mark | J14: Groenewegen Dylan | K14: Costa Rui | L14: Jakobsen Fabio
A15: =D15 -> Tim | D15: Tim | E15: Vingegaard Jonas | F15: Benoot Tiesj | G15: Hindley Jai | H15: McNulty Brandon | I15: Skjelmose Mattias | J15: Van Wilder Ilan | K15: O'Connor Ben | L15: Kämna Lennard
A16: =D16 -> Cameron | D16: Cameron | E16: Pogačar Tadej | F16: Geoghegan Hart Tao | G16: Rodríguez Carlos | H16: Alaphilippe Julian | I16: Gaudu David | J16: Landa Mikel | K16: Hirschi Marc | L16: Bardet Romain
A17: =D17 -> Andrew | D17: Andrew | E17: Evenepoel Remco | F17: Martin Guillaume | G17: Jorgenson Matteo | H17: Ayuso Juan | I17: Madouas Valentin | J17: Uijtdebroeks Cian | K17: Vermeersch Florian | L17: Lutsenko Alexey
A18: =D18 -> Chris | D18: Chris | E18: Roglič Primož | F18: Kuss Sepp | G18: Vlasov Aleksandr | H18: Thomas Geraint | I18: Lampaert Yves | J18: Sivakov Pavel | K18: Merlier Tim | L18: Grégoire Romain
A19: =D19 -> Mike | D19: Mike | E19: Kooij Olav | F19: Philipsen Jasper | G19: De Lie Arnaud | H19: Yates Simon | I19: Küng Stefan | J19: Ewan Caleb | K19: Girmay Biniam | L19: Carapaz Richard
A20: =D20 -> Joe | D20: Joe | E20: Pidcock Thomas | F20: Almeida João | G20: Healy Ben | H20: Tiller Rasmus | I20: Mas Enric | J20: Laporte Christophe | K20: Ciccone Giulio | L20: Yates Adam
A21: =D21 -> Campbell | D21: Campbell | E21: van Aert Wout | F21: Groves Kaden | G21: Mohorič Matej | H21: Powless Neilson | I21: Gall Felix | J21: Bilbao Pello | K21: Sheffield Magnus | L21: Gee Derek
A22: =D22 -> Dave | D22: Dave | E22: Zingle Axel | F22: Rubio Einer | G22: Buitrago Santiago | H22: Woods Michael | I22: Johannessen Tobias Halland | J22: Bagioli Andrea | K22: Aranburu Alex | L22: Izagirre Ion
A23: =D23 -> Hipster's Choice | D23: Hipster's Choice | E23: Kragh Andersen Søren | F23: Cort Magnus | G23: Asgreen Kasper | H23: Vine Jay | I23: Milan Jonathan | J23: Zana Filippo | K23: Martinez Lenny | L23: Wright Fred

Sheet 2024 Rankings
A1: Rank | B1: Prev. Rank | C1: Rank Diff. | D1: Rider | E1: Team | F1: Points | I1: Manager
A2: 1 | B2: 1 | C2: - | D2: POGAČAR Tadej | E2: UAE Team Emirates | F2: 4588 | I2: {=INDEX('2024 Points'!$D$14:$D$23,MATCH(1,MMULT(--('2024 Points'!$E$14:$L$23=D2),TRANSPOSE(COLUMN('2024 Points'!$E$14:$L$23)^0)),0))} -> Cameron
A3: 2 | B3: 2 | C3: - | D3: EVENEPOEL Remco | E3: Soudal Quick-Step | F3: 2889 | I3: {=INDEX('2024 Points'!$D$14:$D$23,MATCH(1,MMULT(--('2024 Points'!$E$14:$L$23=D3),TRANSPOSE(COLUMN('2024 Points'!$E$14:$L$23)^0)),0))} -> Andrew
A4: 3 | B4: 5 | C4: ▲2 | D4: PHILIPSEN Jasper | E4: Alpecin - Deceuninck | F4: 2355 | I4: {=INDEX('2024 Points'!$D$14:$D$23,MATCH(1,MMULT(--('2024 Points'!$E$14:$L$23=D4),TRANSPOSE(COLUMN('2024 Points'!$E$14:$L$23)^0)),0))} -> Mike
A5: 4 | B5: 9 | C5: ▲5 | D5: HIRSCHI Marc | E5: UAE Team Emirates | F5: 2041 | I5: {=INDEX('2024 Points'!$D$14:$D$23,MATCH(1,MMULT(--('2024 Points'!$E$14:$L$23=D5),TRANSPOSE(COLUMN('2024 Points'!$E$14:$L$23)^0)),0))} -> Cameron
A6: 5 | B6: 3 | C6: ▼2 | D6: VINGEGAARD Jonas | E6: Team Visma | Lease a Bike | F6: 1702 | I6: {=INDEX('2024 Points'!$D$14:$D$23,MATCH(1,MMULT(--('2024 Points'!$E$14:$L$23=D6),TRANSPOSE(COLUMN('2024 Points'!$E$14:$L$23)^0)),0))} -> Tim
A7: 6 | B7: 46 | C7: ▲40 | D7: O'CONNOR Ben | E7: Decathlon AG2R La Mondiale Team | F7: 1695 | I7: {=INDEX('2024 Points'!$D$14:$D$23,MATCH(1,MMULT(--('2024 Points'!$E$14:$L$23=D7),TRANSPOSE(COLUMN('2024 Points'!$E$14:$L$23)^0)),0))} -> Tim
A8: 7 | B8: 114 | C8: ▲107 | D8: GIRMAY Biniam | E8: Intermarché - Wanty | F8: 1666 | I8: {=INDEX('2024 Points'!$D$14:$D$23,MATCH(1,MMULT(--('2024 Points'!$E$14:$L$23=D8),TRANSPOSE(COLUMN('2024 Points'!$E$14:$L$23)^0)),0))} -> Mike
A9: 8 | B9: 11 | C9: ▲3 | D9: VAN DER POEL Mathieu | E9: Alpecin - Deceuninck | F9: 1612 | I9: {=INDEX('2024 Points'!$D$14:$D$23,MATCH(1,MMULT(--('2024 Points'!$E$14:$L$23=D9),TRANSPOSE(COLUMN('2024 Points'!$E$14:$L$23)^0)),0))} -> Nick
A10: 9 | B10: 4 | C10: ▼5 | D10: ROGLIČ Primož | E10: Red Bull - BORA - hansgrohe | F10: 1513 | I10: {=INDEX('2024 Points'!$D$14:$D$23,MATCH(1,MMULT(--('2024 Points'!$E$14:$L$23=D10),TRANSPOSE(COLUMN('2024 Points'!$E$14:$L$23)^0)),0))} -> Chris
A11: 10 | B11: 41 | C11: ▲31 | D11: MERLIER Tim | E11: Soudal Quick-Step | F11: 1485 | I11: {=INDEX('2024 Points'!$D$14:$D$23,MATCH(1,MMULT(--('2024 Points'!$E$14:$L$23=D11),TRANSPOSE(COLUMN('2024 Points'!$E$14:$L$23)^0)),0))} -> Chris
A12: 11 | B12: 7 | C12: ▼4 | D12: PEDERSEN Mads | E12: Lidl - Trek | F12: 1467 | I12: {=INDEX('2024 Points'!$D$14:$D$23,MATCH(1,MMULT(--('2024 Points'!$E$14:$L$23=D12),TRANSPOSE(COLUMN('2024 Points'!$E$14:$L$23)^0)),0))} -> Nick
A13: 12 | B13: 30 | C13: ▲18 | D13: JORGENSON Matteo | E13: Team Visma | Lease a Bike | F13: 1466 | I13: {=INDEX('2024 Points'!$D$14:$D$23,MATCH(1,MMULT(--('2024 Points'!$E$14:$L$23=D13),TRANSPOSE(COLUMN('2024 Points'!$E$14:$L$23)^0)),0))} -> Andrew
... A133: 132 | B133: 113 | C133: ▼19 | D133: TARLING Joshua | E133: INEOS Grenadiers | F133: 460 | I133: {=INDEX('2024 Points'!$D$14:$D$23,MATCH(1,MMULT(--('2024 Points'!$E$14:$L$23=D133),TRANSPOSE(COLUMN('2024 Points'!$E$14:$L$23)^0)),0))} -> Nick
A134: 133 | C134: new | D134: KRIJNSEN Jelte | E134: Parkhotel Valkenburg | F134: 459 | I134: {=INDEX('2024 Points'!$D$14:$D$23,MATCH(1,MMULT(--('2024 Points'!$E$14:$L$23=D134),TRANSPOSE(COLUMN('2024 Points'!$E$14:$L$23)^0)),0))} -> #N/A
A135: 134 | B135: 466 | C135: ▲332 | D135: PARET-PEINTRE Valentin | E135: Decathlon AG2R La Mondiale Team | F135: 458 | I135: {=INDEX('2024 Points'!$D$14:$D$23,MATCH(1,MMULT(--('2024 Points'!$E$14:$L$23=D135),TRANSPOSE(COLUMN('2024 Points'!$E$14:$L$23)^0)),0))} -> #N/A
A136: 135 | B136: 57 | C136: ▼78 | D136: IZAGIRRE Ion | E136: Cofidis | F136: 457 | I136: {=INDEX('2024 Points'!$D$14:$D$23,MATCH(1,MMULT(--('2024 Points'!$E$14:$L$23=D136),TRANSPOSE(COLUMN('2024 Points'!$E$14:$L$23)^0)),0))} -> Dave
A137: 136 | B137: 182 | C137: ▲46 | D137: VENTURINI Clément | E137: Arkéa - B&B Hotels | F137: 455 | I137: {=INDEX('2024 Points'!$D$14:$D$23,MATCH(1,MMULT(--('2024 Points'!$E$14:$L$23=D137),TRANSPOSE(COLUMN('2024 Points'!$E$14:$L$23)^0)),0))} -> #N/A
A138: 137 | B138: 82 | C138: ▼55 | D138: THOMAS Geraint | E138: INEOS Grenadiers | F138: 454 | I138: {=INDEX('2024 Points'!$D$14:$D$23,MATCH(1,MMULT(--('2024 Points'!$E$14:$L$23=D138),TRANSPOSE(COLUMN('2024 Points'!$E$14:$L$23)^0)),0))} -> Chris
A139: 138 | B139: 384 | C139: ▲246 | D139: PELLIZZARI Giulio | E139: VF Group - Bardiani CSF - Faizanè | F139: 452 | I139: {=INDEX('2024 Points'!$D$14:$D$23,MATCH(1,MMULT(--('2024 Points'!$E$14:$L$23=D139),TRANSPOSE(COLUMN('2024 Points'!$E$14:$L$23)^0)),0))} -> #N/A
A140: 139 | B140: 109 | C140: ▼30 | D140: RODRÍGUEZ Cristián | E140: Arkéa - B&B Hotels | F140: 452 | I140: {=INDEX('2024 Points'!$D$14:$D$23,MATCH(1,MMULT(--('2024 Points'!$E$14:$L$23=D140),TRANSPOSE(COLUMN('2024 Points'!$E$14:$L$23)^0)),0))} -> #N/A
A141: 140 | B141: 260 | C141: ▲120 | D141: ALEOTTI Giovanni | E141: Red Bull - BORA - hansgrohe | F141: 449 | I141: {=INDEX('2024 Points'!$D$14:$D$23,MATCH(1,MMULT(--('2024 Points'!$E$14:$L$23=D141),TRANSPOSE(COLUMN('2024 Points'!$E$14:$L$23)^0)),0))} -> #N/A
A142: 141 | B142: 83 | C142: ▼58 | D142: POELS Wout | E142: Bahrain - Victorious | F142: 448 | I142: {=INDEX('2024 Points'!$D$14:$D$23,MATCH(1,MMULT(--('2024 Points'!$E$14:$L$23=D142),TRANSPOSE(COLUMN('2024 Points'!$E$14:$L$23)^0)),0))} -> #N/A
A143: 142 | B143: 670 | C143: ▲528 | D143: BITTNER Pavel | E143: Team dsm-firmenich PostNL | F143: 447 | I143: {=INDEX('2024 Points'!$D$14:$D$23,MATCH(1,MMULT(--('2024 Points'!$E$14:$L$23=D143),TRANSPOSE(COLUMN('2024 Points'!$E$14:$L$23)^0)),0))} -> #N/A
A144: 143 | C144: new | D144: SILVA Guillermo Thomas | E144: Caja Rural - Seguros RGA | F144: 445 | I144: {=INDEX('2024 Points'!$D$14:$D$23,MATCH(1,MMULT(--('2024 Points'!$E$14:$L$23=D144),TRANSPOSE(COLUMN('2024 Points'!$E$14:$L$23)^0)),0))} -> #N/A
A145: 144 | B145: 754 | C145: ▲610 | D145: MAGNIER Paul | E145: Soudal Quick-Step | F145: 438 | I145: {=INDEX('2024 Points'!$D$14:$D$23,MATCH(1,MMULT(--('2024 Points'!$E$14:$L$23=D145),TRANSPOSE(COLUMN('2024 Points'!$E$14:$L$23)^0)),0))} -> #N/A
A146: 145 | B146: 72 | C146: ▼73 | D146: MULUBRHAN Henok | E146: Astana Qazaqstan Team | F146: 438 | I146: {=INDEX('2024 Points'!$D$14:$D$23,MATCH(1,MMULT(--('2024 Points'!$E$14:$L$23=D146),TRANSPOSE(COLUMN('2024 Points'!$E$14:$L$23)^0)),0))} -> #N/A
A147: 146 | B147: 102 | C147: ▼44 | D147: TEUNISSEN Mike | E147: Intermarché - Wanty | F147: 438 | I147: {=INDEX('2024 Points'!$D$14:$D$23,MATCH(1,MMULT(--('2024 Points'!$E$14:$L$23=D147),TRANSPOSE(COLUMN('2024 Points'!$E$14:$L$23)^0)),0))} -> #N/A
A148: 147 | B148: 108 | C148: ▼39 | D148: LAZKANO Oier | E148: Movistar Team | F148: 436 | I148: {=INDEX('2024 Points'!$D$14:$D$23,MATCH(1,MMULT(--('2024 Points'!$E$14:$L$23=D148),TRANSPOSE(COLUMN('2024 Points'!$E$14:$L$23)^0)),0))} -> #N/A
A149: 148 | B149: 347 | C149: ▲199 | D149: LAURANCE Axel | E149: Alpecin - Deceuninck | F149: 435 | I149: {=INDEX('2024 Points'!$D$14:$D$23,MATCH(1,MMULT(--('2024 Points'!$E$14:$L$23=D149),TRANSPOSE(COLUMN('2024 Points'!$E$14:$L$23)^0)),0))} -> #N/A
A150: 149 | B150: 216 | C150: ▲67 | D150: VAN ASBROECK Tom | E150: Israel - Premier Tech | F150: 434 | I150: {=INDEX('2024 Points'!$D$14:$D$23,MATCH(1,MMULT(--('2024 Points'!$E$14:$L$23=D150),TRANSPOSE(COLUMN('2024 Points'!$E$14:$L$23)^0)),0))} -> #N/A
A151: 150 | B151: 473 | C151: ▲323 | D151: SCHACHMANN Maximilian | E151: Red Bull - BORA - hansgrohe | F151: 434 | I151: {=INDEX('2024 Points'!$D$14:$D$23,MATCH(1,MMULT(--('2024 Points'!$E$14:$L$23=D151),TRANSPOSE(COLUMN('2024 Points'!$E$14:$L$23)^0)),0))} -> #N/A
A152: 151 | B152: 141 | C152: ▼10 | D152: BJERG Mikkel | E152: UAE Team Emirates | F152: 433 | I152: {=INDEX('2024 Points'!$D$14:$D$23,MATCH(1,MMULT(--('2024 Points'!$E$14:$L$23=D152),TRANSPOSE(COLUMN('2024 Points'!$E$14:$L$23)^0)),0))} -> #N/A
A153: 152 | B153: 96 | C153: ▼56 | D153: PENHOËT Paul | E153: Groupama - FDJ | F153: 433 | I153: {=INDEX('2024 Points'!$D$14:$D$23,MATCH(1,MMULT(--('2024 Points'!$E$14:$L$23=D153),TRANSPOSE(COLUMN('2024 Points'!$E$14:$L$23)^0)),0))} -> #N/A
A154: 153 | B154: 163 | C154: ▲10 | D154: BIERMANS Jenthe | E154: Arkéa - B&B Hotels | F154: 432 | I154: {=INDEX('2024 Points'!$D$14:$D$23,MATCH(1,MMULT(--('2024 Points'!$E$14:$L$23=D154),TRANSPOSE(COLUMN('2024 Points'!$E$14:$L$23)^0)),0))} -> #N/A
A155: 154 | B155: 69 | C155: ▼85 | D155: COQUARD Bryan | E155: Cofidis | F155: 429 | I155: {=INDEX('2024 Points'!$D$14:$D$23,MATCH(1,MMULT(--('2024 Points'!$E$14:$L$23=D155),TRANSPOSE(COLUMN('2024 Points'!$E$14:$L$23)^0)),0))} -> #N/A
A156: 155 | B156: 560 | C156: ▲405 | D156: VAN DEN BROEK Frank | E156: Team dsm-firmenich PostNL | F156: 428 | I156: {=INDEX('2024 Points'!$D$14:$D$23,MATCH(1,MMULT(--('2024 Points'!$E$14:$L$23=D156),TRANSPOSE(COLUMN('2024 Points'!$E$14:$L$23)^0)),0))} -> #N/A
... A325: 324 | B325: 143 | C325: ▼181 | D325: CAVENDISH Mark | E325: Astana Qazaqstan Team | F325: 190 | I325: {=INDEX('2024 Points'!$D$14:$D$23,MATCH(1,MMULT(--('2024 Points'!$E$14:$L$23=D325),TRANSPOSE(COLUMN('2024 Points'!$E$14:$L$23)^0)),0))} -> Nick
A326: 325 | C326: new | D326: GEARY Dillon | E326: First Internet Bank Cycling | F326: 190 | I326: {=INDEX('2024 Points'!$D$14:$D$23,MATCH(1,MMULT(--('2024 Points'!$E$14:$L$23=D326),TRANSPOSE(COLUMN('2024 Points'!$E$14:$L$23)^0)),0))} -> #N/A
A327: 326 | B327: 330 | C327: ▲4 | D327: MÜHLBERGER Gregor | E327: Movistar Team | F327: 190 | I327: {=INDEX('2024 Points'!$D$14:$D$23,MATCH(1,MMULT(--('2024 Points'!$E$14:$L$23=D327),TRANSPOSE(COLUMN('2024 Points'!$E$14:$L$23)^0)),0))} -> #N/A
A328: 327 | B328: 148 | C328: ▼179 | D328: GARCÍA CORTINA Iván | E328: Movistar Team | F328: 189 | I328: {=INDEX('2024 Points'!$D$14:$D$23,MATCH(1,MMULT(--('2024 Points'!$E$14:$L$23=D328),TRANSPOSE(COLUMN('2024 Points'!$E$14:$L$23)^0)),0))} -> #N/A
A329: 328 | B329: 180 | C329: ▼148 | D329: MONIQUET Sylvain | E329: Lotto Dstny | F329: 189 | I329: {=INDEX('2024 Points'!$D$14:$D$23,MATCH(1,MMULT(--('2024 Points'!$E$14:$L$23=D329),TRANSPOSE(COLUMN('2024 Points'!$E$14:$L$23)^0)),0))} -> #N/A
A330: 329 | B330: 142 | C330: ▼187 | D330: ZWIEHOFF Ben | E330: Red Bull - BORA - hansgrohe | F330: 188 | I330: {=INDEX('2024 Points'!$D$14:$D$23,MATCH(1,MMULT(--('2024 Points'!$E$14:$L$23=D330),TRANSPOSE(COLUMN('2024 Points'!$E$14:$L$23)^0)),0))} -> #N/A
A331: 330 | B331: 262 | C331: ▼68 | D331: BARRÉ Louis | E331: Arkéa - B&B Hotels | F331: 188 | I331: {=INDEX('2024 Points'!$D$14:$D$23,MATCH(1,MMULT(--('2024 Points'!$E$14:$L$23=D331),TRANSPOSE(COLUMN('2024 Points'!$E$14:$L$23)^0)),0))} -> #N/A
A332: 331 | B332: 1766 | C332: ▲1435 | D332: QUINTANA Nairo | E332: Movistar Team | F332: 187 | I332: {=INDEX('2024 Points'!$D$14:$D$23,MATCH(1,MMULT(--('2024 Points'!$E$14:$L$23=D332),TRANSPOSE(COLUMN('2024 Points'!$E$14:$L$23)^0)),0))} -> #N/A
A333: 332 | B333: 847 | C333: ▲515 | D333: BARBIER Pierre | E333: Philippe Wagner/Bazin | F333: 186 | I333: {=INDEX('2024 Points'!$D$14:$D$23,MATCH(1,MMULT(--('2024 Points'!$E$14:$L$23=D333),TRANSPOSE(COLUMN('2024 Points'!$E$14:$L$23)^0)),0))} -> #N/A
A334: 333 | B334: 452 | C334: ▲119 | D334: FLYNN Sean | E334: Team dsm-firmenich PostNL | F334: 185 | I334: {=INDEX('2024 Points'!$D$14:$D$23,MATCH(1,MMULT(--('2024 Points'!$E$14:$L$23=D334),TRANSPOSE(COLUMN('2024 Points'!$E$14:$L$23)^0)),0))} -> #N/A
A335: 334 | B335: 1158 | C335: ▲824 | D335: CONTRERAS Rodrigo | E335: Nu Colombia | F335: 185 | I335: {=INDEX('2024 Points'!$D$14:$D$23,MATCH(1,MMULT(--('2024 Points'!$E$14:$L$23=D335),TRANSPOSE(COLUMN('2024 Points'!$E$14:$L$23)^0)),0))} -> #N/A
A336: 335 | B336: 317 | C336: ▼18 | D336: HERREGODTS Rune | E336: Intermarché - Wanty | F336: 185 | I336: {=INDEX('2024 Points'!$D$14:$D$23,MATCH(1,MMULT(--('2024 Points'!$E$14:$L$23=D336),TRANSPOSE(COLUMN('2024 Points'!$E$14:$L$23)^0)),0))} -> #N/A
A337: 336 | B337: 517 | C337: ▲181 | D337: GOVEKAR Matevž | E337: Bahrain - Victorious | F337: 185 | I337: {=INDEX('2024 Points'!$D$14:$D$23,MATCH(1,MMULT(--('2024 Points'!$E$14:$L$23=D337),TRANSPOSE(COLUMN('2024 Points'!$E$14:$L$23)^0)),0))} -> #N/A
A338: 337 | B338: 522 | C338: ▲185 | D338: DINA Márton | E338: ATT Investments | F338: 185 | I338: {=INDEX('2024 Points'!$D$14:$D$23,MATCH(1,MMULT(--('2024 Points'!$E$14:$L$23=D338),TRANSPOSE(COLUMN('2024 Points'!$E$14:$L$23)^0)),0))} -> #N/A
... A402: 401 | B402: 322 | C402: ▼79 | D402: MARECZKO Jakub | E402: Team Corratec - Vini Fantini | F402: 154 | I402: {=INDEX('2024 Points'!$D$14:$D$23,MATCH(1,MMULT(--('2024 Points'!$E$14:$L$23=D402),TRANSPOSE(COLUMN('2024 Points'!$E$14:$L$23)^0)),0))} -> #N/A
A403: 402 | B403: 1253 | C403: ▲851 | D403: DOSTIYEV Ilkhan | F403: 154 | I403: {=INDEX('2024 Points'!$D$14:$D$23,MATCH(1,MMULT(--('2024 Points'!$E$14:$L$23=D403),TRANSPOSE(COLUMN('2024 Points'!$E$14:$L$23)^0)),0))} -> #N/A
A404: 403 | B404: 328 | C404: ▼75 | D404: MAESTRI Mirco | E404: Team Polti Kometa | F404: 154 | I404: {=INDEX('2024 Points'!$D$14:$D$23,MATCH(1,MMULT(--('2024 Points'!$E$14:$L$23=D404),TRANSPOSE(COLUMN('2024 Points'!$E$14:$L$23)^0)),0))} -> #N/A
A405: 404 | B405: 492 | C405: ▲88 | D405: HOOLE Daan | E405: Lidl - Trek | F405: 154 | I405: {=INDEX('2024 Points'!$D$14:$D$23,MATCH(1,MMULT(--('2024 Points'!$E$14:$L$23=D405),TRANSPOSE(COLUMN('2024 Points'!$E$14:$L$23)^0)),0))} -> #N/A
A406: 405 | B406: 181 | C406: ▼224 | D406: SEPÚLVEDA Eduardo | E406: Lotto Dstny | F406: 154 | I406: {=INDEX('2024 Points'!$D$14:$D$23,MATCH(1,MMULT(--('2024 Points'!$E$14:$L$23=D406),TRANSPOSE(COLUMN('2024 Points'!$E$14:$L$23)^0)),0))} -> #N/A
A407: 406 | C407: new | D407: WIDAR Jarno | E407: Lotto Dstny Development Team | F407: 154 | I407: {=INDEX('2024 Points'!$D$14:$D$23,MATCH(1,MMULT(--('2024 Points'!$E$14:$L$23=D407),TRANSPOSE(COLUMN('2024 Points'!$E$14:$L$23)^0)),0))} -> #N/A
A408: 407 | B408: 1109 | C408: ▲702 | D408: VERCHER Mattéo | E408: TotalEnergies | F408: 153 | I408: {=INDEX('2024 Points'!$D$14:$D$23,MATCH(1,MMULT(--('2024 Points'!$E$14:$L$23=D408),TRANSPOSE(COLUMN('2024 Points'!$E$14:$L$23)^0)),0))} -> #N/A
A409: 408 | B409: 359 | C409: ▼49 | D409: HAMILTON Chris | E409: Team dsm-firmenich PostNL | F409: 152 | I409: {=INDEX('2024 Points'!$D$14:$D$23,MATCH(1,MMULT(--('2024 Points'!$E$14:$L$23=D409),TRANSPOSE(COLUMN('2024 Points'!$E$14:$L$23)^0)),0))} -> #N/A
A410: 409 | B410: 358 | C410: ▼51 | D410: SOSA Iván Ramiro | E410: Movistar Team | F410: 152 | I410: {=INDEX('2024 Points'!$D$14:$D$23,MATCH(1,MMULT(--('2024 Points'!$E$14:$L$23=D410),TRANSPOSE(COLUMN('2024 Points'!$E$14:$L$23)^0)),0))} -> #N/A
A411: 410 | B411: 1079 | C411: ▲669 | D411: DESAL Ceriel | E411: Bingoal WB | F411: 152 | I411: {=INDEX('2024 Points'!$D$14:$D$23,MATCH(1,MMULT(--('2024 Points'!$E$14:$L$23=D411),TRANSPOSE(COLUMN('2024 Points'!$E$14:$L$23)^0)),0))} -> #N/A
A412: 411 | B412: 467 | C412: ▲56 | D412: SCOTSON Callum | E412: Team Jayco AlUla | F412: 152 | I412: {=INDEX('2024 Points'!$D$14:$D$23,MATCH(1,MMULT(--('2024 Points'!$E$14:$L$23=D412),TRANSPOSE(COLUMN('2024 Points'!$E$14:$L$23)^0)),0))} -> #N/A
A413: 412 | B413: 439 | C413: ▲27 | D413: BARRENETXEA Jon | E413: Movistar Team | F413: 151 | I413: {=INDEX('2024 Points'!$D$14:$D$23,MATCH(1,MMULT(--('2024 Points'!$E$14:$L$23=D413),TRANSPOSE(COLUMN('2024 Points'!$E$14:$L$23)^0)),0))} -> #N/A
A414: 413 | B414: 264 | C414: ▼149 | D414: CHAVES Esteban | E414: EF Education - EasyPost | F414: 151 | I414: {=INDEX('2024 Points'!$D$14:$D$23,MATCH(1,MMULT(--('2024 Points'!$E$14:$L$23=D414),TRANSPOSE(COLUMN('2024 Points'!$E$14:$L$23)^0)),0))} -> #N/A
A415: 414 | B415: 70 | C415: ▼344 | D415: GEOGHEGAN HART Tao | E415: Lidl - Trek | F415: 151 | I415: {=INDEX('2024 Points'!$D$14:$D$23,MATCH(1,MMULT(--('2024 Points'!$E$14:$L$23=D415),TRANSPOSE(COLUMN('2024 Points'!$E$14:$L$23)^0)),0))} -> Cameron
A416: 415 | B416: 1181 | C416: ▲766 | D416: ROMELE Alessandro | E416: Astana Qazaqstan Development Team | F416: 151 | I416: {=INDEX('2024 Points'!$D$14:$D$23,MATCH(1,MMULT(--('2024 Points'!$E$14:$L$23=D416),TRANSPOSE(COLUMN('2024 Points'!$E$14:$L$23)^0)),0))} -> #N/A
A417: 416 | B417: 190 | C417: ▼226 | D417: DEGENKOLB John | E417: Team dsm-firmenich PostNL | F417: 151 | I417: {=INDEX('2024 Points'!$D$14:$D$23,MATCH(1,MMULT(--('2024 Points'!$E$14:$L$23=D417),TRANSPOSE(COLUMN('2024 Points'!$E$14:$L$23)^0)),0))} -> #N/A
A418: 417 | B418: 480 | C418: ▲63 | D418: ZIJLAARD Maikel | E418: Tudor Pro Cycling Team | F418: 150 | I418: {=INDEX('2024 Points'!$D$14:$D$23,MATCH(1,MMULT(--('2024 Points'!$E$14:$L$23=D418),TRANSPOSE(COLUMN('2024 Points'!$E$14:$L$23)^0)),0))} -> #N/A
A419: 418 | B419: 28 | C419: ▼390 | D419: COSTA Rui | E419: EF Education - EasyPost | F419: 149 | I419: {=INDEX('2024 Points'!$D$14:$D$23,MATCH(1,MMULT(--('2024 Points'!$E$14:$L$23=D419),TRANSPOSE(COLUMN('2024 Points'!$E$14:$L$23)^0)),0))} -> Nick
... A423: 422 | B423: 1280 | C423: ▲858 | D423: GALVÁN Francisco | E423: Equipo Kern Pharma | F423: 147 | I423: {=INDEX('2024 Points'!$D$14:$D$23,MATCH(1,MMULT(--('2024 Points'!$E$14:$L$23=D423),TRANSPOSE(COLUMN('2024 Points'!$E$14:$L$23)^0)),0))} -> #N/A
A424: 423 | C424: new | D424: NORDHAGEN Jørgen | E424: Team Visma | Lease a Bike Development | F424: 147 | I424: {=INDEX('2024 Points'!$D$14:$D$23,MATCH(1,MMULT(--('2024 Points'!$E$14:$L$23=D424),TRANSPOSE(COLUMN('2024 Points'!$E$14:$L$23)^0)),0))} -> #N/A
A425: 424 | B425: 233 | C425: ▼191 | D425: BALLERINI Davide | E425: Astana Qazaqstan Team | F425: 147 | I425: {=INDEX('2024 Points'!$D$14:$D$23,MATCH(1,MMULT(--('2024 Points'!$E$14:$L$23=D425),TRANSPOSE(COLUMN('2024 Points'!$E$14:$L$23)^0)),0))} -> #N/A
A426: 425 | B426: 792 | C426: ▲367 | D426: VAN DIJKE Mick | E426: Team Visma | Lease a Bike | F426: 145 | I426: {=INDEX('2024 Points'!$D$14:$D$23,MATCH(1,MMULT(--('2024 Points'!$E$14:$L$23=D426),TRANSPOSE(COLUMN('2024 Points'!$E$14:$L$23)^0)),0))} -> #N/A
A427: 426 | B427: 241 | C427: ▼185 | D427: TOWNSEND Rory | E427: Q36.5 Pro Cycling Team | F427: 145 | I427: {=INDEX('2024 Points'!$D$14:$D$23,MATCH(1,MMULT(--('2024 Points'!$E$14:$L$23=D427),TRANSPOSE(COLUMN('2024 Points'!$E$14:$L$23)^0)),0))} -> #N/A
A428: 427 | B428: 631 | C428: ▲204 | D428: MARIAULT Axel | E428: Cofidis | F428: 144 | I428: {=INDEX('2024 Points'!$D$14:$D$23,MATCH(1,MMULT(--('2024 Points'!$E$14:$L$23=D428),TRANSPOSE(COLUMN('2024 Points'!$E$14:$L$23)^0)),0))} -> #N/A
A429: 428 | B429: 464 | C429: ▲36 | D429: DE VRIES Hartthijs | E429: TDT - Unibet Cycling Team | F429: 144 | I429: {=INDEX('2024 Points'!$D$14:$D$23,MATCH(1,MMULT(--('2024 Points'!$E$14:$L$23=D429),TRANSPOSE(COLUMN('2024 Points'!$E$14:$L$23)^0)),0))} -> #N/A
A430: 429 | B430: 58 | C430: ▼371 | D430: CARUSO Damiano | E430: Bahrain - Victorious | F430: 144 | I430: {=INDEX('2024 Points'!$D$14:$D$23,MATCH(1,MMULT(--('2024 Points'!$E$14:$L$23=D430),TRANSPOSE(COLUMN('2024 Points'!$E$14:$L$23)^0)),0))} -> #N/A
A431: 430 | B431: 1620 | C431: ▲1190 | D431: ROLLAND Brieuc | E431: Equipe continentale Groupama-FDJ | F431: 143 | I431: {=INDEX('2024 Points'!$D$14:$D$23,MATCH(1,MMULT(--('2024 Points'!$E$14:$L$23=D431),TRANSPOSE(COLUMN('2024 Points'!$E$14:$L$23)^0)),0))} -> #N/A
A432: 431 | C432: new | D432: DE SCHUYTENEER Steffen | E432: Lotto Dstny Development Team | F432: 143 | I432: {=INDEX('2024 Points'!$D$14:$D$23,MATCH(1,MMULT(--('2024 Points'!$E$14:$L$23=D432),TRANSPOSE(COLUMN('2024 Points'!$E$14:$L$23)^0)),0))} -> #N/A
A433: 432 | B433: 228 | C433: ▼204 | D433: MARIT Arne | E433: Intermarché - Wanty | F433: 142 | I433: {=INDEX('2024 Points'!$D$14:$D$23,MATCH(1,MMULT(--('2024 Points'!$E$14:$L$23=D433),TRANSPOSE(COLUMN('2024 Points'!$E$14:$L$23)^0)),0))} -> #N/A
A434: 433 | B434: 653 | C434: ▲220 | D434: GIBBONS Ryan | E434: Lidl - Trek | F434: 142 | I434: {=INDEX('2024 Points'!$D$14:$D$23,MATCH(1,MMULT(--('2024 Points'!$E$14:$L$23=D434),TRANSPOSE(COLUMN('2024 Points'!$E$14:$L$23)^0)),0))} -> #N/A
A435: 434 | B435: 433 | C435: ▼1 | D435: SBARAGLI Kristian | E435: Team Corratec - Vini Fantini | F435: 142 | I435: {=INDEX('2024 Points'!$D$14:$D$23,MATCH(1,MMULT(--('2024 Points'!$E$14:$L$23=D435),TRANSPOSE(COLUMN('2024 Points'!$E$14:$L$23)^0)),0))} -> #N/A
A436: 435 | B436: 340 | C436: ▼95 | D436: VARGAS Walter | E436: Team Medellín - EPM | F436: 141 | I436: {=INDEX('2024 Points'!$D$14:$D$23,MATCH(1,MMULT(--('2024 Points'!$E$14:$L$23=D436),TRANSPOSE(COLUMN('2024 Points'!$E$14:$L$23)^0)),0))} -> #N/A
A437: 436 | B437: 420 | C437: ▼16 | D437: COVI Alessandro | E437: UAE Team Emirates | F437: 140 | I437: {=INDEX('2024 Points'!$D$14:$D$23,MATCH(1,MMULT(--('2024 Points'!$E$14:$L$23=D437),TRANSPOSE(COLUMN('2024 Points'!$E$14:$L$23)^0)),0))} -> #N/A
A438: 437 | B438: 599 | C438: ▲162 | D438: O'BRIEN Kelland | E438: Team Jayco AlUla | F438: 139 | I438: {=INDEX('2024 Points'!$D$14:$D$23,MATCH(1,MMULT(--('2024 Points'!$E$14:$L$23=D438),TRANSPOSE(COLUMN('2024 Points'!$E$14:$L$23)^0)),0))} -> #N/A
A439: 438 | B439: 189 | C439: ▼249 | D439: SOBRERO Matteo | E439: Red Bull - BORA - hansgrohe | F439: 139 | I439: {=INDEX('2024 Points'!$D$14:$D$23,MATCH(1,MMULT(--('2024 Points'!$E$14:$L$23=D439),TRANSPOSE(COLUMN('2024 Points'!$E$14:$L$23)^0)),0))} -> #N/A
A440: 439 | B440: 244 | C440: ▼195 | D440: TRÆEN Torstein | E440: Bahrain - Victorious | F440: 139 | I440: {=INDEX('2024 Points'!$D$14:$D$23,MATCH(1,MMULT(--('2024 Points'!$E$14:$L$23=D440),TRANSPOSE(COLUMN('2024 Points'!$E$14:$L$23)^0)),0))} -> #N/A
A441: 440 | B441: 678 | C441: ▲238 | D441: ARCHIBOLD Franklin | E441: Panamá es Cultura y Valores | F441: 138 | I441: {=INDEX('2024 Points'!$D$14:$D$23,MATCH(1,MMULT(--('2024 Points'!$E$14:$L$23=D441),TRANSPOSE(COLUMN('2024 Points'!$E$14:$L$23)^0)),0))} -> #N/A
A442: 441 | B442: 722 | C442: ▲281 | D442: STORK Florian | E442: Tudor Pro Cycling Team | F442: 138 | I442: {=INDEX('2024 Points'!$D$14:$D$23,MATCH(1,MMULT(--('2024 Points'!$E$14:$L$23=D442),TRANSPOSE(COLUMN('2024 Points'!$E$14:$L$23)^0)),0))} -> #N/A
A443: 442 | B443: 1004 | C443: ▲562 | D443: VANGHELUWE Warre | E443: Soudal Quick-Step | F443: 137 | I443: {=INDEX('2024 Points'!$D$14:$D$23,MATCH(1,MMULT(--('2024 Points'!$E$14:$L$23=D443),TRANSPOSE(COLUMN('2024 Points'!$E$14:$L$23)^0)),0))} -> #N/A
A444: 443 | B444: 541 | C444: ▲98 | D444: THOMAS Benjamin | E444: Cofidis | F444: 136 | I444: {=INDEX('2024 Points'!$D$14:$D$23,MATCH(1,MMULT(--('2024 Points'!$E$14:$L$23=D444),TRANSPOSE(COLUMN('2024 Points'!$E$14:$L$23)^0)),0))} -> #N/A
... A467: 466 | B467: 691 | C467: ▲225 | D467: SWIFT Ben | E467: INEOS Grenadiers | F467: 126 | I467: {=INDEX('2024 Points'!$D$14:$D$23,MATCH(1,MMULT(--('2024 Points'!$E$14:$L$23=D467),TRANSPOSE(COLUMN('2024 Points'!$E$14:$L$23)^0)),0))} -> #N/A
A468: 467 | C468: new | D468: SMIRNOV Ivan | E468: PC Baix Ebre | F468: 126 | I468: {=INDEX('2024 Points'!$D$14:$D$23,MATCH(1,MMULT(--('2024 Points'!$E$14:$L$23=D468),TRANSPOSE(COLUMN('2024 Points'!$E$14:$L$23)^0)),0))} -> #N/A
A469: 468 | B469: 867 | C469: ▲399 | D469: GELDERS Gil | E469: Soudal Quick-Step | F469: 125 | I469: {=INDEX('2024 Points'!$D$14:$D$23,MATCH(1,MMULT(--('2024 Points'!$E$14:$L$23=D469),TRANSPOSE(COLUMN('2024 Points'!$E$14:$L$23)^0)),0))} -> #N/A
A470: 469 | B470: 582 | C470: ▲113 | D470: CHAIYASOMBAT Thanakhan | E470: Thailand Continental Cycling Team | F470: 124 | I470: {=INDEX('2024 Points'!$D$14:$D$23,MATCH(1,MMULT(--('2024 Points'!$E$14:$L$23=D470),TRANSPOSE(COLUMN('2024 Points'!$E$14:$L$23)^0)),0))} -> #N/A
A471: 470 | B471: 530 | C471: ▲60 | D471: BERHE Welay Hagos | E471: Team Jayco AlUla | F471: 124 | I471: {=INDEX('2024 Points'!$D$14:$D$23,MATCH(1,MMULT(--('2024 Points'!$E$14:$L$23=D471),TRANSPOSE(COLUMN('2024 Points'!$E$14:$L$23)^0)),0))} -> #N/A
A472: 471 | B472: 1054 | C472: ▲583 | D472: ARTZ Huub | E472: Wanty - ReUz - Technord | F472: 124 | I472: {=INDEX('2024 Points'!$D$14:$D$23,MATCH(1,MMULT(--('2024 Points'!$E$14:$L$23=D472),TRANSPOSE(COLUMN('2024 Points'!$E$14:$L$23)^0)),0))} -> #N/A
A473: 472 | B473: 586 | C473: ▲114 | D473: STAUNE-MITTET Johannes | E473: Team Visma | Lease a Bike | F473: 123 | I473: {=INDEX('2024 Points'!$D$14:$D$23,MATCH(1,MMULT(--('2024 Points'!$E$14:$L$23=D473),TRANSPOSE(COLUMN('2024 Points'!$E$14:$L$23)^0)),0))} -> #N/A
A474: 473 | B474: 1039 | C474: ▲566 | D474: WALKER Max | E474: Astana Qazaqstan Development Team | F474: 123 | I474: {=INDEX('2024 Points'!$D$14:$D$23,MATCH(1,MMULT(--('2024 Points'!$E$14:$L$23=D474),TRANSPOSE(COLUMN('2024 Points'!$E$14:$L$23)^0)),0))} -> #N/A
A475: 474 | B475: 321 | C475: ▼153 | D475: KOISHI Yuma | E475: JCL Team UKYO | F475: 122 | I475: {=INDEX('2024 Points'!$D$14:$D$23,MATCH(1,MMULT(--('2024 Points'!$E$14:$L$23=D475),TRANSPOSE(COLUMN('2024 Points'!$E$14:$L$23)^0)),0))} -> #N/A
...

Sheet 2024 Draft
A1: Nick | C1: Tim | E1: Cameron | G1: Andrew | I1: Chris | L1: Riders
A2: Budget remaining | B2: =1000-SUM(B5:B12) -> 8 | C2: Budget remaining | D2: =1000-SUM(D5:D12) -> 43 | E2: Budget remaining | F2: =1000-SUM(F5:F12) -> 34 | G2: Budget remaining | H2: =1000-SUM(H5:H12) -> 12 | I2: Budget remaining | J2: =1000-SUM(J5:J12) -> 87 | L2: Pogačar Tadej
A3: Spaces remaining | B3: =COUNTBLANK(A5:A12) -> 0 | C3: Spaces remaining | D3: =COUNTBLANK(C5:C12) -> 0 | E3: Spaces remaining | F3: =COUNTBLANK(E5:E12) -> 0 | G3: Spaces remaining | H3: =COUNTBLANK(G5:G12) -> 0 | I3: Spaces remaining | J3: =COUNTBLANK(I5:I12) -> 0 | L3: Evenepoel Remco
A4: Rider | B4: Spend | C4: Rider | D4: Spend | E4: Rider | F4: Spend | G4: Rider | H4: Spend | I4: Rider | J4: Spend | L4: Vingegaard Jonas
A5: van der Poel Mathieu | B5: 500 | C5: Vingegaard Jonas | D5: 690 | E5: Pogačar Tadej | F5: 780 | G5: Evenepoel Remco | H5: 600 | I5: Roglič Primož | J5: 610 | L5: Roglič Primož
A6: Pedersen Mads | B6: 300 | C6: Benoot Tiesj | D6: 40 | E6: Geoghegan Hart Tao | F6: 45 | G6: Martin Guillaume | H6: 55 | I6: Kuss Sepp | J6: 170 | L6: Philipsen Jasper
A7: Ganna Filippo | B7: 125 | C7: Hindley Jai | D7: 45 | E7: Rodríguez Carlos | F7: 46 | G7: Jorgenson Matteo | H7: 120 | I7: Vlasov Aleksandr | J7: 32 | L7: Pedersen Mads
A8: Tarling Joshua | B8: 30 | C8: McNulty Brandon | D8: 30 | E8: Alaphilippe Julian | F8: 46 | G8: Ayuso Juan | H8: 110 | I8: Thomas Geraint | J8: 24 | L8: van Aert Wout
A9: Cavendish Mark | B9: 25 | C9: Skjelmose Mattias | D9: 97 | E9: Gaudu David | F9: 27 | G9: Madouas Valentin | H9: 46 | I9: Lampaert Yves | J9: 12 | L9: Yates Adam
A10: Groenewegen Dylan | B10: 10 | C10: Van Wilder Ilan | D10: 20 | E10: Landa Mikel | F10: 11 | G10: Uijtdebroeks Cian | H10: 45 | I10: Sivakov Pavel | J10: 20 | L10: Hirschi Marc
A11: Costa Rui | B11: 1 | C11: O'Connor Ben | D11: 25 | E11: Hirschi Marc | F11: 10 | G11: Vermeersch Florian | H11: 10 | I11: Merlier Tim | J11: 20 | L11: van der Poel Mathieu
A12: Jakobsen Fabio | B12: 1 | C12: Kämna Lennard | D12: 10 | E12: Bardet Romain | F12: 1 | G12: Lutsenko Alexey | H12: 2 | I12: Grégoire Romain | J12: 25 | L12: De Lie Arnaud
A13: Mike | C13: Joe | E13: Campbell | G13: Dave | I13: Hipster's Choice | L13: Skjelmose Mattias
A14: Budget remaining | B14: =1000-SUM(B17:B24) -> 1 | C14: Budget remaining | D14: =1000-SUM(D17:D24) -> 0 | E14: Budget remaining | F14: =1000-SUM(F17:F24) -> 8 | G14: Budget remaining | H14: =1000-SUM(H17:H24) -> 1000 | I14: Budget remaining | J14: =1000-SUM(J17:J24) -> 1000 | L14: Almeida João
A15: Spaces remaining | B15: =COUNTBLANK(A17:A24) -> 0 | C15: Spaces remaining | D15: =COUNTBLANK(C17:C24) -> 0 | E15: Spaces remaining | F15: =COUNTBLANK(E17:E24) -> 0 | G15: Spaces remaining | H15: =COUNTBLANK(G17:G24) -> 0 | I15: Spaces remaining | J15: =COUNTBLANK(I17:I24) -> 0 | L15: Ganna Filippo
A16: Rider | B16: Spend | C16: Rider | D16: Spend | E16: Rider | F16: Spend | G16: Rider | H16: Spend | I16: Rider | J16: Spend | L16: Kooij Olav
A17: Kooij Olav | B17: 210 | C17: Pidcock Thomas | D17: 140 | E17: van Aert Wout | F17: 470 | G17: Zingle Axel | I17: Kragh Andersen Søren | L17: Yates Simon
A18: Philipsen Jasper | B18: 450 | C18: Almeida João | D18: 160 | E18: Groves Kaden | F18: 70 | G18: Rubio Einer | I18: Cort Magnus | L18: Bilbao Pello
A19: De Lie Arnaud | B19: 220 | C19: Healy Ben | D19: 115 | E19: Mohorič Matej | F19: 180 | G19: Buitrago Santiago | I19: Asgreen Kasper | L19: Landa Mikel
A20: Yates Simon | B20: 26 | C20: Tiller Rasmus | D20: 10 | E20: Powless Neilson | F20: 100 | G20: Woods Michael | I20: Vine Jay | L20: Mohorič Matej
A21: Küng Stefan | B21: 35 | C21: Mas Enric | D21: 35 | E21: Gall Felix | F21: 65 | G21: Johannessen Tobias Halland | I21: Milan Jonathan | L21: Laporte Christophe
A22: Ewan Caleb | B22: 20 | C22: Laporte Christophe | D22: 60 | E22: Bilbao Pello | F22: 75 | G22: Bagioli Andrea | I22: Zana Filippo | L22: Kuss Sepp
A23: Girmay Biniam | B23: 14 | C23: Ciccone Giulio | D23: 60 | E23: Sheffield Magnus | F23: 21 | G23: Aranburu Alex | I23: Martinez Lenny | L23: Pinot Thibaut
A24: Carapaz Richard | B24: 24 | C24: Yates Adam | D24: 420 | E24: Gee Derek | F24: 11 | G24: Izagirre Ion | I24: Wright Fred | L24: Pidcock Thomas
L25: Powless Neilson
A26: Budget remaining | B26: =1000-SUM(B29:B36) -> 1000 | C26: Budget remaining | D26: =1000-SUM(D29:D36) -> 1000 | L26: Healy Ben
A27: Spaces remaining | B27: =COUNTBLANK(A29:A36) -> 8 | C27: Spaces remaining | D27: =COUNTBLANK(C29:C36) -> 8 | L27: Gall Felix
A28: Rider | B28: Spend | C28: Rider | D28: Spend | L28: Groves Kaden
L29: Costa Rui
L30: Ciccone Giulio
L31: Jorgenson Matteo
L32: Vlasov Aleksandr
L33: Madouas Valentin
L34: Van Wilder Ilan
L35: Martin Guillaume
L36: Hindley Jai
L37: McNulty Brandon
L38: Vermeersch Florian
L39: Benoot Tiesj
L40: Gaudu David
... L2437: Le Huitouze Eddy

Sheet Current 2023 Points
A1: Team | B1: Rank | C1: Null | D1: Total | E1: Pre Transfer | F1: Post Transfer
A2: Campbell | B2: =rank(D2,D$2:D$13) -> 2 | C2: =countif(G2:N2, 0) -> 0 | D2: =E2+F2 -> 9233 | E2: 4927 | F2: =sum(G2:N2) -> 4306 | G2: =IFERROR(VLOOKUP(G16,'Current 2023 Ranking'!$D:$K,8,0),0) -> 1061 | H2: =IFERROR(VLOOKUP(H16,'Current 2023 Ranking'!$D:$K,8,0),0) -> 1094 | I2: =IFERROR(VLOOKUP(I16,'Current 2023 Ranking'!$D:$K,8,0),0) -> 568 | J2: =IFERROR(VLOOKUP(J16,'Current 2023 Ranking'!$D:$K,8,0),0) -> 237 | K2: =IFERROR(VLOOKUP(K16,'Current 2023 Ranking'!$D:$K,8,0),0) -> 268 | L2: =IFERROR(VLOOKUP(L16,'Current 2023 Ranking'!$D:$K,8,0),0) -> 643 | M2: =IFERROR(VLOOKUP(M16,'Current 2023 Ranking'!$D:$K,8,0),0) -> 131 | N2: =IFERROR(VLOOKUP(N16,'Current 2023 Ranking'!$D:$K,8,0),0) -> 304
A3: Cameron | B3: =rank(D3,D$2:D$13) -> 6 | C3: =countif(G3:N3, 0) -> 0 | D3: =E3+F3 -> 6757 | E3: 3708 | F3: =sum(G3:N3) -> 3049 | G3: =IFERROR(VLOOKUP(G17,'Current 2023 Ranking'!$D:$K,8,0),0) -> 1099 | H3: =IFERROR(VLOOKUP(H17,'Current 2023 Ranking'!$D:$K,8,0),0) -> 306 | I3: =IFERROR(VLOOKUP(I17,'Current 2023 Ranking'!$D:$K,8,0),0) -> 155 | J3: =IFERROR(VLOOKUP(J17,'Current 2023 Ranking'!$D:$K,8,0),0) -> 27 | K3: =IFERROR(VLOOKUP(K17,'Current 2023 Ranking'!$D:$K,8,0),0) -> 205 | L3: =IFERROR(VLOOKUP(L17,'Current 2023 Ranking'!$D:$K,8,0),0) -> 120 | M3: =IFERROR(VLOOKUP(M17,'Current 2023 Ranking'!$D:$K,8,0),0) -> 820 | N3: =IFERROR(VLOOKUP(N17,'Current 2023 Ranking'!$D:$K,8,0),0) -> 317
A4: Chris | B4: =rank(D4,D$2:D$13) -> 12 | C4: =countif(G4:N4, 0) -> 1 | D4: =E4+F4 -> 2762 | E4: 1720 | F4: =sum(G4:N4) -> 1042 | G4: =IFERROR(VLOOKUP(G18,'Current 2023 Ranking'!$D:$K,8,0),0) -> 6 | H4: =IFERROR(VLOOKUP(H18,'Current 2023 Ranking'!$D:$K,8,0),0) -> 1 | I4: =IFERROR(VLOOKUP(I18,'Current 2023 Ranking'!$D:$K,8,0),0) -> 478 | J4: =IFERROR(VLOOKUP(J18,'Current 2023 Ranking'!$D:$K,8,0),0) -> 303 | K4: =IFERROR(VLOOKUP(K18,'Current 2023 Ranking'!$D:$K,8,0),0) -> 0 | L4: =IFERROR(VLOOKUP(L18,'Current 2023 Ranking'!$D:$K,8,0),0) -> 122 | M4: =IFERROR(VLOOKUP(M18,'Current 2023 Ranking'!$D:$K,8,0),0) -> 55 | N4: =IFERROR(VLOOKUP(N18,'Current 2023 Ranking'!$D:$K,8,0),0) -> 77
A5: Jason | B5: =rank(D5,D$2:D$13) -> 8 | C5: =countif(G5:N5, 0) -> 0 | D5: =E5+F5 -> 6029 | E5: 3409 | F5: =sum(G5:N5) -> 2620 | G5: =IFERROR(VLOOKUP(G19,'Current 2023 Ranking'!$D:$K,8,0),0) -> 49 | H5: =IFERROR(VLOOKUP(H19,'Current 2023 Ranking'!$D:$K,8,0),0) -> 589 | I5: =IFERROR(VLOOKUP(I19,'Current 2023 Ranking'!$D:$K,8,0),0) -> 451 | J5: =IFERROR(VLOOKUP(J19,'Current 2023 Ranking'!$D:$K,8,0),0) -> 240 | K5: =IFERROR(VLOOKUP(K19,'Current 2023 Ranking'!$D:$K,8,0),0) -> 20 | L5: =IFERROR(VLOOKUP(L19,'Current 2023 Ranking'!$D:$K,8,0),0) -> 8 | M5: =IFERROR(VLOOKUP(M19,'Current 2023 Ranking'!$D:$K,8,0),0) -> 96 | N5: =IFERROR(VLOOKUP(N19,'Current 2023 Ranking'!$D:$K,8,0),0) -> 1167
A6: Dave | B6: =rank(D6,D$2:D$13) -> 4 | C6: =countif(G6:N6, 0) -> 0 | D6: =E6+F6 -> 8193 | E6: 4490 | F6: =sum(G6:N6) -> 3703 | G6: =IFERROR(VLOOKUP(G20,'Current 2023 Ranking'!$D:$K,8,0),0) -> 1300 | H6: =IFERROR(VLOOKUP(H20,'Current 2023 Ranking'!$D:$K,8,0),0) -> 279 | I6: =IFERROR(VLOOKUP(I20,'Current 2023 Ranking'!$D:$K,8,0),0) -> 260 | J6: =IFERROR(VLOOKUP(J20,'Current 2023 Ranking'!$D:$K,8,0),0) -> 337 | K6: =IFERROR(VLOOKUP(K20,'Current 2023 Ranking'!$D:$K,8,0),0) -> 337 | L6: =IFERROR(VLOOKUP(L20,'Current 2023 Ranking'!$D:$K,8,0),0) -> 604 | M6: =IFERROR(VLOOKUP(M20,'Current 2023 Ranking'!$D:$K,8,0),0) -> 267 | N6: =IFERROR(VLOOKUP(N20,'Current 2023 Ranking'!$D:$K,8,0),0) -> 319
A7: Joe | B7: =rank(D7,D$2:D$13) -> 3 | C7: =countif(G7:N7, 0) -> 0 | D7: =E7+F7 -> 8405 | E7: 4582 | F7: =sum(G7:N7) -> 3823 | G7: =IFERROR(VLOOKUP(G21,'Current 2023 Ranking'!$D:$K,8,0),0) -> 393 | H7: =IFERROR(VLOOKUP(H21,'Current 2023 Ranking'!$D:$K,8,0),0) -> 719 | I7: =IFERROR(VLOOKUP(I21,'Current 2023 Ranking'!$D:$K,8,0),0) -> 449 | J7: =IFERROR(VLOOKUP(J21,'Current 2023 Ranking'!$D:$K,8,0),0) -> 339 | K7: =IFERROR(VLOOKUP(K21,'Current 2023 Ranking'!$D:$K,8,0),0) -> 1055 | L7: =IFERROR(VLOOKUP(L21,'Current 2023 Ranking'!$D:$K,8,0),0) -> 398 | M7: =IFERROR(VLOOKUP(M21,'Current 2023 Ranking'!$D:$K,8,0),0) -> 356 | N7: =IFERROR(VLOOKUP(N21,'Current 2023 Ranking'!$D:$K,8,0),0) -> 114
A8: Nick | B8: =rank(D8,D$2:D$13) -> 7 | C8: =countif(G8:N8, 0) -> 0 | D8: =E8+F8 -> 6679 | E8: 3471 | F8: =sum(G8:N8) -> 3208 | G8: =IFERROR(VLOOKUP(G22,'Current 2023 Ranking'!$D:$K,8,0),0) -> 488 | H8: =IFERROR(VLOOKUP(H22,'Current 2023 Ranking'!$D:$K,8,0),0) -> 1219 | I8: =IFERROR(VLOOKUP(I22,'Current 2023 Ranking'!$D:$K,8,0),0) -> 296 | J8: =IFERROR(VLOOKUP(J22,'Current 2023 Ranking'!$D:$K,8,0),0) -> 121 | K8: =IFERROR(VLOOKUP(K22,'Current 2023 Ranking'!$D:$K,8,0),0) -> 57 | L8: =IFERROR(VLOOKUP(L22,'Current 2023 Ranking'!$D:$K,8,0),0) -> 165 | M8: =IFERROR(VLOOKUP(M22,'Current 2023 Ranking'!$D:$K,8,0),0) -> 128 | N8: =IFERROR(VLOOKUP(N22,'Current 2023 Ranking'!$D:$K,8,0),0) -> 734
A9: Tim | B9: =rank(D9,D$2:D$13) -> 9 | C9: =countif(G9:N9, 0) -> 0 | D9: =E9+F9 -> 5508 | E9: 2967 | F9: =sum(G9:N9) -> 2541 | G9: =IFERROR(VLOOKUP(G23,'Current 2023 Ranking'!$D:$K,8,0),0) -> 911 | H9: =IFERROR(VLOOKUP(H23,'Current 2023 Ranking'!$D:$K,8,0),0) -> 146 | I9: =IFERROR(VLOOKUP(I23,'Current 2023 Ranking'!$D:$K,8,0),0) -> 331 | J9: =IFERROR(VLOOKUP(J23,'Current 2023 Ranking'!$D:$K,8,0),0) -> 155 | K9: =IFERROR(VLOOKUP(K23,'Current 2023 Ranking'!$D:$K,8,0),0) -> 518 | L9: =IFERROR(VLOOKUP(L23,'Current 2023 Ranking'!$D:$K,8,0),0) -> 309 | M9: =IFERROR(VLOOKUP(M23,'Current 2023 Ranking'!$D:$K,8,0),0) -> 159 | N9: =IFERROR(VLOOKUP(N23,'Current 2023 Ranking'!$D:$K,8,0),0) -> 12
A10: Mike | B10: =rank(D10,D$2:D$13) -> 5 | C10: =countif(G10:N10, 0) -> 0 | D10: =E10+F10 -> 7468 | E10: 3873 | F10: =sum(G10:N10) -> 3595 | G10: =IFERROR(VLOOKUP(G24,'Current 2023 Ranking'!$D:$K,8,0),0) -> 215 | H10: =IFERROR(VLOOKUP(H24,'Current 2023 Ranking'!$D:$K,8,0),0) -> 1509 | I10: =IFERROR(VLOOKUP(I24,'Current 2023 Ranking'!$D:$K,8,0),0) -> 59 | J10: =IFERROR(VLOOKUP(J24,'Current 2023 Ranking'!$D:$K,8,0),0) -> 457 | K10: =IFERROR(VLOOKUP(K24,'Current 2023 Ranking'!$D:$K,8,0),0) -> 200 | L10: =IFERROR(VLOOKUP(L24,'Current 2023 Ranking'!$D:$K,8,0),0) -> 183 | M10: =IFERROR(VLOOKUP(M24,'Current 2023 Ranking'!$D:$K,8,0),0) -> 94 | N10: =IFERROR(VLOOKUP(N24,'Current 2023 Ranking'!$D:$K,8,0),0) -> 878
A11: Andy | B11: =rank(D11,D$2:D$13) -> 1 | C11: =countif(G11:N11, 0) -> 0 | D11: =E11+F11 -> 9798 | E11: 5098 | F11: =sum(G11:N11) -> 4700 | G11: =IFERROR(VLOOKUP(G25,'Current 2023 Ranking'!$D:$K,8,0),0) -> 1635 | H11: =IFERROR(VLOOKUP(H25,'Current 2023 Ranking'!$D:$K,8,0),0) -> 387 | I11: =IFERROR(VLOOKUP(I25,'Current 2023 Ranking'!$D:$K,8,0),0) -> 524 | J11: =IFERROR(VLOOKUP(J25,'Current 2023 Ranking'!$D:$K,8,0),0) -> 430 | K11: =IFERROR(VLOOKUP(K25,'Current 2023 Ranking'!$D:$K,8,0),0) -> 521 | L11: =IFERROR(VLOOKUP(L25,'Current 2023 Ranking'!$D:$K,8,0),0) -> 399 | M11: =IFERROR(VLOOKUP(M25,'Current 2023 Ranking'!$D:$K,8,0),0) -> 516 | N11: =IFERROR(VLOOKUP(N25,'Current 2023 Ranking'!$D:$K,8,0),0) -> 288
A12: Past performance is not a reliable indicator of future results | B12: =rank(D12,D$2:D$13) -> 11 | C12: =countif(G12:N12, 0) -> 1 | D12: =E12+F12 -> 3340 | E12: 2470 | F12: =sum(G12:N12) -> 870 | G12: =IFERROR(VLOOKUP(G26,'Current 2023 Ranking'!$D:$K,8,0),0) -> 41 | H12: =IFERROR(VLOOKUP(H26,'Current 2023 Ranking'!$D:$K,8,0),0) -> 82 | I12: =IFERROR(VLOOKUP(I26,'Current 2023 Ranking'!$D:$K,8,0),0) -> 44 | J12: =IFERROR(VLOOKUP(J26,'Current 2023 Ranking'!$D:$K,8,0),0) -> 57 | K12: =IFERROR(VLOOKUP(K26,'Current 2023 Ranking'!$D:$K,8,0),0) -> 32 | L12: =IFERROR(VLOOKUP(L26,'Current 2023 Ranking'!$D:$K,8,0),0) -> 366 | M12: =IFERROR(VLOOKUP(M26,'Current 2023 Ranking'!$D:$K,8,0),0) -> 0 | N12: =IFERROR(VLOOKUP(N26,'Current 2023 Ranking'!$D:$K,8,0),0) -> 248
A13: Hipster's Choice | B13: =rank(D13,D$2:D$13) -> 10 | C13: =countif(G13:N13, 0) -> 0 | D13: =E13+F13 -> 3798 | E13: 2086 | F13: =sum(G13:N13) -> 1712 | G13: =IFERROR(VLOOKUP(G27,'Current 2023 Ranking'!$D:$K,8,0),0) -> 38 | H13: =IFERROR(VLOOKUP(H27,'Current 2023 Ranking'!$D:$K,8,0),0) -> 657 | I13: =IFERROR(VLOOKUP(I27,'Current 2023 Ranking'!$D:$K,8,0),0) -> 543 | J13: =IFERROR(VLOOKUP(J27,'Current 2023 Ranking'!$D:$K,8,0),0) -> 54 | K13: =IFERROR(VLOOKUP(K27,'Current 2023 Ranking'!$D:$K,8,0),0) -> 10 | L13: =IFERROR(VLOOKUP(L27,'Current 2023 Ranking'!$D:$K,8,0),0) -> 27 | M13: =IFERROR(VLOOKUP(M27,'Current 2023 Ranking'!$D:$K,8,0),0) -> 158 | N13: =IFERROR(VLOOKUP(N27,'Current 2023 Ranking'!$D:$K,8,0),0) -> 225
F15: Manager | G15: 1 | H15: 2 | I15: 3 | J15: 4 | K15: 5 | L15: 6 | M15: 7 | N15: 8
A16: Campbell | F16: Campbell | G16: Roglič Primož | H16: Pedersen Mads | I16: van der Poel Mathieu | J16: Healy Ben | K16: Jorgenson Matteo | L16: Rodríguez Carlos | M16: Bennett Sam | N16: Kragh Andersen Søren
A17: Cameron | F17: Cameron | G17: van Aert Wout | H17: Bardet Romain | I17: Bettiol Alberto | J17: Martínez Daniel Felipe | K17: Matthews Michael | L17: van Baarle Dylan | M17: Mohorič Matej | N17: Pinot Thibaut
A18: Chris | F18: Chris | G18: Arensman Thymen | H18: Meintjes Louis | I18: McNulty Brandon | J18: Trentin Matteo | K18: Quintana Nairo | L18: Hermans Quinten | M18: López Miguel Ángel | N18: Simon Julien
A19: Jason | F19: Jason | G19: Higuita Sergio | H19: Skjelmose Mattias | I19: Landa Mikel | J19: Barguil Warren | K19: Thomas Benjamin | L19: Capiot Amaury | M19: Mollema Bauke | N19: Hirschi Marc
A20: Dave | F20: Dave | G20: Evenepoel Remco | H20: Hayter Ethan | I20: Ciccone Giulio | J20: Woods Michael | K20: Izagirre Ion | L20: Kooij Olav | M20: Pidcock Thomas | N20: Powless Neilson
A21: Joe | F21: Joe | G21: Kristoff Alexander | H21: Bilbao Pello | I21: Groenewegen Dylan | J21: Laporte Christophe | K21: Yates Adam | L21: Küng Stefan | M21: Démare Arnaud | N21: Thomas Geraint
A22: Nick | F22: Nick | G22: Hindley Jai | H22: Philipsen Jasper | I22: Carapaz Richard | J22: Ewan Caleb | K22: Bernal Egan | L22: Alaphilippe Julian | M22: Cavendish Mark | N22: Ganna Filippo
A23: Tim | F23: Tim | G23: De Lie Arnaud | H23: Cort Magnus | I23: Lampaert Yves | J23: Zana Filippo | K23: van Poppel Danny | L23: Mozzato Luca | M23: Caruso Damiano | N23: Consonni Simone
A24: Mike | F24: Mike | G24: Girmay Biniam | H24: Vingegaard Jonas | I24: Wright Fred | J24: Ayuso Juan | K24: Kelderman Wilco | L24: Jakobsen Fabio | M24: Vine Jay | N24: Yates Simon
A25: Andy | F25: Andy | G25: Pogačar Tadej | H25: Mas Enric | I25: Almeida João | J25: Benoot Tiesj | K25: Madouas Valentin | L25: O'Connor Ben | M25: Martin Guillaume | N25: Gaudu David
A26: Past performance is not a reliable indicator of future results | F26: Past performance is not a reliable indicator of future results | G26: Gaviria Fernando | H26: Sagan Peter | I26: Schachmann Maximilian | J26: Foss Tobias | K26: Ackermann Pascal | L26: Stuyven Jasper | M26: Geoghegan Hart Tao | N26: Carthy Hugh
A27: Hipster's Choice | F27: Hipster's Choice | G27: Vansevenant Mauri | H27: Johannessen Tobias Halland | I27: Sivakov Pavel | J27: Gee Derek | K27: Plapp Luke | L27: Leknessund Andreas | M27: Turgis Anthony | N27: Uijtdebroeks Cian

Sheet Current 2023 Ranking
A1: Rank | B1: Prev. Rank | C1: Rank Diff. | D1: Rider | E1: Team | F1: Points | I1: Manager | K1: Adjusted points | L1: In pre-transfer team? | M1: In post-transfer team?
A2: 1 | B2: 1 | C2: - | D2: Pogačar Tadej | E2: UAE Team Emirates | F2: 3309 | I2: {=INDEX('Current 2023 Points'!$F$16:$F$27,MATCH(1,MMULT(--('Current 2023 Points'!$G$16:$N$27=D2),TRANSPOSE(COLUMN('Current 2023 Points'!$G$16:$N$27)^0)),0))} -> Andy | K2: =F2-IFERROR(VLOOKUP(D2,'Pre-transfer 2023 Ranking'!$D:$F,3,0),0) -> 1635 | L2: =countif('Pre-transfer 2023 Points'!$E$13:$L$21,D2) -> 0 | M2: =countif('Current 2023 Points'!$G$13:$N$21,D2) -> 0
A3: 2 | B3: 3 | C3: ▲1 | D3: Evenepoel Remco | E3: Soudal - Quick Step | F3: 2843 | I3: {=INDEX('Current 2023 Points'!$F$16:$F$27,MATCH(1,MMULT(--('Current 2023 Points'!$G$16:$N$27=D3),TRANSPOSE(COLUMN('Current 2023 Points'!$G$16:$N$27)^0)),0))} -> Dave | K3: =F3-IFERROR(VLOOKUP(D3,'Pre-transfer 2023 Ranking'!$D:$F,3,0),0) -> 1300 | L3: =countif('Pre-transfer 2022 Points'!$E$13:$L$21,D3) -> 1 | M3: =countif('2022 Points'!$G$13:$N$21,D3) -> 1
A4: 3 | B4: 4 | C4: ▲1 | D4: Vingegaard Jonas | E4: Jumbo-Visma | F4: 2715 | I4: {=INDEX('Current 2023 Points'!$F$16:$F$27,MATCH(1,MMULT(--('Current 2023 Points'!$G$16:$N$27=D4),TRANSPOSE(COLUMN('Current 2023 Points'!$G$16:$N$27)^0)),0))} -> Mike | K4: =F4-IFERROR(VLOOKUP(D4,'Pre-transfer 2023 Ranking'!$D:$F,3,0),0) -> 1509 | L4: =countif('Pre-transfer 2022 Points'!$E$13:$L$21,D4) -> 1 | M4: =countif('2022 Points'!$G$13:$N$21,D4) -> 1
A5: 4 | B5: 16 | C5: ▲12 | D5: Roglič Primož | E5: Jumbo-Visma | F5: 2526 | I5: {=INDEX('Current 2023 Points'!$F$16:$F$27,MATCH(1,MMULT(--('Current 2023 Points'!$G$16:$N$27=D5),TRANSPOSE(COLUMN('Current 2023 Points'!$G$16:$N$27)^0)),0))} -> Campbell | K5: =F5-IFERROR(VLOOKUP(D5,'Pre-transfer 2023 Ranking'!$D:$F,3,0),0) -> 1061 | L5: =countif('Pre-transfer 2022 Points'!$E$13:$L$21,D5) -> 1 | M5: =countif('2022 Points'!$G$13:$N$21,D5) -> 1
A6: 5 | B6: 7 | C6: ▲2 | D6: Philipsen Jasper | E6: Alpecin-Deceuninck | F6: 2152 | I6: {=INDEX('Current 2023 Points'!$F$16:$F$27,MATCH(1,MMULT(--('Current 2023 Points'!$G$16:$N$27=D6),TRANSPOSE(COLUMN('Current 2023 Points'!$G$16:$N$27)^0)),0))} -> Nick | K6: =F6-IFERROR(VLOOKUP(D6,'Pre-transfer 2023 Ranking'!$D:$F,3,0),0) -> 1219 | L6: =countif('Pre-transfer 2022 Points'!$E$13:$L$21,D6) -> 1 | M6: =countif('2022 Points'!$G$13:$N$21,D6) -> 1
A7: 6 | B7: 6 | C7: - | D7: Pedersen Mads | E7: Lidl - Trek | F7: 1989 | I7: {=INDEX('Current 2023 Points'!$F$16:$F$27,MATCH(1,MMULT(--('Current 2023 Points'!$G$16:$N$27=D7),TRANSPOSE(COLUMN('Current 2023 Points'!$G$16:$N$27)^0)),0))} -> Campbell | K7: =F7-IFERROR(VLOOKUP(D7,'Pre-transfer 2023 Ranking'!$D:$F,3,0),0) -> 1094 | L7: =countif('Pre-transfer 2022 Points'!$E$13:$L$21,D7) -> 0 | M7: =countif('2022 Points'!$G$13:$N$21,D7) -> 0
A8: 7 | B8: 2 | C8: ▼5 | D8: van Aert Wout | E8: Jumbo-Visma | F8: 1988 | I8: {=INDEX('Current 2023 Points'!$F$16:$F$27,MATCH(1,MMULT(--('Current 2023 Points'!$G$16:$N$27=D8),TRANSPOSE(COLUMN('Current 2023 Points'!$G$16:$N$27)^0)),0))} -> Cameron | K8: =F8-IFERROR(VLOOKUP(D8,'Pre-transfer 2023 Ranking'!$D:$F,3,0),0) -> 1099 | L8: =countif('Pre-transfer 2022 Points'!$E$13:$L$21,D8) -> 1 | M8: =countif('2022 Points'!$G$13:$N$21,D8) -> 1
A9: 8 | B9: 23 | C9: ▲15 | D9: Yates Adam | E9: UAE Team Emirates | F9: 1947 | I9: {=INDEX('Current 2023 Points'!$F$16:$F$27,MATCH(1,MMULT(--('Current 2023 Points'!$G$16:$N$27=D9),TRANSPOSE(COLUMN('Current 2023 Points'!$G$16:$N$27)^0)),0))} -> Joe | K9: =F9-IFERROR(VLOOKUP(D9,'Pre-transfer 2023 Ranking'!$D:$F,3,0),0) -> 1055 | L9: =countif('Pre-transfer 2022 Points'!$E$13:$L$21,D9) -> 1 | M9: =countif('2022 Points'!$G$13:$N$21,D9) -> 1
A10: 9 | B10: 70 | C10: ▲61 | D10: Hirschi Marc | E10: UAE Team Emirates | F10: 1817 | I10: {=INDEX('Current 2023 Points'!$F$16:$F$27,MATCH(1,MMULT(--('Current 2023 Points'!$G$16:$N$27=D10),TRANSPOSE(COLUMN('Current 2023 Points'!$G$16:$N$27)^0)),0))} -> Jason | K10: =F10-IFERROR(VLOOKUP(D10,'Pre-transfer 2023 Ranking'!$D:$F,3,0),0) -> 1167 | L10: =countif('Pre-transfer 2022 Points'!$E$13:$L$21,D10) -> 1 | M10: =countif('2022 Points'!$G$13:$N$21,D10) -> 1
A11: 10 | B11: 18 | C11: ▲8 | D11: van der Poel Mathieu | E11: Alpecin-Deceuninck | F11: 1719 | I11: {=INDEX('Current 2023 Points'!$F$16:$F$27,MATCH(1,MMULT(--('Current 2023 Points'!$G$16:$N$27=D11),TRANSPOSE(COLUMN('Current 2023 Points'!$G$16:$N$27)^0)),0))} -> Campbell | K11: =F11-IFERROR(VLOOKUP(D11,'Pre-transfer 2023 Ranking'!$D:$F,3,0),0) -> 568 | L11: =countif('Pre-transfer 2022 Points'!$E$13:$L$21,D11) -> 1 | M11: =countif('2022 Points'!$G$13:$N$21,D11) -> 1
A12: 11 | B12: 13 | C12: ▲2 | D12: De Lie Arnaud | E12: Lotto Dstny | F12: 1695 | I12: {=INDEX('Current 2023 Points'!$F$16:$F$27,MATCH(1,MMULT(--('Current 2023 Points'!$G$16:$N$27=D12),TRANSPOSE(COLUMN('Current 2023 Points'!$G$16:$N$27)^0)),0))} -> Tim | K12: =F12-IFERROR(VLOOKUP(D12,'Pre-transfer 2023 Ranking'!$D:$F,3,0),0) -> 911 | L12: =countif('Pre-transfer 2022 Points'!$E$13:$L$21,D12) -> 0 | M12: =countif('2022 Points'!$G$13:$N$21,D12) -> 1
A13: 12 | B13: 42 | C13: ▲30 | D13: Skjelmose Mattias | E13: Lidl - Trek | F13: 1595 | I13: {=INDEX('Current 2023 Points'!$F$16:$F$27,MATCH(1,MMULT(--('Current 2023 Points'!$G$16:$N$27=D13),TRANSPOSE(COLUMN('Current 2023 Points'!$G$16:$N$27)^0)),0))} -> Jason | K13: =F13-IFERROR(VLOOKUP(D13,'Pre-transfer 2023 Ranking'!$D:$F,3,0),0) -> 589 | L13: =countif('Pre-transfer 2022 Points'!$E$13:$L$21,D13) -> 0 | M13: =countif('2022 Points'!$G$13:$N$21,D13) -> 0
A14: 13 | B14: 32 | C14: ▲19 | D14: Almeida João | E14: UAE Team Emirates | F14: 1478 | I14: {=INDEX('Current 2023 Points'!$F$16:$F$27,MATCH(1,MMULT(--('Current 2023 Points'!$G$16:$N$27=D14),TRANSPOSE(COLUMN('Current 2023 Points'!$G$16:$N$27)^0)),0))} -> Andy | K14: =F14-IFERROR(VLOOKUP(D14,'Pre-transfer 2023 Ranking'!$D:$F,3,0),0) -> 524 | L14: =countif('Pre-transfer 2022 Points'!$E$13:$L$21,D14) -> 1 | M14: =countif('2022 Points'!$G$13:$N$21,D14) -> 1
... A127: 126 | B127: 181 | C127: ▲55 | D127: Valter Attila | E127: Jumbo-Visma | F127: 468 | I127: {=INDEX('Current 2023 Points'!$F$16:$F$27,MATCH(1,MMULT(--('Current 2023 Points'!$G$16:$N$27=D127),TRANSPOSE(COLUMN('Current 2023 Points'!$G$16:$N$27)^0)),0))} -> #N/A | K127: =F127-IFERROR(VLOOKUP(D127,'Pre-transfer 2023 Ranking'!$D:$F,3,0),0) -> 125 | L127: =countif('Pre-transfer 2022 Points'!$E$13:$L$21,D127) -> 0 | M127: =countif('2022 Points'!$G$13:$N$21,D127) -> 0
A128: 127 | C128: new | D128: Tarling Joshua | E128: INEOS Grenadiers | F128: 467 | I128: {=INDEX('Current 2023 Points'!$F$16:$F$27,MATCH(1,MMULT(--('Current 2023 Points'!$G$16:$N$27=D128),TRANSPOSE(COLUMN('Current 2023 Points'!$G$16:$N$27)^0)),0))} -> #N/A | K128: =F128-IFERROR(VLOOKUP(D128,'Pre-transfer 2023 Ranking'!$D:$F,3,0),0) -> 438 | L128: =countif('Pre-transfer 2022 Points'!$E$13:$L$21,D128) -> 0 | M128: =countif('2022 Points'!$G$13:$N$21,D128) -> 0
A129: 128 | B129: 256 | C129: ▲128 | D129: Vernon Ethan | E129: Soudal - Quick Step | F129: 463 | I129: {=INDEX('Current 2023 Points'!$F$16:$F$27,MATCH(1,MMULT(--('Current 2023 Points'!$G$16:$N$27=D129),TRANSPOSE(COLUMN('Current 2023 Points'!$G$16:$N$27)^0)),0))} -> #N/A | K129: =F129-IFERROR(VLOOKUP(D129,'Pre-transfer 2023 Ranking'!$D:$F,3,0),0) -> 142 | L129: =countif('Pre-transfer 2022 Points'!$E$13:$L$21,D129) -> 0 | M129: =countif('2022 Points'!$G$13:$N$21,D129) -> 0
A130: 129 | B130: 788 | C130: ▲659 | D130: Gee Derek | E130: Israel - Premier Tech | F130: 461 | I130: {=INDEX('Current 2023 Points'!$F$16:$F$27,MATCH(1,MMULT(--('Current 2023 Points'!$G$16:$N$27=D130),TRANSPOSE(COLUMN('Current 2023 Points'!$G$16:$N$27)^0)),0))} -> Hipster's Choice | K130: =F130-IFERROR(VLOOKUP(D130,'Pre-transfer 2023 Ranking'!$D:$F,3,0),0) -> 54 | L130: =countif('Pre-transfer 2022 Points'!$E$13:$L$21,D130) -> 0 | M130: =countif('2022 Points'!$G$13:$N$21,D130) -> 0
A131: 130 | B131: 88 | C131: ▼42 | D131: Vauquelin Kévin | E131: Team Arkéa Samsic | F131: 461 | I131: {=INDEX('Current 2023 Points'!$F$16:$F$27,MATCH(1,MMULT(--('Current 2023 Points'!$G$16:$N$27=D131),TRANSPOSE(COLUMN('Current 2023 Points'!$G$16:$N$27)^0)),0))} -> #N/A | K131: =F131-IFERROR(VLOOKUP(D131,'Pre-transfer 2023 Ranking'!$D:$F,3,0),0) -> 69 | L131: =countif('Pre-transfer 2022 Points'!$E$13:$L$21,D131) -> 0 | M131: =countif('2022 Points'!$G$13:$N$21,D131) -> 0
A132: 131 | B132: 240 | C132: ▲109 | D132: Formolo Davide | E132: UAE Team Emirates | F132: 453 | I132: {=INDEX('Current 2023 Points'!$F$16:$F$27,MATCH(1,MMULT(--('Current 2023 Points'!$G$16:$N$27=D132),TRANSPOSE(COLUMN('Current 2023 Points'!$G$16:$N$27)^0)),0))} -> #N/A | K132: =F132-IFERROR(VLOOKUP(D132,'Pre-transfer 2023 Ranking'!$D:$F,3,0),0) -> 293 | L132: =countif('Pre-transfer 2022 Points'!$E$13:$L$21,D132) -> 0 | M132: =countif('2022 Points'!$G$13:$N$21,D132) -> 0
A133: 132 | B133: 19 | C133: ▼113 | D133: Carapaz Richard | E133: EF Education-EasyPost | F133: 453 | I133: {=INDEX('Current 2023 Points'!$F$16:$F$27,MATCH(1,MMULT(--('Current 2023 Points'!$G$16:$N$27=D133),TRANSPOSE(COLUMN('Current 2023 Points'!$G$16:$N$27)^0)),0))} -> Nick | K133: =F133-IFERROR(VLOOKUP(D133,'Pre-transfer 2023 Ranking'!$D:$F,3,0),0) -> 296 | L133: =countif('Pre-transfer 2022 Points'!$E$13:$L$21,D133) -> 1 | M133: =countif('2022 Points'!$G$13:$N$21,D133) -> 1
A134: 133 | B134: 436 | C134: ▲303 | D134: Van Eetvelt Lennert | E134: Lotto Dstny | F134: 451 | I134: {=INDEX('Current 2023 Points'!$F$16:$F$27,MATCH(1,MMULT(--('Current 2023 Points'!$G$16:$N$27=D134),TRANSPOSE(COLUMN('Current 2023 Points'!$G$16:$N$27)^0)),0))} -> #N/A | K134: =F134-IFERROR(VLOOKUP(D134,'Pre-transfer 2023 Ranking'!$D:$F,3,0),0) -> 225 | L134: =countif('Pre-transfer 2022 Points'!$E$13:$L$21,D134) -> 0 | M134: =countif('2022 Points'!$G$13:$N$21,D134) -> 0
A135: 134 | B135: 227 | C135: ▲93 | D135: Dunbar Eddie | E135: Team Jayco AlUla | F135: 451 | I135: {=INDEX('Current 2023 Points'!$F$16:$F$27,MATCH(1,MMULT(--('Current 2023 Points'!$G$16:$N$27=D135),TRANSPOSE(COLUMN('Current 2023 Points'!$G$16:$N$27)^0)),0))} -> #N/A | K135: =F135-IFERROR(VLOOKUP(D135,'Pre-transfer 2023 Ranking'!$D:$F,3,0),0) -> 123 | L135: =countif('Pre-transfer 2022 Points'!$E$13:$L$21,D135) -> 0 | M135: =countif('2022 Points'!$G$13:$N$21,D135) -> 0
A136: 135 | B136: 235 | C136: ▲100 | D136: Kamp Alexander | E136: Tudor Pro Cycling Team | F136: 450 | I136: {=INDEX('Current 2023 Points'!$F$16:$F$27,MATCH(1,MMULT(--('Current 2023 Points'!$G$16:$N$27=D136),TRANSPOSE(COLUMN('Current 2023 Points'!$G$16:$N$27)^0)),0))} -> #N/A | K136: =F136-IFERROR(VLOOKUP(D136,'Pre-transfer 2023 Ranking'!$D:$F,3,0),0) -> 138 | L136: =countif('Pre-transfer 2022 Points'!$E$13:$L$21,D136) -> 0 | M136: =countif('2022 Points'!$G$13:$N$21,D136) -> 0
A137: 136 | B137: 526 | C137: ▲390 | D137: Poole Max | E137: Team dsm - firmenich | F137: 446 | I137: {=INDEX('Current 2023 Points'!$F$16:$F$27,MATCH(1,MMULT(--('Current 2023 Points'!$G$16:$N$27=D137),TRANSPOSE(COLUMN('Current 2023 Points'!$G$16:$N$27)^0)),0))} -> #N/A | K137: =F137-IFERROR(VLOOKUP(D137,'Pre-transfer 2023 Ranking'!$D:$F,3,0),0) -> 91 | L137: =countif('Pre-transfer 2022 Points'!$E$13:$L$21,D137) -> 0 | M137: =countif('2022 Points'!$G$13:$N$21,D137) -> 0
A138: 137 | B138: 499 | C138: ▲362 | D138: Zwiehoff Ben | E138: BORA - hansgrohe | F138: 443 | I138: {=INDEX('Current 2023 Points'!$F$16:$F$27,MATCH(1,MMULT(--('Current 2023 Points'!$G$16:$N$27=D138),TRANSPOSE(COLUMN('Current 2023 Points'!$G$16:$N$27)^0)),0))} -> #N/A | K138: =F138-IFERROR(VLOOKUP(D138,'Pre-transfer 2023 Ranking'!$D:$F,3,0),0) -> 195 | L138: =countif('Pre-transfer 2022 Points'!$E$13:$L$21,D138) -> 0 | M138: =countif('2022 Points'!$G$13:$N$21,D138) -> 0
A139: 138 | B139: 447 | C139: ▲309 | D139: Engelhardt Felix | E139: Team Jayco AlUla | F139: 442 | I139: {=INDEX('Current 2023 Points'!$F$16:$F$27,MATCH(1,MMULT(--('Current 2023 Points'!$G$16:$N$27=D139),TRANSPOSE(COLUMN('Current 2023 Points'!$G$16:$N$27)^0)),0))} -> #N/A | K139: =F139-IFERROR(VLOOKUP(D139,'Pre-transfer 2023 Ranking'!$D:$F,3,0),0) -> 268 | L139: =countif('Pre-transfer 2022 Points'!$E$13:$L$21,D139) -> 0 | M139: =countif('2022 Points'!$G$13:$N$21,D139) -> 0
A140: 139 | B140: 81 | C140: ▼58 | D140: Cavendish Mark | E140: Astana Qazaqstan Team | F140: 439 | I140: {=INDEX('Current 2023 Points'!$F$16:$F$27,MATCH(1,MMULT(--('Current 2023 Points'!$G$16:$N$27=D140),TRANSPOSE(COLUMN('Current 2023 Points'!$G$16:$N$27)^0)),0))} -> Nick | K140: =F140-IFERROR(VLOOKUP(D140,'Pre-transfer 2023 Ranking'!$D:$F,3,0),0) -> 128 | L140: =countif('Pre-transfer 2022 Points'!$E$13:$L$21,D140) -> 1 | M140: =countif('2022 Points'!$G$13:$N$21,D140) -> 1
... A196: 195 | B196: 231 | C196: ▲36 | D196: Dupont Timothy | E196: Tarteletto - Isorex | F196: 327 | I196: {=INDEX('Current 2023 Points'!$F$16:$F$27,MATCH(1,MMULT(--('Current 2023 Points'!$G$16:$N$27=D196),TRANSPOSE(COLUMN('Current 2023 Points'!$G$16:$N$27)^0)),0))} -> #N/A | K196: =F196-IFERROR(VLOOKUP(D196,'Pre-transfer 2023 Ranking'!$D:$F,3,0),0) -> 128 | L196: =countif('Pre-transfer 2022 Points'!$E$13:$L$21,D196) -> 0 | M196: =countif('2022 Points'!$G$13:$N$21,D196) -> 0
A197: 196 | C197: new | D197: Sevilla Óscar | E197: Team Medellín - EPM | F197: 326 | I197: {=INDEX('Current 2023 Points'!$F$16:$F$27,MATCH(1,MMULT(--('Current 2023 Points'!$G$16:$N$27=D197),TRANSPOSE(COLUMN('Current 2023 Points'!$G$16:$N$27)^0)),0))} -> #N/A | K197: =F197-IFERROR(VLOOKUP(D197,'Pre-transfer 2023 Ranking'!$D:$F,3,0),0) -> 233 | L197: =countif('Pre-transfer 2022 Points'!$E$13:$L$21,D197) -> 0 | M197: =countif('2022 Points'!$G$13:$N$21,D197) -> 0
A198: 197 | B198: 1114 | C198: ▲917 | D198: Zanoncello Enrico | E198: Green Project-Bardiani CSF-Faizanè | F198: 325 | I198: {=INDEX('Current 2023 Points'!$F$16:$F$27,MATCH(1,MMULT(--('Current 2023 Points'!$G$16:$N$27=D198),TRANSPOSE(COLUMN('Current 2023 Points'!$G$16:$N$27)^0)),0))} -> #N/A | K198: =F198-IFERROR(VLOOKUP(D198,'Pre-transfer 2023 Ranking'!$D:$F,3,0),0) -> 248 | L198: =countif('Pre-transfer 2022 Points'!$E$13:$L$21,D198) -> 0 | M198: =countif('2022 Points'!$G$13:$N$21,D198) -> 0
A199: 198 | B199: 327 | C199: ▲129 | D199: Harper Chris | E199: Team Jayco AlUla | F199: 325 | I199: {=INDEX('Current 2023 Points'!$F$16:$F$27,MATCH(1,MMULT(--('Current 2023 Points'!$G$16:$N$27=D199),TRANSPOSE(COLUMN('Current 2023 Points'!$G$16:$N$27)^0)),0))} -> #N/A | K199: =F199-IFERROR(VLOOKUP(D199,'Pre-transfer 2023 Ranking'!$D:$F,3,0),0) -> 251 | L199: =countif('Pre-transfer 2022 Points'!$E$13:$L$21,D199) -> 0 | M199: =countif('2022 Points'!$G$13:$N$21,D199) -> 0
A200: 199 | B200: 101 | C200: ▼98 | D200: Leknessund Andreas | E200: Team dsm - firmenich | F200: 322 | I200: {=INDEX('Current 2023 Points'!$F$16:$F$27,MATCH(1,MMULT(--('Current 2023 Points'!$G$16:$N$27=D200),TRANSPOSE(COLUMN('Current 2023 Points'!$G$16:$N$27)^0)),0))} -> Hipster's Choice | K200: =F200-IFERROR(VLOOKUP(D200,'Pre-transfer 2023 Ranking'!$D:$F,3,0),0) -> 27 | L200: =countif('Pre-transfer 2022 Points'!$E$13:$L$21,D200) -> 0 | M200: =countif('2022 Points'!$G$13:$N$21,D200) -> 0
A201: 200 | B201: 505 | C201: ▲305 | D201: Kielich Timo | E201: Alpecin-Deceuninck Development Team | F201: 321 | I201: {=INDEX('Current 2023 Points'!$F$16:$F$27,MATCH(1,MMULT(--('Current 2023 Points'!$G$16:$N$27=D201),TRANSPOSE(COLUMN('Current 2023 Points'!$G$16:$N$27)^0)),0))} -> #N/A | K201: =F201-IFERROR(VLOOKUP(D201,'Pre-transfer 2023 Ranking'!$D:$F,3,0),0) -> 80 | L201: =countif('Pre-transfer 2022 Points'!$E$13:$L$21,D201) -> 0 | M201: =countif('2022 Points'!$G$13:$N$21,D201) -> 0
A202: 201 | B202: 282 | C202: ▲81 | D202: Sainbayar Jambaljamts | E202: Terengganu Polygon Cycling Team | F202: 319 | I202: {=INDEX('Current 2023 Points'!$F$16:$F$27,MATCH(1,MMULT(--('Current 2023 Points'!$G$16:$N$27=D202),TRANSPOSE(COLUMN('Current 2023 Points'!$G$16:$N$27)^0)),0))} -> #N/A | K202: =F202-IFERROR(VLOOKUP(D202,'Pre-transfer 2023 Ranking'!$D:$F,3,0),0) -> 171 | L202: =countif('Pre-transfer 2022 Points'!$E$13:$L$21,D202) -> 0 | M202: =countif('2022 Points'!$G$13:$N$21,D202) -> 0
A203: 202 | B203: 340 | C203: ▲138 | D203: Askey Lewis | E203: Groupama - FDJ | F203: 319 | I203: {=INDEX('Current 2023 Points'!$F$16:$F$27,MATCH(1,MMULT(--('Current 2023 Points'!$G$16:$N$27=D203),TRANSPOSE(COLUMN('Current 2023 Points'!$G$16:$N$27)^0)),0))} -> #N/A | K203: =F203-IFERROR(VLOOKUP(D203,'Pre-transfer 2023 Ranking'!$D:$F,3,0),0) -> 179 | L203: =countif('Pre-transfer 2022 Points'!$E$13:$L$21,D203) -> 0 | M203: =countif('2022 Points'!$G$13:$N$21,D203) -> 0
A204: 203 | B204: 702 | C204: ▲499 | D204: Howson Damien | E204: Q36.5 Pro Cycling Team | F204: 319 | I204: {=INDEX('Current 2023 Points'!$F$16:$F$27,MATCH(1,MMULT(--('Current 2023 Points'!$G$16:$N$27=D204),TRANSPOSE(COLUMN('Current 2023 Points'!$G$16:$N$27)^0)),0))} -> #N/A | K204: =F204-IFERROR(VLOOKUP(D204,'Pre-transfer 2023 Ranking'!$D:$F,3,0),0) -> 195 | L204: =countif('Pre-transfer 2022 Points'!$E$13:$L$21,D204) -> 0 | M204: =countif('2022 Points'!$G$13:$N$21,D204) -> 0
A205: 204 | B205: 310 | C205: ▲106 | D205: Perez Anthony | E205: Cofidis | F205: 318 | I205: {=INDEX('Current 2023 Points'!$F$16:$F$27,MATCH(1,MMULT(--('Current 2023 Points'!$G$16:$N$27=D205),TRANSPOSE(COLUMN('Current 2023 Points'!$G$16:$N$27)^0)),0))} -> #N/A | K205: =F205-IFERROR(VLOOKUP(D205,'Pre-transfer 2023 Ranking'!$D:$F,3,0),0) -> 38 | L205: =countif('Pre-transfer 2022 Points'!$E$13:$L$21,D205) -> 0 | M205: =countif('2022 Points'!$G$13:$N$21,D205) -> 0
A206: 205 | B206: 59 | C206: ▼146 | D206: Bennett Sam | E206: BORA - hansgrohe | F206: 316 | I206: {=INDEX('Current 2023 Points'!$F$16:$F$27,MATCH(1,MMULT(--('Current 2023 Points'!$G$16:$N$27=D206),TRANSPOSE(COLUMN('Current 2023 Points'!$G$16:$N$27)^0)),0))} -> Campbell | K206: =F206-IFERROR(VLOOKUP(D206,'Pre-transfer 2023 Ranking'!$D:$F,3,0),0) -> 131 | L206: =countif('Pre-transfer 2022 Points'!$E$13:$L$21,D206) -> 1 | M206: =countif('2022 Points'!$G$13:$N$21,D206) -> 1
A207: 206 | B207: 501 | C207: ▲295 | D207: Carr Simon | E207: EF Education-EasyPost | F207: 316 | I207: {=INDEX('Current 2023 Points'!$F$16:$F$27,MATCH(1,MMULT(--('Current 2023 Points'!$G$16:$N$27=D207),TRANSPOSE(COLUMN('Current 2023 Points'!$G$16:$N$27)^0)),0))} -> #N/A | K207: =F207-IFERROR(VLOOKUP(D207,'Pre-transfer 2023 Ranking'!$D:$F,3,0),0) -> 180 | L207: =countif('Pre-transfer 2022 Points'!$E$13:$L$21,D207) -> 0 | M207: =countif('2022 Points'!$G$13:$N$21,D207) -> 0
A208: 207 | B208: 531 | C208: ▲324 | D208: Nys Thibau | E208: Lidl - Trek | F208: 316 | I208: {=INDEX('Current 2023 Points'!$F$16:$F$27,MATCH(1,MMULT(--('Current 2023 Points'!$G$16:$N$27=D208),TRANSPOSE(COLUMN('Current 2023 Points'!$G$16:$N$27)^0)),0))} -> #N/A | K208: =F208-IFERROR(VLOOKUP(D208,'Pre-transfer 2023 Ranking'!$D:$F,3,0),0) -> 25 | L208: =countif('Pre-transfer 2022 Points'!$E$13:$L$21,D208) -> 0 | M208: =countif('2022 Points'!$G$13:$N$21,D208) -> 0
A209: 208 | B209: 209 | C209: ▲1 | D209: Viviani Elia | E209: INEOS Grenadiers | F209: 315 | I209: {=INDEX('Current 2023 Points'!$F$16:$F$27,MATCH(1,MMULT(--('Current 2023 Points'!$G$16:$N$27=D209),TRANSPOSE(COLUMN('Current 2023 Points'!$G$16:$N$27)^0)),0))} -> #N/A | K209: =F209-IFERROR(VLOOKUP(D209,'Pre-transfer 2023 Ranking'!$D:$F,3,0),0) -> 279 | L209: =countif('Pre-transfer 2022 Points'!$E$13:$L$21,D209) -> 0 | M209: =countif('2022 Points'!$G$13:$N$21,D209) -> 0
... A229: 228 | B229: 217 | C229: ▼11 | D229: Ballerini Davide | E229: Soudal - Quick Step | F229: 281 | I229: {=INDEX('Current 2023 Points'!$F$16:$F$27,MATCH(1,MMULT(--('Current 2023 Points'!$G$16:$N$27=D229),TRANSPOSE(COLUMN('Current 2023 Points'!$G$16:$N$27)^0)),0))} -> #N/A | K229: =F229-IFERROR(VLOOKUP(D229,'Pre-transfer 2023 Ranking'!$D:$F,3,0),0) -> 22 | L229: =countif('Pre-transfer 2022 Points'!$E$13:$L$21,D229) -> 0 | M229: =countif('2022 Points'!$G$13:$N$21,D229) -> 0
